Workbook

Sheet ZMRP
A1: Application | B1: Condition Type | C1: Material | D1: Valid to | E1: Valid From | F1: Amount | G1: Unit of measure | H1: ok
A2: V | B2: ZMRP | C2: 1403173 | D2: 2958465 | E2: 44764 | F2: 175 | G2: CAN
A3: V | B3: ZMRP | C3: 1403174 | D3: 2958465 | E3: 44764 | F3: 175 | G3: CAN
A4: V | B4: ZMRP | C4: 1403176 | D4: 2958465 | E4: 44764 | F4: 175 | G4: CAN
A5: V | B5: ZMRP | C5: 1403177 | D5: 2958465 | E5: 44764 | F5: 175 | G5: CAN
A6: V | B6: ZMRP | C6: 1403183 | D6: 2958465 | E6: 44764 | F6: 335 | G6: CAN
A7: V | B7: ZMRP | C7: 1403184 | D7: 2958465 | E7: 44764 | F7: 335 | G7: CAN
A8: V | B8: ZMRP | C8: 1403187 | D8: 2958465 | E8: 44764 | F8: 335 | G8: CAN
A9: V | B9: ZMRP | C9: 1403188 | D9: 2958465 | E9: 44764 | F9: 335 | G9: CAN
A10: V | B10: ZMRP | C10: 1403229 | D10: 2958465 | E10: 44764 | F10: 335 | G10: CAN
A11: V | B11: ZMRP | C11: 1403233 | D11: 2958465 | E11: 44764 | F11: 1650 | G11: CAN
A12: V | B12: ZMRP | C12: 1403234 | D12: 2958465 | E12: 44764 | F12: 1650 | G12: CAN
A13: V | B13: ZMRP | C13: 1403240 | D13: 2958465 | E13: 44764 | F13: 1650 | G13: CAN
... A3564: V | B3564: ZMRP | C3564: 9901906 | D3564: 2958465 | E3564: 44431 | F3564: 105 | G3564: CAN

Sheet ZLAM
A1: Application | B1: Condition Type | C1: Material | D1: Valid to | E1: Valid From | F1: Amount | G1: Unit of measure | H1: oka
A2: V | B2: ZLAM | C2: 1304233 | D2: 2958465 | E2: 42300 | F2: 83.33
A3: V | B3: ZLAM | C3: 1403173 | D3: 2958465 | E3: 44764 | F3: 80.85
A4: V | B4: ZLAM | C4: 1403174 | D4: 2958465 | E4: 44764 | F4: 80.85
A5: V | B5: ZLAM | C5: 1403176 | D5: 2958465 | E5: 44764 | F5: 80.85
A6: V | B6: ZLAM | C6: 1403177 | D6: 2958465 | E6: 44764 | F6: 80.85
A7: V | B7: ZLAM | C7: 1403183 | D7: 2958465 | E7: 44764 | F7: 82.23
A8: V | B8: ZLAM | C8: 1403184 | D8: 2958465 | E8: 44764 | F8: 82.23
A9: V | B9: ZLAM | C9: 1403187 | D9: 2958465 | E9: 44764 | F9: 82.23
A10: V | B10: ZLAM | C10: 1403188 | D10: 2958465 | E10: 44764 | F10: 82.23
A11: V | B11: ZLAM | C11: 1403229 | D11: 2958465 | E11: 44764 | F11: 82.23
A12: V | B12: ZLAM | C12: 1403233 | D12: 2958465 | E12: 44764 | F12: 82.32
A13: V | B13: ZLAM | C13: 1403234 | D13: 2958465 | E13: 44764 | F13: 82.32
... A3596: V | B3596: ZLAM | C3596: 9901906 | D3596: 2958465 | E3596: 44431 | F3596: 80

Sheet ZTRV
A1: Application | B1: Condition Type | C1: Customer group | D1: Material | E1: Valid to | F1: Valid From | G1: Amount | H1: Unit of measure | I1: oka
A2: V | B2: ZTRV | C2: SA | D2: 1301288 | E2: 46022 | F2: 45931 | G2: -8 | H2: L29
A3: V | B3: ZTRV | C3: SA | D3: 1301401 | E3: 46022 | F3: 45931 | G3: -8 | H3: L29
A4: V | B4: ZTRV | C4: SA | D4: 1303401 | E4: 46022 | F4: 45931 | G4: -8 | H4: L29
A5: V | B5: ZTRV | C5: SA | D5: 1304401 | E5: 46022 | F5: 45931 | G5: -8 | H5: L29
A6: V | B6: ZTRV | C6: SA | D6: 1305401 | E6: 46022 | F6: 45931 | G6: -8 | H6: L29
A7: V | B7: ZTRV | C7: SA | D7: 1403401 | E7: 46022 | F7: 45931 | G7: -8 | H7: L29
A8: V | B8: ZTRV | C8: SA | D8: 1404183 | E8: 46022 | F8: 45931 | G8: -8 | H8: L29
A9: V | B9: ZTRV | C9: SA | D9: 1404184 | E9: 46022 | F9: 45931 | G9: -8 | H9: L29
A10: V | B10: ZTRV | C10: SA | D10: 1404233 | E10: 46022 | F10: 45931 | G10: -8 | H10: L29
A11: V | B11: ZTRV | C11: SA | D11: 1404234 | E11: 46022 | F11: 45931 | G11: -8 | H11: L29
A12: V | B12: ZTRV | C12: SA | D12: 1404242 | E12: 46022 | F12: 45931 | G12: -8 | H12: L29
A13: V | B13: ZTRV | C13: SA | D13: 1404265 | E13: 46022 | F13: 45931 | G13: -8 | H13: L29
... A676: V | B676: ZTRV | C676: SA | D676: 7903451 | E676: 46022 | F676: 45931 | G676: -23 | H676: KG

Sheet ZTR1
A1: Application | B1: Condition Type | C1: Customer group | D1: Material | E1: Valid to | F1: Valid From | G1: Amount | H1: Unit of measure | I1: oka
A2: V | B2: ZTR1 | C2: SA | D2: 2825022 | E2: 45961 | F2: 45937 | G2: -200 | H2: L29
A3: V | B3: ZTR1 | C3: SA | D3: 2825023 | E3: 45961 | F3: 45937 | G3: -200 | H3: L29
A4: V | B4: ZTR1 | C4: SA | D4: 2825181 | E4: 45961 | F4: 45937 | G4: -200 | H4: L29
A5: V | B5: ZTR1 | C5: SA | D5: 2825183 | E5: 45961 | F5: 45937 | G5: -200 | H5: L29
A6: V | B6: ZTR1 | C6: SA | D6: 2825185 | E6: 45961 | F6: 45937 | G6: -200 | H6: L29
A7: V | B7: ZTR1 | C7: SA | D7: 2825258 | E7: 45961 | F7: 45937 | G7: -200 | H7: L29

Sheet ZTR2
A1: Application | B1: Condition Type | C1: Customer group | D1: Material | E1: Valid to | F1: Valid From | G1: Amount | H1: Unit of measure | I1: oka

Sheet ZSSD
A1: Application | B1: Condition Type | C1: Customer group | D1: Material | E1: Valid to | F1: Valid From | G1: Amount | H1: Unit of measure | J1: oka | K1: Mate | L1: rial
A2: V | B2: ZSSD | C2: SA | D2: 1408163 | E2: 46112 | F2: 45748 | G2: -4 | H2: L29 | I2: =VLOOKUP(K2,[1]GRADE!$A:$P,16,FALSE) -> SILVER | K2: 1408 | L2: 163
A3: V | B3: ZSSD | C3: SA | D3: 1408164 | E3: 46112 | F3: 45748 | G3: -4 | H3: L29 | I3: =VLOOKUP(K3,[1]GRADE!$A:$P,16,FALSE) -> SILVER | K3: 1408 | L3: 164
A4: V | B4: ZSSD | C4: SA | D4: 1408183 | E4: 46112 | F4: 45748 | G4: -4 | H4: L29 | I4: =VLOOKUP(K4,[1]GRADE!$A:$P,16,FALSE) -> SILVER | K4: 1408 | L4: 183
A5: V | B5: ZSSD | C5: SA | D5: 1408184 | E5: 46112 | F5: 45748 | G5: -4 | H5: L29 | I5: =VLOOKUP(K5,[1]GRADE!$A:$P,16,FALSE) -> SILVER | K5: 1408 | L5: 184
A6: V | B6: ZSSD | C6: SA | D6: 1408243 | E6: 46112 | F6: 45748 | G6: -4 | H6: L29 | I6: =VLOOKUP(K6,[1]GRADE!$A:$P,16,FALSE) -> SILVER | K6: 1408 | L6: 243
A7: V | B7: ZSSD | C7: SA | D7: 1408244 | E7: 46112 | F7: 45748 | G7: -4 | H7: L29 | I7: =VLOOKUP(K7,[1]GRADE!$A:$P,16,FALSE) -> SILVER | K7: 1408 | L7: 244
A8: V | B8: ZSSD | C8: SA | D8: 1412183 | E8: 46112 | F8: 45748 | G8: -4 | H8: L29 | I8: =VLOOKUP(K8,[1]GRADE!$A:$P,16,FALSE) -> SILVER | K8: 1412 | L8: 183
A9: V | B9: ZSSD | C9: SA | D9: 1412184 | E9: 46112 | F9: 45748 | G9: -4 | H9: L29 | I9: =VLOOKUP(K9,[1]GRADE!$A:$P,16,FALSE) -> SILVER | K9: 1412 | L9: 184
A10: V | B10: ZSSD | C10: SA | D10: 1412196 | E10: 46112 | F10: 45748 | G10: -4 | H10: L29 | I10: =VLOOKUP(K10,[1]GRADE!$A:$P,16,FALSE) -> SILVER | K10: 1412 | L10: 196
A11: V | B11: ZSSD | C11: SA | D11: 1412197 | E11: 46112 | F11: 45748 | G11: -4 | H11: L29 | I11: =VLOOKUP(K11,[1]GRADE!$A:$P,16,FALSE) -> SILVER | K11: 1412 | L11: 197
A12: V | B12: ZSSD | C12: SA | D12: 1412233 | E12: 46112 | F12: 45748 | G12: -4 | H12: L29 | I12: =VLOOKUP(K12,[1]GRADE!$A:$P,16,FALSE) -> SILVER | K12: 1412 | L12: 233
A13: V | B13: ZSSD | C13: SA | D13: 1412234 | E13: 46112 | F13: 45748 | G13: -4 | H13: L29 | I13: =VLOOKUP(K13,[1]GRADE!$A:$P,16,FALSE) -> SILVER | K13: 1412 | L13: 234
... A30: V | B30: ZSSD | C30: SA | D30: 1415295 | E30: 46112 | F30: 45748 | G30: -4 | H30: L29 | I30: =VLOOKUP(K30,[1]GRADE!$A:$P,16,FALSE) -> SILVER | K30: 1415 | L30: 295
A31: V | B31: ZSSD | C31: SA | D31: 2050180 | E31: 46112 | F31: 45748 | G31: -8 | I31: =VLOOKUP(K31,[1]GRADE!$A:$P,16,FALSE) -> Gold | K31: 2050 | L31: 180
A32: V | B32: ZSSD | C32: SA | D32: 2050221 | E32: 46112 | F32: 45748 | G32: -8 | I32: =VLOOKUP(K32,[1]GRADE!$A:$P,16,FALSE) -> Gold | K32: 2050 | L32: 221
A33: V | B33: ZSSD | C33: SA | D33: 2050223 | E33: 46112 | F33: 45748 | G33: -8 | I33: =VLOOKUP(K33,[1]GRADE!$A:$P,16,FALSE) -> Gold | K33: 2050 | L33: 223
A34: V | B34: ZSSD | C34: SA | D34: 2051180 | E34: 46112 | F34: 45748 | G34: -8 | I34: =VLOOKUP(K34,[1]GRADE!$A:$P,16,FALSE) -> Gold | K34: 2051 | L34: 180
A35: V | B35: ZSSD | C35: SA | D35: 2051221 | E35: 46112 | F35: 45748 | G35: -8 | I35: =VLOOKUP(K35,[1]GRADE!$A:$P,16,FALSE) -> Gold | K35: 2051 | L35: 221
A36: V | B36: ZSSD | C36: SA | D36: 2051223 | E36: 46112 | F36: 45748 | G36: -8 | I36: =VLOOKUP(K36,[1]GRADE!$A:$P,16,FALSE) -> Gold | K36: 2051 | L36: 223
A37: V | B37: ZSSD | C37: SA | D37: 2485254 | E37: 46112 | F37: 45748 | G37: -4 | H37: L29 | I37: =VLOOKUP(K37,[1]GRADE!$A:$P,16,FALSE) -> SILVER | K37: 2485 | L37: 254
A38: V | B38: ZSSD | C38: SA | D38: 2486089 | E38: 46112 | F38: 45748 | G38: -4 | H38: L29 | I38: =VLOOKUP(K38,[1]GRADE!$A:$P,16,FALSE) -> SILVER | K38: 2486 | L38: 89
A39: V | B39: ZSSD | C39: SA | D39: 2486163 | E39: 46112 | F39: 45748 | G39: -4 | H39: L29 | I39: =VLOOKUP(K39,[1]GRADE!$A:$P,16,FALSE) -> SILVER | K39: 2486 | L39: 163
A40: V | B40: ZSSD | C40: SA | D40: 2486164 | E40: 46112 | F40: 45748 | G40: -4 | H40: L29 | I40: =VLOOKUP(K40,[1]GRADE!$A:$P,16,FALSE) -> SILVER | K40: 2486 | L40: 164
A41: V | B41: ZSSD | C41: SA | D41: 2486183 | E41: 46112 | F41: 45748 | G41: -4 | H41: L29 | I41: =VLOOKUP(K41,[1]GRADE!$A:$P,16,FALSE) -> SILVER | K41: 2486 | L41: 183
A42: V | B42: ZSSD | C42: SA | D42: 2486184 | E42: 46112 | F42: 45748 | G42: -4 | H42: L29 | I42: =VLOOKUP(K42,[1]GRADE!$A:$P,16,FALSE) -> SILVER | K42: 2486 | L42: 184
A43: V | B43: ZSSD | C43: SA | D43: 2486189 | E43: 46112 | F43: 45748 | G43: -4 | H43: L29 | I43: =VLOOKUP(K43,[1]GRADE!$A:$P,16,FALSE) -> SILVER | K43: 2486 | L43: 189
A44: V | B44: ZSSD | C44: SA | D44: 2486190 | E44: 46112 | F44: 45748 | G44: -4 | H44: L29 | I44: =VLOOKUP(K44,[1]GRADE!$A:$P,16,FALSE) -> SILVER | K44: 2486 | L44: 190
A45: V | B45: ZSSD | C45: SA | D45: 2510193 | E45: 46112 | F45: 45748 | G45: -5.5 | I45: =VLOOKUP(K45,[1]GRADE!$A:$P,16,FALSE) -> BRONZE | K45: 2510 | L45: 193
A46: V | B46: ZSSD | C46: SA | D46: 2510195 | E46: 46112 | F46: 45748 | G46: -5.5 | I46: =VLOOKUP(K46,[1]GRADE!$A:$P,16,FALSE) -> BRONZE | K46: 2510 | L46: 195
A47: V | B47: ZSSD | C47: SA | D47: 2518183 | E47: 46112 | F47: 45748 | G47: -5.5 | I47: =VLOOKUP(K47,[1]GRADE!$A:$P,16,FALSE) -> SILVER | K47: 2518 | L47: 183
A48: V | B48: ZSSD | C48: SA | D48: 2518184 | E48: 46112 | F48: 45748 | G48: -5.5 | I48: =VLOOKUP(K48,[1]GRADE!$A:$P,16,FALSE) -> SILVER | K48: 2518 | L48: 184
A49: V | B49: ZSSD | C49: SA | D49: 2518251 | E49: 46112 | F49: 45748 | G49: -5.5 | I49: =VLOOKUP(K49,[1]GRADE!$A:$P,16,FALSE) -> SILVER | K49: 2518 | L49: 251
A50: V | B50: ZSSD | C50: SA | D50: 2519183 | E50: 46112 | F50: 45748 | G50: -5.5 | I50: =VLOOKUP(K50,[1]GRADE!$A:$P,16,FALSE) -> SILVER | K50: 2519 | L50: 183
A51: V | B51: ZSSD | C51: SA | D51: 2519184 | E51: 46112 | F51: 45748 | G51: -5.5 | I51: =VLOOKUP(K51,[1]GRADE!$A:$P,16,FALSE) -> SILVER | K51: 2519 | L51: 184
A52: V | B52: ZSSD | C52: SA | D52: 2519187 | E52: 46112 | F52: 45748 | G52: -5.5 | I52: =VLOOKUP(K52,[1]GRADE!$A:$P,16,FALSE) -> SILVER | K52: 2519 | L52: 187
A53: V | B53: ZSSD | C53: SA | D53: 2519188 | E53: 46112 | F53: 45748 | G53: -5.5 | I53: =VLOOKUP(K53,[1]GRADE!$A:$P,16,FALSE) -> SILVER | K53: 2519 | L53: 188
A54: V | B54: ZSSD | C54: SA | D54: 2519242 | E54: 46112 | F54: 45748 | G54: -5.5 | I54: =VLOOKUP(K54,[1]GRADE!$A:$P,16,FALSE) -> SILVER | K54: 2519 | L54: 242
A55: V | B55: ZSSD | C55: SA | D55: 2527163 | E55: 46112 | F55: 45748 | G55: -4 | H55: L29 | I55: =VLOOKUP(K55,[1]GRADE!$A:$P,16,FALSE) -> SILVER | K55: 2527 | L55: 163
A56: V | B56: ZSSD | C56: SA | D56: 2527164 | E56: 46112 | F56: 45748 | G56: -4 | H56: L29 | I56: =VLOOKUP(K56,[1]GRADE!$A:$P,16,FALSE) -> SILVER | K56: 2527 | L56: 164
A57: V | B57: ZSSD | C57: SA | D57: 2527184 | E57: 46112 | F57: 45748 | G57: -4 | H57: L29 | I57: =VLOOKUP(K57,[1]GRADE!$A:$P,16,FALSE) -> SILVER | K57: 2527 | L57: 184
A58: V | B58: ZSSD | C58: SA | D58: 2527196 | E58: 46112 | F58: 45748 | G58: -4 | H58: L29 | I58: =VLOOKUP(K58,[1]GRADE!$A:$P,16,FALSE) -> SILVER | K58: 2527 | L58: 196
A59: V | B59: ZSSD | C59: SA | D59: 2527197 | E59: 46112 | F59: 45748 | G59: -4 | H59: L29 | I59: =VLOOKUP(K59,[1]GRADE!$A:$P,16,FALSE) -> SILVER | K59: 2527 | L59: 197
A60: V | B60: ZSSD | C60: SA | D60: 2528183 | E60: 46112 | F60: 45748 | G60: -5.5 | I60: =VLOOKUP(K60,[1]GRADE!$A:$P,16,FALSE) -> SILVER | K60: 2528 | L60: 183
A61: V | B61: ZSSD | C61: SA | D61: 2528184 | E61: 46112 | F61: 45748 | G61: -5.5 | I61: =VLOOKUP(K61,[1]GRADE!$A:$P,16,FALSE) -> SILVER | K61: 2528 | L61: 184
A62: V | B62: ZSSD | C62: SA | D62: 2528242 | E62: 46112 | F62: 45748 | G62: -5.5 | I62: =VLOOKUP(K62,[1]GRADE!$A:$P,16,FALSE) -> SILVER | K62: 2528 | L62: 242
A63: V | B63: ZSSD | C63: SA | D63: 2528256 | E63: 46112 | F63: 45748 | G63: -5.5 | I63: =VLOOKUP(K63,[1]GRADE!$A:$P,16,FALSE) -> SILVER | K63: 2528 | L63: 256
A64: V | B64: ZSSD | C64: SA | D64: 2537196 | E64: 46112 | F64: 45748 | G64: -4 | H64: L29 | I64: =VLOOKUP(K64,[1]GRADE!$A:$P,16,FALSE) -> SILVER | K64: 2537 | L64: 196
A65: V | B65: ZSSD | C65: SA | D65: 2537197 | E65: 46112 | F65: 45748 | G65: -4 | H65: L29 | I65: =VLOOKUP(K65,[1]GRADE!$A:$P,16,FALSE) -> SILVER | K65: 2537 | L65: 197
A66: V | B66: ZSSD | C66: SA | D66: 2540183 | E66: 46112 | F66: 45748 | G66: -5.5 | I66: =VLOOKUP(K66,[1]GRADE!$A:$P,16,FALSE) -> BRONZE | K66: 2540 | L66: 183
A67: V | B67: ZSSD | C67: SA | D67: 2540184 | E67: 46112 | F67: 45748 | G67: -5.5 | I67: =VLOOKUP(K67,[1]GRADE!$A:$P,16,FALSE) -> BRONZE | K67: 2540 | L67: 184
A68: V | B68: ZSSD | C68: SA | D68: 2540198 | E68: 46112 | F68: 45748 | G68: -5.5 | I68: =VLOOKUP(K68,[1]GRADE!$A:$P,16,FALSE) -> BRONZE | K68: 2540 | L68: 198
A69: V | B69: ZSSD | C69: SA | D69: 2540199 | E69: 46112 | F69: 45748 | G69: -5.5 | I69: =VLOOKUP(K69,[1]GRADE!$A:$P,16,FALSE) -> BRONZE | K69: 2540 | L69: 199
A70: V | B70: ZSSD | C70: SA | D70: 2545189 | E70: 46112 | F70: 45748 | G70: -4 | H70: L29 | I70: =VLOOKUP(K70,[1]GRADE!$A:$P,16,FALSE) -> SILVER | K70: 2545 | L70: 189
A71: V | B71: ZSSD | C71: SA | D71: 2545190 | E71: 46112 | F71: 45748 | G71: -4 | H71: L29 | I71: =VLOOKUP(K71,[1]GRADE!$A:$P,16,FALSE) -> SILVER | K71: 2545 | L71: 190
A72: V | B72: ZSSD | C72: SA | D72: 2554163 | E72: 46112 | F72: 45748 | G72: -4 | H72: L29 | I72: =VLOOKUP(K72,[1]GRADE!$A:$P,16,FALSE) -> SILVER | K72: 2554 | L72: 163
A73: V | B73: ZSSD | C73: SA | D73: 2554164 | E73: 46112 | F73: 45748 | G73: -4 | H73: L29 | I73: =VLOOKUP(K73,[1]GRADE!$A:$P,16,FALSE) -> SILVER | K73: 2554 | L73: 164
A74: V | B74: ZSSD | C74: SA | D74: 2554183 | E74: 46112 | F74: 45748 | G74: -4 | H74: L29 | I74: =VLOOKUP(K74,[1]GRADE!$A:$P,16,FALSE) -> SILVER | K74: 2554 | L74: 183
A75: V | B75: ZSSD | C75: SA | D75: 2554184 | E75: 46112 | F75: 45748 | G75: -4 | H75: L29 | I75: =VLOOKUP(K75,[1]GRADE!$A:$P,16,FALSE) -> SILVER | K75: 2554 | L75: 184
A76: V | B76: ZSSD | C76: SA | D76: 2554196 | E76: 46112 | F76: 45748 | G76: -4 | H76: L29 | I76: =VLOOKUP(K76,[1]GRADE!$A:$P,16,FALSE) -> SILVER | K76: 2554 | L76: 196
A77: V | B77: ZSSD | C77: SA | D77: 2554197 | E77: 46112 | F77: 45748 | G77: -4 | H77: L29 | I77: =VLOOKUP(K77,[1]GRADE!$A:$P,16,FALSE) -> SILVER | K77: 2554 | L77: 197
A78: V | B78: ZSSD | C78: SA | D78: 2557193 | E78: 46112 | F78: 45748 | G78: -5.5 | I78: =VLOOKUP(K78,[1]GRADE!$A:$P,16,FALSE) -> BRONZE | K78: 2557 | L78: 193
A79: V | B79: ZSSD | C79: SA | D79: 2557195 | E79: 46112 | F79: 45748 | G79: -5.5 | I79: =VLOOKUP(K79,[1]GRADE!$A:$P,16,FALSE) -> BRONZE | K79: 2557 | L79: 195
A80: V | B80: ZSSD | C80: SA | D80: 2560163 | E80: 46112 | F80: 45748 | G80: -4 | H80: L29 | I80: =VLOOKUP(K80,[1]GRADE!$A:$P,16,FALSE) -> SILVER | K80: 2560 | L80: 163
A81: V | B81: ZSSD | C81: SA | D81: 2560164 | E81: 46112 | F81: 45748 | G81: -4 | H81: L29 | I81: =VLOOKUP(K81,[1]GRADE!$A:$P,16,FALSE) -> SILVER | K81: 2560 | L81: 164
A82: V | B82: ZSSD | C82: SA | D82: 2560183 | E82: 46112 | F82: 45748 | G82: -4 | H82: L29 | I82: =VLOOKUP(K82,[1]GRADE!$A:$P,16,FALSE) -> SILVER | K82: 2560 | L82: 183
A83: V | B83: ZSSD | C83: SA | D83: 2560184 | E83: 46112 | F83: 45748 | G83: -4 | H83: L29 | I83: =VLOOKUP(K83,[1]GRADE!$A:$P,16,FALSE) -> SILVER | K83: 2560 | L83: 184
A84: V | B84: ZSSD | C84: SA | D84: 2560196 | E84: 46112 | F84: 45748 | G84: -4 | H84: L29 | I84: =VLOOKUP(K84,[1]GRADE!$A:$P,16,FALSE) -> SILVER | K84: 2560 | L84: 196
A85: V | B85: ZSSD | C85: SA | D85: 2560197 | E85: 46112 | F85: 45748 | G85: -4 | H85: L29 | I85: =VLOOKUP(K85,[1]GRADE!$A:$P,16,FALSE) -> SILVER | K85: 2560 | L85: 197
A86: V | B86: ZSSD | C86: SA | D86: 2586183 | E86: 46112 | F86: 45748 | G86: -10 | H86: L29 | I86: =VLOOKUP(K86,[1]GRADE!$A:$P,16,FALSE) -> BRONZE | K86: 2586 | L86: 183
A87: V | B87: ZSSD | C87: SA | D87: 2586184 | E87: 46112 | F87: 45748 | G87: -10 | H87: L29 | I87: =VLOOKUP(K87,[1]GRADE!$A:$P,16,FALSE) -> BRONZE | K87: 2586 | L87: 184
A88: V | B88: ZSSD | C88: SA | D88: 2588205 | E88: 46112 | F88: 45748 | G88: -10 | H88: L29 | I88: =VLOOKUP(K88,[1]GRADE!$A:$P,16,FALSE) -> BRONZE | K88: 2588 | L88: 205
A89: V | B89: ZSSD | C89: SA | D89: 2589185 | E89: 46112 | F89: 45748 | G89: -8 | I89: =VLOOKUP(K89,[1]GRADE!$A:$P,16,FALSE) -> GOLD | K89: 2589 | L89: 185
A90: V | B90: ZSSD | C90: SA | D90: 2590185 | E90: 46112 | F90: 45748 | G90: -8 | I90: =VLOOKUP(K90,[1]GRADE!$A:$P,16,FALSE) -> GOLD | K90: 2590 | L90: 185
A91: V | B91: ZSSD | C91: SA | D91: 2824151 | E91: 46112 | F91: 45748 | G91: -7 | I91: =VLOOKUP(K91,[1]GRADE!$A:$P,16,FALSE) -> GREEN | K91: 2824 | L91: 151
A92: V | B92: ZSSD | C92: SA | D92: 2824152 | E92: 46112 | F92: 45748 | G92: -7 | I92: =VLOOKUP(K92,[1]GRADE!$A:$P,16,FALSE) -> GREEN | K92: 2824 | L92: 152
A93: V | B93: ZSSD | C93: SA | D93: 2824183 | E93: 46112 | F93: 45748 | G93: -7 | I93: =VLOOKUP(K93,[1]GRADE!$A:$P,16,FALSE) -> GREEN | K93: 2824 | L93: 183
A94: V | B94: ZSSD | C94: SA | D94: 2824184 | E94: 46112 | F94: 45748 | G94: -7 | I94: =VLOOKUP(K94,[1]GRADE!$A:$P,16,FALSE) -> GREEN | K94: 2824 | L94: 184
A95: V | B95: ZSSD | C95: SA | D95: 2825022 | E95: 46112 | F95: 45748 | G95: -8 | I95: =VLOOKUP(K95,[1]GRADE!$A:$P,16,FALSE) -> Gold | K95: 2825 | L95: 22
A96: V | B96: ZSSD | C96: SA | D96: 2825023 | E96: 46112 | F96: 45748 | G96: -8 | I96: =VLOOKUP(K96,[1]GRADE!$A:$P,16,FALSE) -> Gold | K96: 2825 | L96: 23
A97: V | B97: ZSSD | C97: SA | D97: 2825024 | E97: 46112 | F97: 45748 | G97: -8 | I97: =VLOOKUP(K97,[1]GRADE!$A:$P,16,FALSE) -> Gold | K97: 2825 | L97: 24
A98: V | B98: ZSSD | C98: SA | D98: 2825181 | E98: 46112 | F98: 45748 | G98: -8 | I98: =VLOOKUP(K98,[1]GRADE!$A:$P,16,FALSE) -> Gold | K98: 2825 | L98: 181
A99: V | B99: ZSSD | C99: SA | D99: 2825183 | E99: 46112 | F99: 45748 | G99: -8 | I99: =VLOOKUP(K99,[1]GRADE!$A:$P,16,FALSE) -> Gold | K99: 2825 | L99: 183
A100: V | B100: ZSSD | C100: SA | D100: 2825185 | E100: 46112 | F100: 45748 | G100: -8 | I100: =VLOOKUP(K100,[1]GRADE!$A:$P,16,FALSE) -> Gold | K100: 2825 | L100: 185
... A128: V | B128: ZSSD | C128: SA | D128: 2830230 | E128: 46112 | F128: 45748 | G128: -8 | I128: =VLOOKUP(K128,[1]GRADE!$A:$P,16,FALSE) -> Gold | K128: 2830 | L128: 230
A129: V | B129: ZSSD | C129: SA | D129: 2874151 | E129: 46112 | F129: 45810 | G129: -6 | H129: L29 | I129: =VLOOKUP(K129,[1]GRADE!$A:$P,16,FALSE) -> SPECIAL | K129: 2874 | L129: 151
A130: V | B130: ZSSD | C130: SA | D130: 2874152 | E130: 46112 | F130: 45810 | G130: -6 | H130: L29 | I130: =VLOOKUP(K130,[1]GRADE!$A:$P,16,FALSE) -> SPECIAL | K130: 2874 | L130: 152
A131: V | B131: ZSSD | C131: SA | D131: 2874183 | E131: 46112 | F131: 45810 | G131: -6 | H131: L29 | I131: =VLOOKUP(K131,[1]GRADE!$A:$P,16,FALSE) -> SPECIAL | K131: 2874 | L131: 183
A132: V | B132: ZSSD | C132: SA | D132: 2874184 | E132: 46112 | F132: 45810 | G132: -6 | H132: L29 | I132: =VLOOKUP(K132,[1]GRADE!$A:$P,16,FALSE) -> SPECIAL | K132: 2874 | L132: 184
A133: V | B133: ZSSD | C133: SA | D133: 2909163 | E133: 46112 | F133: 45772 | G133: -8 | I133: =VLOOKUP(K133,[1]GRADE!$A:$P,16,FALSE) -> Gold | K133: 2909 | L133: 163
A134: V | B134: ZSSD | C134: SA | D134: 2909165 | E134: 46112 | F134: 45772 | G134: -8 | I134: =VLOOKUP(K134,[1]GRADE!$A:$P,16,FALSE) -> Gold | K134: 2909 | L134: 165
A135: V | B135: ZSSD | C135: SA | D135: 2909173 | E135: 46112 | F135: 45772 | G135: -8 | I135: =VLOOKUP(K135,[1]GRADE!$A:$P,16,FALSE) -> Gold | K135: 2909 | L135: 173
A136: V | B136: ZSSD | C136: SA | D136: 2909175 | E136: 46112 | F136: 45772 | G136: -8 | I136: =VLOOKUP(K136,[1]GRADE!$A:$P,16,FALSE) -> Gold | K136: 2909 | L136: 175
A137: V | B137: ZSSD | C137: SA | D137: 2914163 | E137: 46112 | F137: 45748 | G137: -8 | I137: =VLOOKUP(K137,[1]GRADE!$A:$P,16,FALSE) -> Gold | K137: 2914 | L137: 163
A138: V | B138: ZSSD | C138: SA | D138: 2914165 | E138: 46112 | F138: 45748 | G138: -8 | I138: =VLOOKUP(K138,[1]GRADE!$A:$P,16,FALSE) -> Gold | K138: 2914 | L138: 165
A139: V | B139: ZSSD | C139: SA | D139: 2914173 | E139: 46112 | F139: 45748 | G139: -8 | I139: =VLOOKUP(K139,[1]GRADE!$A:$P,16,FALSE) -> Gold | K139: 2914 | L139: 173
A140: V | B140: ZSSD | C140: SA | D140: 2914175 | E140: 46112 | F140: 45748 | G140: -8 | I140: =VLOOKUP(K140,[1]GRADE!$A:$P,16,FALSE) -> Gold | K140: 2914 | L140: 175
A141: V | B141: ZSSD | C141: SA | D141: 2918163 | E141: 46112 | F141: 45748 | G141: -5.5 | I141: =VLOOKUP(K141,[1]GRADE!$A:$P,16,FALSE) -> BRONZE | K141: 2918 | L141: 163
A142: V | B142: ZSSD | C142: SA | D142: 2918164 | E142: 46112 | F142: 45748 | G142: -5.5 | I142: =VLOOKUP(K142,[1]GRADE!$A:$P,16,FALSE) -> BRONZE | K142: 2918 | L142: 164
A143: V | B143: ZSSD | C143: SA | D143: 2918165 | E143: 46112 | F143: 45748 | G143: -5.5 | I143: =VLOOKUP(K143,[1]GRADE!$A:$P,16,FALSE) -> BRONZE | K143: 2918 | L143: 165
...

Sheet ZCON
A1: Application | B1: Condition Type | C1: Customer group | D1: Material | E1: Valid to | F1: Valid From | G1: Amount | H1: Unit of measure | I1: oka
A2: V | B2: ZCON | C2: SA | D2: 1000401 | E2: 46112 | F2: 45748 | G2: -6
A3: V | B3: ZCON | C3: SA | D3: 1407401 | E3: 46112 | F3: 45748 | G3: -4 | H3: L29
A4: V | B4: ZCON | C4: SA | D4: 1408401 | E4: 46112 | F4: 45748 | G4: -4 | H4: L29
A5: V | B5: ZCON | C5: SA | D5: 1412401 | E5: 46112 | F5: 45748 | G5: -4 | H5: L29
A6: V | B6: ZCON | C6: SA | D6: 1414401 | E6: 46112 | F6: 45748 | G6: -4 | H6: L29
A7: V | B7: ZCON | C7: SA | D7: 1415401 | E7: 46112 | F7: 45748 | G7: -4 | H7: L29
A8: V | B8: ZCON | C8: SA | D8: 1418401 | E8: 46112 | F8: 45748 | G8: -4 | H8: L29
A9: V | B9: ZCON | C9: SA | D9: 1507401 | E9: 46112 | F9: 45748 | G9: -6
A10: V | B10: ZCON | C10: SA | D10: 1513401 | E10: 46112 | F10: 45748 | G10: -6
A11: V | B11: ZCON | C11: SA | D11: 1514401 | E11: 46112 | F11: 45748 | G11: -6
A12: V | B12: ZCON | C12: SA | D12: 1515401 | E12: 46112 | F12: 45748 | G12: -6
A13: V | B13: ZCON | C13: SA | D13: 1516401 | E13: 46112 | F13: 45748 | G13: -6
A14: V | B14: ZCON | C14: SA | D14: 1517401 | E14: 46112 | F14: 45748 | G14: -6
A15: V | B15: ZCON | C15: SA | D15: 2476401 | E15: 46112 | F15: 45748 | G15: -4 | H15: L29
A16: V | B16: ZCON | C16: SA | D16: 2484401 | E16: 46112 | F16: 45748 | G16: -4 | H16: L29
A17: V | B17: ZCON | C17: SA | D17: 2485401 | E17: 46112 | F17: 45748 | G17: -4 | H17: L29
A18: V | B18: ZCON | C18: SA | D18: 2486401 | E18: 46112 | F18: 45748 | G18: -4 | H18: L29
A19: V | B19: ZCON | C19: SA | D19: 2510401 | E19: 46112 | F19: 45748 | G19: -5.5
A20: V | B20: ZCON | C20: SA | D20: 2518401 | E20: 46112 | F20: 45748 | G20: -5.5
A21: V | B21: ZCON | C21: SA | D21: 2519401 | E21: 46112 | F21: 45748 | G21: -5.5
A22: V | B22: ZCON | C22: SA | D22: 2525401 | E22: 46112 | F22: 45748 | G22: -4 | H22: L29
A23: V | B23: ZCON | C23: SA | D23: 2527401 | E23: 46112 | F23: 45748 | G23: -4 | H23: L29
A24: V | B24: ZCON | C24: SA | D24: 2528401 | E24: 46112 | F24: 45748 | G24: -5.5
A25: V | B25: ZCON | C25: SA | D25: 2540401 | E25: 46112 | F25: 45748 | G25: -5.5
A26: V | B26: ZCON | C26: SA | D26: 2545401 | E26: 46112 | F26: 45748 | G26: -4 | H26: L29
A27: V | B27: ZCON | C27: SA | D27: 2546401 | E27: 46112 | F27: 45748 | G27: -4 | H27: L29
A28: V | B28: ZCON | C28: SA | D28: 2548401 | E28: 46112 | F28: 45748 | G28: -5.5
A29: V | B29: ZCON | C29: SA | D29: 2549401 | E29: 46112 | F29: 45748 | G29: -5.5
A30: V | B30: ZCON | C30: SA | D30: 2554401 | E30: 46112 | F30: 45748 | G30: -4 | H30: L29
A31: V | B31: ZCON | C31: SA | D31: 2557401 | E31: 46112 | F31: 45748 | G31: -5.5
A32: V | B32: ZCON | C32: SA | D32: 2560401 | E32: 46112 | F32: 45748 | G32: -4 | H32: L29
A33: V | B33: ZCON | C33: SA | D33: 2577401 | E33: 46112 | F33: 45748 | G33: -5.5
A34: V | B34: ZCON | C34: SA | D34: 2704401 | E34: 46112 | F34: 45748 | G34: -6
A35: V | B35: ZCON | C35: SA | D35: 2705401 | E35: 46112 | F35: 45748 | G35: -6
A36: V | B36: ZCON | C36: SA | D36: 2706401 | E36: 46112 | F36: 45748 | G36: -6
A37: V | B37: ZCON | C37: SA | D37: 2824401 | E37: 46112 | F37: 45748 | G37: -7
A38: V | B38: ZCON | C38: SA | D38: 2828401 | E38: 46112 | F38: 45748 | G38: -8
A39: V | B39: ZCON | C39: SA | D39: 2829401 | E39: 46112 | F39: 45748 | G39: -8
A40: V | B40: ZCON | C40: SA | D40: 2909401 | E40: 46112 | F40: 45772 | G40: -8
A41: V | B41: ZCON | C41: SA | D41: 2914401 | E41: 46112 | F41: 45748 | G41: -8
A42: V | B42: ZCON | C42: SA | D42: 2918401 | E42: 46112 | F42: 45748 | G42: -5.5
A43: V | B43: ZCON | C43: SA | D43: 2927401 | E43: 46112 | F43: 45748 | G43: -5.5
A44: V | B44: ZCON | C44: SA | D44: 2929401 | E44: 46112 | F44: 45748 | G44: -5.5
... A99: V | B99: ZCON | C99: SA | D99: 3055401 | E99: 46112 | F99: 45748 | G99: -6
A100: V | B100: ZCON | C100: SA | D100: 3060271 | E100: 46112 | F100: 45748 | G100: -4 | H100: L29
A101: V | B101: ZCON | C101: SA | D101: 3062401 | E101: 46112 | F101: 45748 | G101: -6
A102: V | B102: ZCON | C102: SA | D102: 3064271 | E102: 46112 | F102: 45748 | G102: -6
A103: V | B103: ZCON | C103: SA | D103: 3064288 | E103: 46112 | F103: 45748 | G103: -6
A104: V | B104: ZCON | C104: SA | D104: 3064401 | E104: 46112 | F104: 45748 | G104: -6
A105: V | B105: ZCON | C105: SA | D105: 3065401 | E105: 46112 | F105: 45748 | G105: -6
A106: V | B106: ZCON | C106: SA | D106: 3066401 | E106: 46112 | F106: 45748 | G106: -6
A107: V | B107: ZCON | C107: SA | D107: 3069401 | E107: 46112 | F107: 45748 | G107: -6
A108: V | B108: ZCON | C108: SA | D108: 3070401 | E108: 46112 | F108: 45748 | G108: -6
A109: V | B109: ZCON | C109: SA | D109: 3071401 | E109: 46112 | F109: 45748 | G109: -6
A110: V | B110: ZCON | C110: SA | D110: 3077401 | E110: 46112 | F110: 45748 | G110: -4 | H110: L29
A111: V | B111: ZCON | C111: SA | D111: 3078401 | E111: 46112 | F111: 45748 | G111: -6
A112: V | B112: ZCON | C112: SA | D112: 3079401 | E112: 46112 | F112: 45748 | G112: -6
A113: V | B113: ZCON | C113: SA | D113: 3080401 | E113: 46112 | F113: 45748 | G113: -6
A114: V | B114: ZCON | C114: SA | D114: 3081401 | E114: 46112 | F114: 45748 | G114: -6
A115: V | B115: ZCON | C115: SA | D115: 3081403 | E115: 46112 | F115: 45748 | G115: -6
A116: V | B116: ZCON | C116: SA | D116: 3081405 | E116: 46112 | F116: 45748 | G116: -6
A117: V | B117: ZCON | C117: SA | D117: 3082288 | E117: 46112 | F117: 45748 | G117: -6
A118: V | B118: ZCON | C118: SA | D118: 3082401 | E118: 46112 | F118: 45748 | G118: -6
A119: V | B119: ZCON | C119: SA | D119: 3082403 | E119: 46112 | F119: 45748 | G119: -6
A120: V | B120: ZCON | C120: SA | D120: 3083401 | E120: 46112 | F120: 45748 | G120: -6
A121: V | B121: ZCON | C121: SA | D121: 3084271 | E121: 46112 | F121: 45748 | G121: -6
A122: V | B122: ZCON | C122: SA | D122: 3084288 | E122: 46112 | F122: 45748 | G122: -6
... A510: V | B510: ZCON | C510: SA | D510: 4911401 | E510: 46112 | F510: 45748 | G510: -5.5
A511: V | B511: ZCON | C511: SA | D511: 4929401 | E511: 46112 | F511: 45748 | G511: -4 | H511: L29
A512: V | B512: ZCON | C512: SA | D512: 4940401 | E512: 46112 | F512: 45748 | G512: -6
A513: V | B513: ZCON | C513: SA | D513: 4943401 | E513: 46112 | F513: 45748 | G513: -5.5
A514: V | B514: ZCON | C514: SA | D514: 4948401 | E514: 46112 | F514: 45748 | G514: -6
A515: V | B515: ZCON | C515: SA | D515: 4956401 | E515: 46112 | F515: 45748 | G515: -4 | H515: L29
A516: V | B516: ZCON | C516: SA | D516: 4963401 | E516: 46112 | F516: 45748 | G516: -6
A517: V | B517: ZCON | C517: SA | D517: 5001401 | E517: 46112 | F517: 45748 | G517: -6
A518: V | B518: ZCON | C518: SA | D518: 5002401 | E518: 46112 | F518: 45748 | G518: -6
A519: V | B519: ZCON | C519: SA | D519: 5003401 | E519: 46112 | F519: 45748 | G519: -6
A520: V | B520: ZCON | C520: SA | D520: 5004401 | E520: 46112 | F520: 45748 | G520: -6
A521: V | B521: ZCON | C521: SA | D521: 5005401 | E521: 46112 | F521: 45748 | G521: -6
A522: V | B522: ZCON | C522: SA | D522: 5010401 | E522: 46112 | F522: 45748 | G522: -6
A523: V | B523: ZCON | C523: SA | D523: 5013401 | E523: 46112 | F523: 45748 | G523: -6
A524: V | B524: ZCON | C524: SA | D524: 5015401 | E524: 46112 | F524: 45748 | G524: -6
A525: V | B525: ZCON | C525: SA | D525: 5016401 | E525: 46112 | F525: 45748 | G525: -6
A526: V | B526: ZCON | C526: SA | D526: 5020401 | E526: 46112 | F526: 45748 | G526: -6
A527: V | B527: ZCON | C527: SA | D527: 5023401 | E527: 46112 | F527: 45748 | G527: -6
... A628: V | B628: ZCON | C628: SA | D628: 7209401 | E628: 46112 | F628: 45748 | G628: -5.5
A629: V | B629: ZCON | C629: SA | D629: 7264401 | E629: 46112 | F629: 45748 | G629: -10 | H629: L29
A630: V | B630: ZCON | C630: SA | D630: 7264403 | E630: 46112 | F630: 45771 | G630: -10 | H630: L29
A631: V | B631: ZCON | C631: SA | D631: 7265401 | E631: 46112 | F631: 45748 | G631: -10 | H631: L29
A632: V | B632: ZCON | C632: SA | D632: 7265403 | E632: 46112 | F632: 45771 | G632: -10 | H632: L29
A633: V | B633: ZCON | C633: SA | D633: 7266403 | E633: 46112 | F633: 45748 | G633: -6
A634: V | B634: ZCON | C634: SA | D634: 7267401 | E634: 46112 | F634: 45748 | G634: -10 | H634: L29
A635: V | B635: ZCON | C635: SA | D635: 7269401 | E635: 46112 | F635: 45748 | G635: -4 | H635: L29
A636: V | B636: ZCON | C636: SA | D636: 7271401 | E636: 46112 | F636: 45748 | G636: -8
A637: V | B637: ZCON | C637: SA | D637: 7285451 | E637: 46112 | F637: 45748 | G637: -6
A638: V | B638: ZCON | C638: SA | D638: 7310281 | E638: 46112 | F638: 45748 | G638: -6
A639: V | B639: ZCON | C639: SA | D639: 7330000 | E639: 46112 | F639: 45751 | G639: -3
A640: V | B640: ZCON | C640: SA | D640: 7330288 | E640: 46112 | F640: 45751 | G640: -3
A641: V | B641: ZCON | C641: SA | D641: 7330401 | E641: 46112 | F641: 45751 | G641: -3
...

Sheet ZAVL
A1: Application | B1: Condition Type | C1: Material | D1: Valid to | E1: Valid From | F1: Amount | G1: Unit of measure | H1: oka
A2: V | B2: ZAVL | C2: 830981014 | D2: 2958465 | E2: 38504 | F2: 102 | G2: EA
A3: V | B3: ZAVL | C3: 838900001 | D3: 2958465 | E3: 42664 | F3: 140 | G3: EA
A4: V | B4: ZAVL | C4: 083890000A | D4: 2958465 | E4: 42401 | F4: 150 | G4: EA
A5: V | B5: ZAVL | C5: 838900044 | D5: 2958465 | E5: 41198 | F5: 1 | G5: EA
A6: V | B6: ZAVL | C6: 838900054 | D6: 2958465 | E6: 37712 | F6: 1 | G6: EA
A7: V | B7: ZAVL | C7: 838900084 | D7: 2958465 | E7: 37841 | F7: 1 | G7: EA
A8: V | B8: ZAVL | C8: 838900104 | D8: 2958465 | E8: 37288 | F8: 1 | G8: EA
A9: V | B9: ZAVL | C9: 838900254 | D9: 2958465 | E9: 38108 | F9: 0.02 | G9: EA
A10: V | B10: ZAVL | C10: 838900454 | D10: 2958465 | E10: 40637 | F10: 0.01 | G10: EA
A11: V | B11: ZAVL | C11: 838900554 | D11: 2958465 | E11: 40634 | F11: 0.01 | G11: EA
A12: V | B12: ZAVL | C12: 838903004 | D12: 2958465 | E12: 37326 | F12: 1 | G12: EA
A13: V | B13: ZAVL | C13: 838904004 | D13: 2958465 | E13: 41613 | F13: 1 | G13: EA
A14: V | B14: ZAVL | C14: 838907004 | D14: 2958465 | E14: 42262 | F14: 0.01 | G14: EA
A15: V | B15: ZAVL | C15: 838920104 | D15: 46142 | E15: 45824 | F15: 3 | G15: EA
A16: V | B16: ZAVL | C16: 838920203 | D16: 2958465 | E16: 45047 | F16: 1 | G16: EA
... A7924: V | B7924: ZAVL | C7924: 9901906 | D7924: 2958465 | E7924: 44431 | F7924: 68.25 | G7924: CAN
A7925: V | B7925: ZAVL | C7925: B49200 | D7925: 2958465 | E7925: 44075 | F7925: 24629 | G7925: TO
A7926: V | B7926: ZAVL | C7926: G16000 | D7926: 2958465 | E7926: 43932 | F7926: 1 | G7926: KL
A7927: V | B7927: ZAVL | C7927: G50000 | D7927: 2958465 | E7927: 43932 | F7927: 1 | G7927: KL
A7928: V | B7928: ZAVL | C7928: M00014 | D7928: 2958465 | E7928: 38322 | F7928: 1 | G7928: EA
A7929: V | B7929: ZAVL | C7929: M00028 | D7929: 2958465 | E7929: 40800 | F7929: 1 | G7929: EA
A7930: V | B7930: ZAVL | C7930: M00032 | D7930: 2958465 | E7930: 40800 | F7930: 1 | G7930: EA
A7931: V | B7931: ZAVL | C7931: M00040 | D7931: 2958465 | E7931: 39202 | F7931: 1 | G7931: EA
A7932: V | B7932: ZAVL | C7932: M00046 | D7932: 2958465 | E7932: 37834 | F7932: 1 | G7932: EA
A7933: V | B7933: ZAVL | C7933: M00047 | D7933: 2958465 | E7933: 37834 | F7933: 1 | G7933: EA
A7934: V | B7934: ZAVL | C7934: M00066 | D7934: 2958465 | E7934: 40044 | F7934: 1 | G7934: EA

Sheet SMALL PACK
A1: Material | B1: MAT | C1: PACK CODE | D1: Type | E1: Material Description | F1: PACK SIZE in L | G1: Item Size in L | H1: No of items in one pack | I1: MRP/item | J1: MRP/L | K1: DLP conv | L1: DLP/ITEM | M1: DLP/L | N1: RSP/ITEM | O1: RSP/L | P1: HO DISC/L | Q1: UPHAAR UTSAV/L | R1: MSS/L | S1: TOTAL DISCOUNT /item | T1: Discounted RSP/ITEM | U1: EDLP/item | V1: EDLP/L | W1: EDLP/PACK | X1: Margin/item | Y1: Margin/pack | Z1: Margin/L | AA1: Stockist Discount % | AB1: Stockist Discount/ITEM | AC1: Cash Discount | AD1: Cash Discount/ITEM | AE1: Stockist Discount/L | AF1: Cash Discount/L | AH1: CATEGORY
A2: 1404174 | B2: =VALUE(LEFT(A2,4)) -> 1404 | C2: =VALUE(RIGHT(A2,3)) -> 174 | D2: =VLOOKUP(C2,Sheet1!$A$2:$K$369991,11,0) -> CAR | E2: SERVO PRIDE 40 - 40x1/2L - HDPE | F2: =VLOOKUP(C2,'PACK MASTER'!$A$2:$I$512998,9,0)*1000 -> 20 | G2: =VLOOKUP(C2,'PACK MASTER'!$A$2:$G$512998,7,0) -> 0.5 | H2: =F2/G2 -> 40 | I2: =VLOOKUP($A2,ZMRP!$C$2:$F$99995,4,0) -> 183 | J2: =I2/G2 -> 366 | K2: =VLOOKUP($A2,ZLAM!$C$2:$F$99999,4,0) -> 78.68 | L2: =I2*K2/100 -> 143.9844 | M2: =L2/G2 -> 287.9688 | N2: =L2/1.18 -> 122.02068 | O2: =N2/G2 -> 244.04136 | P2: =IFERROR(ABS(VLOOKUP($A2,ZTRV!$D$2:$G$99407,4,0)),0) -> 0 | Q2: =IFERROR(ABS(VLOOKUP($A2,ZTR1!$D$2:$G$99999,4,0)),0) -> 0 | R2: =IFERROR(ABS(VLOOKUP($A2,ZTR2!$D$2:$G$99939,4,0)),0) -> 0 | S2: =SUM(P2:R2)*G2 -> 0 | T2: =N2-S2 -> 122.02068 | U2: =T2*1.18 -> 143.9844 | V2: =U2/G2 -> 287.9688 | W2: =V2*F2 -> 5759.376 | X2: =I2-U2 -> 39.0156 | Y2: =X2*H2 -> 1560.624 | Z2: =J2-V2 -> 78.0312 | AA2: =IFERROR(ABS(VLOOKUP(A2,ZSSD!$D$2:$G$99933,4,0)),AI2) -> 6.5 | AB2: =IFERROR(IF(VLOOKUP(A2,ZSSD!$D:$H,5,0)="L29",AA2*G2,AA2*L2/100),AA2*L2/100) -> 9.358986 | AC2: 2 | AD2: =2*(T2-AB2)/100 -> 2.2532338 | AE2: =+AB2/G2 -> 18.717972 | AF2: =+AD2/G2 -> 4.5064677 | AG2: =VLOOKUP(A2,ZSSD!D:D,1,0) -> #N/A | AH2: =VLOOKUP(B2,[2]GRADE!$A:$P,16,0) -> SILVER | AI2: =IF(AH2="SILVER",6.5,IF(AH2="GOLD",8,IF(AH2="INDUSTRIAL",6,IF(AH2="GREEN",7,IF(AH2="BRONZE",5.5,0))))) -> 6.5
A3: 1404184 | B3: =VALUE(LEFT(A3,4)) -> 1404 | C3: =VALUE(RIGHT(A3,3)) -> 184 | D3: =VLOOKUP(C3,Sheet1!$A$2:$K$369991,11,0) -> CAR | E3: SERVO PRIDE 40 - 20x1L - HDPE | F3: =VLOOKUP(C3,'PACK MASTER'!$A$2:$I$512998,9,0)*1000 -> 20 | G3: =VLOOKUP(C3,'PACK MASTER'!$A$2:$G$512998,7,0) -> 1 | H3: =F3/G3 -> 20 | I3: =VLOOKUP($A3,ZMRP!$C$2:$F$99995,4,0) -> 355 | J3: =I3/G3 -> 355 | K3: =VLOOKUP($A3,ZLAM!$C$2:$F$99999,4,0) -> 79.24 | L3: =I3*K3/100 -> 281.302 | M3: =L3/G3 -> 281.302 | N3: =L3/1.18 -> 238.39153 | O3: =N3/G3 -> 238.39153 | P3: =IFERROR(ABS(VLOOKUP($A3,ZTRV!$D$2:$G$99407,4,0)),0) -> 8 | Q3: =IFERROR(ABS(VLOOKUP($A3,ZTR1!$D$2:$G$99999,4,0)),0) -> 0 | R3: =IFERROR(ABS(VLOOKUP($A3,ZTR2!$D$2:$G$99939,4,0)),0) -> 0 | S3: =SUM(P3:R3)*G3 -> 8 | T3: =N3-S3 -> 230.39153 | U3: =T3*1.18 -> 271.862 | V3: =U3/G3 -> 271.862 | W3: =V3*F3 -> 5437.24 | X3: =I3-U3 -> 83.138 | Y3: =X3*H3 -> 1662.76 | Z3: =J3-V3 -> 83.138 | AA3: =IFERROR(ABS(VLOOKUP(A3,ZSSD!$D$2:$G$99933,4,0)),AI3) -> 6.5 | AB3: =IFERROR(IF(VLOOKUP(A3,ZSSD!$D:$H,5,0)="L29",AA3*G3,AA3*L3/100),AA3*L3/100) -> 18.28463 | AC3: 2 | AD3: =2*(T3-AB3)/100 -> 4.2421379 | AE3: =+AB3/G3 -> 18.28463 | AF3: =+AD3/G3 -> 4.2421379 | AG3: =VLOOKUP(A3,ZSSD!D:D,1,0) -> #N/A | AH3: =VLOOKUP(B3,[2]GRADE!$A:$P,16,0) -> SILVER | AI3: =IF(AH3="SILVER",6.5,IF(AH3="GOLD",8,IF(AH3="INDUSTRIAL",6,IF(AH3="GREEN",7,IF(AH3="BRONZE",5.5,0))))) -> 6.5
A4: 1404229 | B4: =VALUE(LEFT(A4,4)) -> 1404 | C4: =VALUE(RIGHT(A4,3)) -> 229 | D4: =VLOOKUP(C4,Sheet1!$A$2:$K$369991,11,0) -> CAR | E4: SERVO PRIDE 40-20 X 1 L PROMO | F4: =VLOOKUP(C4,'PACK MASTER'!$A$2:$I$512998,9,0)*1000 -> 20 | G4: =VLOOKUP(C4,'PACK MASTER'!$A$2:$G$512998,7,0) -> 1 | H4: =F4/G4 -> 20 | I4: =VLOOKUP($A4,ZMRP!$C$2:$F$99995,4,0) -> 355 | J4: =I4/G4 -> 355 | K4: =VLOOKUP($A4,ZLAM!$C$2:$F$99999,4,0) -> 79.24 | L4: =I4*K4/100 -> 281.302 | M4: =L4/G4 -> 281.302 | N4: =L4/1.18 -> 238.39153 | O4: =N4/G4 -> 238.39153 | P4: =IFERROR(ABS(VLOOKUP($A4,ZTRV!$D$2:$G$99407,4,0)),0) -> 0 | Q4: =IFERROR(ABS(VLOOKUP($A4,ZTR1!$D$2:$G$99999,4,0)),0) -> 0 | R4: =IFERROR(ABS(VLOOKUP($A4,ZTR2!$D$2:$G$99939,4,0)),0) -> 0 | S4: =SUM(P4:R4)*G4 -> 0 | T4: =N4-S4 -> 238.39153 | U4: =T4*1.18 -> 281.302 | V4: =U4/G4 -> 281.302 | W4: =V4*F4 -> 5626.04 | X4: =I4-U4 -> 73.698 | Y4: =X4*H4 -> 1473.96 | Z4: =J4-V4 -> 73.698 | AA4: =IFERROR(ABS(VLOOKUP(A4,ZSSD!$D$2:$G$99933,4,0)),AI4) -> 6.5 | AB4: =IFERROR(IF(VLOOKUP(A4,ZSSD!$D:$H,5,0)="L29",AA4*G4,AA4*L4/100),AA4*L4/100) -> 18.28463 | AC4: 2 | AD4: =2*(T4-AB4)/100 -> 4.4021379 | AE4: =+AB4/G4 -> 18.28463 | AF4: =+AD4/G4 -> 4.4021379 | AG4: =VLOOKUP(A4,ZSSD!D:D,1,0) -> #N/A | AH4: =VLOOKUP(B4,[2]GRADE!$A:$P,16,0) -> SILVER | AI4: =IF(AH4="SILVER",6.5,IF(AH4="GOLD",8,IF(AH4="INDUSTRIAL",6,IF(AH4="GREEN",7,IF(AH4="BRONZE",5.5,0))))) -> 6.5
A5: 1404234 | B5: =VALUE(LEFT(A5,4)) -> 1404 | C5: =VALUE(RIGHT(A5,3)) -> 234 | D5: =VLOOKUP(C5,Sheet1!$A$2:$K$369991,11,0) -> CAR | E5: SERVO PRIDE 40 - 4x5L - HDPE | F5: =VLOOKUP(C5,'PACK MASTER'!$A$2:$I$512998,9,0)*1000 -> 20 | G5: =VLOOKUP(C5,'PACK MASTER'!$A$2:$G$512998,7,0) -> 5 | H5: =F5/G5 -> 4 | I5: =VLOOKUP($A5,ZMRP!$C$2:$F$99995,4,0) -> 1775 | J5: =I5/G5 -> 355 | K5: =VLOOKUP($A5,ZLAM!$C$2:$F$99999,4,0) -> 78.16 | L5: =I5*K5/100 -> 1387.34 | M5: =L5/G5 -> 277.468 | N5: =L5/1.18 -> 1175.7119 | O5: =N5/G5 -> 235.14237 | P5: =IFERROR(ABS(VLOOKUP($A5,ZTRV!$D$2:$G$99407,4,0)),0) -> 8 | Q5: =IFERROR(ABS(VLOOKUP($A5,ZTR1!$D$2:$G$99999,4,0)),0) -> 0 | R5: =IFERROR(ABS(VLOOKUP($A5,ZTR2!$D$2:$G$99939,4,0)),0) -> 0 | S5: =SUM(P5:R5)*G5 -> 40 | T5: =N5-S5 -> 1135.7119 | U5: =T5*1.18 -> 1340.14 | V5: =U5/G5 -> 268.028 | W5: =V5*F5 -> 5360.56 | X5: =I5-U5 -> 434.86 | Y5: =X5*H5 -> 1739.44 | Z5: =J5-V5 -> 86.972 | AA5: =IFERROR(ABS(VLOOKUP(A5,ZSSD!$D$2:$G$99933,4,0)),AI5) -> 6.5 | AB5: =IFERROR(IF(VLOOKUP(A5,ZSSD!$D:$H,5,0)="L29",AA5*G5,AA5*L5/100),AA5*L5/100) -> 90.1771 | AC5: 2 | AD5: =2*(T5-AB5)/100 -> 20.910695 | AE5: =+AB5/G5 -> 18.03542 | AF5: =+AD5/G5 -> 4.1821391 | AG5: =VLOOKUP(A5,ZSSD!D:D,1,0) -> #N/A | AH5: =VLOOKUP(B5,[2]GRADE!$A:$P,16,0) -> SILVER | AI5: =IF(AH5="SILVER",6.5,IF(AH5="GOLD",8,IF(AH5="INDUSTRIAL",6,IF(AH5="GREEN",7,IF(AH5="BRONZE",5.5,0))))) -> 6.5
A6: 1404240 | B6: =VALUE(LEFT(A6,4)) -> 1404 | C6: =VALUE(RIGHT(A6,3)) -> 240 | D6: =VLOOKUP(C6,Sheet1!$A$2:$K$369991,11,0) -> CAR | E6: SERVO PRIDE 40-4x5L - PROMO | F6: =VLOOKUP(C6,'PACK MASTER'!$A$2:$I$512998,9,0)*1000 -> 20 | G6: =VLOOKUP(C6,'PACK MASTER'!$A$2:$G$512998,7,0) -> 5 | H6: =F6/G6 -> 4 | I6: =VLOOKUP($A6,ZMRP!$C$2:$F$99995,4,0) -> 1775 | J6: =I6/G6 -> 355 | K6: =VLOOKUP($A6,ZLAM!$C$2:$F$99999,4,0) -> 78.16 | L6: =I6*K6/100 -> 1387.34 | M6: =L6/G6 -> 277.468 | N6: =L6/1.18 -> 1175.7119 | O6: =N6/G6 -> 235.14237 | P6: =IFERROR(ABS(VLOOKUP($A6,ZTRV!$D$2:$G$99407,4,0)),0) -> 0 | Q6: =IFERROR(ABS(VLOOKUP($A6,ZTR1!$D$2:$G$99999,4,0)),0) -> 0 | R6: =IFERROR(ABS(VLOOKUP($A6,ZTR2!$D$2:$G$99939,4,0)),0) -> 0 | S6: =SUM(P6:R6)*G6 -> 0 | T6: =N6-S6 -> 1175.7119 | U6: =T6*1.18 -> 1387.34 | V6: =U6/G6 -> 277.468 | W6: =V6*F6 -> 5549.36 | X6: =I6-U6 -> 387.66 | Y6: =X6*H6 -> 1550.64 | Z6: =J6-V6 -> 77.532 | AA6: =IFERROR(ABS(VLOOKUP(A6,ZSSD!$D$2:$G$99933,4,0)),AI6) -> 6.5 | AB6: =IFERROR(IF(VLOOKUP(A6,ZSSD!$D:$H,5,0)="L29",AA6*G6,AA6*L6/100),AA6*L6/100) -> 90.1771 | AC6: 2 | AD6: =2*(T6-AB6)/100 -> 21.710695 | AE6: =+AB6/G6 -> 18.03542 | AF6: =+AD6/G6 -> 4.3421391 | AG6: =VLOOKUP(A6,ZSSD!D:D,1,0) -> #N/A | AH6: =VLOOKUP(B6,[2]GRADE!$A:$P,16,0) -> SILVER | AI6: =IF(AH6="SILVER",6.5,IF(AH6="GOLD",8,IF(AH6="INDUSTRIAL",6,IF(AH6="GREEN",7,IF(AH6="BRONZE",5.5,0))))) -> 6.5
A7: 1404242 | B7: =VALUE(LEFT(A7,4)) -> 1404 | C7: =VALUE(RIGHT(A7,3)) -> 242 | D7: =VLOOKUP(C7,Sheet1!$A$2:$K$369991,11,0) -> BUC | E7: SERVO PRIDE 40 - 10L BUC | F7: =VLOOKUP(C7,'PACK MASTER'!$A$2:$I$512998,9,0)*1000 -> 10 | G7: =VLOOKUP(C7,'PACK MASTER'!$A$2:$G$512998,7,0) -> 10 | H7: =F7/G7 -> 1 | I7: =VLOOKUP($A7,ZMRP!$C$2:$F$99995,4,0) -> 3550 | J7: =I7/G7 -> 355 | K7: =VLOOKUP($A7,ZLAM!$C$2:$F$99999,4,0) -> 77.84 | L7: =I7*K7/100 -> 2763.32 | M7: =L7/G7 -> 276.332 | N7: =L7/1.18 -> 2341.7966 | O7: =N7/G7 -> 234.17966 | P7: =IFERROR(ABS(VLOOKUP($A7,ZTRV!$D$2:$G$99407,4,0)),0) -> 8 | Q7: =IFERROR(ABS(VLOOKUP($A7,ZTR1!$D$2:$G$99999,4,0)),0) -> 0 | R7: =IFERROR(ABS(VLOOKUP($A7,ZTR2!$D$2:$G$99939,4,0)),0) -> 0 | S7: =SUM(P7:R7)*G7 -> 80 | T7: =N7-S7 -> 2261.7966 | U7: =T7*1.18 -> 2668.92 | V7: =U7/G7 -> 266.892 | W7: =V7*F7 -> 2668.92 | X7: =I7-U7 -> 881.08 | Y7: =X7*H7 -> 881.08 | Z7: =J7-V7 -> 88.108 | AA7: =IFERROR(ABS(VLOOKUP(A7,ZSSD!$D$2:$G$99933,4,0)),AI7) -> 6.5 | AB7: =IFERROR(IF(VLOOKUP(A7,ZSSD!$D:$H,5,0)="L29",AA7*G7,AA7*L7/100),AA7*L7/100) -> 179.6158 | AC7: 2 | AD7: =2*(T7-AB7)/100 -> 41.643616 | AE7: =+AB7/G7 -> 17.96158 | AF7: =+AD7/G7 -> 4.1643616 | AG7: =VLOOKUP(A7,ZSSD!D:D,1,0) -> #N/A | AH7: =VLOOKUP(B7,[2]GRADE!$A:$P,16,0) -> SILVER | AI7: =IF(AH7="SILVER",6.5,IF(AH7="GOLD",8,IF(AH7="INDUSTRIAL",6,IF(AH7="GREEN",7,IF(AH7="BRONZE",5.5,0))))) -> 6.5
A8: 1404265 | B8: =VALUE(LEFT(A8,4)) -> 1404 | C8: =VALUE(RIGHT(A8,3)) -> 265 | D8: =VLOOKUP(C8,Sheet1!$A$2:$K$369991,11,0) -> BUC | E8: SERVO PRIDE 40-20L BUC | F8: =VLOOKUP(C8,'PACK MASTER'!$A$2:$I$512998,9,0)*1000 -> 20 | G8: =VLOOKUP(C8,'PACK MASTER'!$A$2:$G$512998,7,0) -> 20 | H8: =F8/G8 -> 1 | I8: =VLOOKUP($A8,ZMRP!$C$2:$F$99995,4,0) -> 6900 | J8: =I8/G8 -> 345 | K8: =VLOOKUP($A8,ZLAM!$C$2:$F$99999,4,0) -> 79.31 | L8: =I8*K8/100 -> 5472.39 | M8: =L8/G8 -> 273.6195 | N8: =L8/1.18 -> 4637.6186 | O8: =N8/G8 -> 231.88093 | P8: =IFERROR(ABS(VLOOKUP($A8,ZTRV!$D$2:$G$99407,4,0)),0) -> 8 | Q8: =IFERROR(ABS(VLOOKUP($A8,ZTR1!$D$2:$G$99999,4,0)),0) -> 0 | R8: =IFERROR(ABS(VLOOKUP($A8,ZTR2!$D$2:$G$99939,4,0)),0) -> 0 | S8: =SUM(P8:R8)*G8 -> 160 | T8: =N8-S8 -> 4477.6186 | U8: =T8*1.18 -> 5283.59 | V8: =U8/G8 -> 264.1795 | W8: =V8*F8 -> 5283.59 | X8: =I8-U8 -> 1616.41 | Y8: =X8*H8 -> 1616.41 | Z8: =J8-V8 -> 80.8205 | AA8: =IFERROR(ABS(VLOOKUP(A8,ZSSD!$D$2:$G$99933,4,0)),AI8) -> 6.5 | AB8: =IFERROR(IF(VLOOKUP(A8,ZSSD!$D:$H,5,0)="L29",AA8*G8,AA8*L8/100),AA8*L8/100) -> 355.70535 | AC8: 2 | AD8: =2*(T8-AB8)/100 -> 82.438266 | AE8: =+AB8/G8 -> 17.785267 | AF8: =+AD8/G8 -> 4.1219133 | AG8: =VLOOKUP(A8,ZSSD!D:D,1,0) -> #N/A | AH8: =VLOOKUP(B8,[2]GRADE!$A:$P,16,0) -> SILVER | AI8: =IF(AH8="SILVER",6.5,IF(AH8="GOLD",8,IF(AH8="INDUSTRIAL",6,IF(AH8="GREEN",7,IF(AH8="BRONZE",5.5,0))))) -> 6.5
A9: 1408164 | B9: =VALUE(LEFT(A9,4)) -> 1408 | C9: =VALUE(RIGHT(A9,3)) -> 164 | D9: =VLOOKUP(C9,Sheet1!$A$2:$K$369991,11,0) -> CAR | E9: MAXIMILE PREMIUM-40X1/4L | F9: =VLOOKUP(C9,'PACK MASTER'!$A$2:$I$512998,9,0)*1000 -> 10 | G9: =VLOOKUP(C9,'PACK MASTER'!$A$2:$G$512998,7,0) -> 0.25 | H9: =F9/G9 -> 40 | I9: =VLOOKUP($A9,ZMRP!$C$2:$F$99995,4,0) -> 74 | J9: =I9/G9 -> 296 | K9: =VLOOKUP($A9,ZLAM!$C$2:$F$99999,4,0) -> 77.72 | L9: =I9*K9/100 -> 57.5128 | M9: =L9/G9 -> 230.0512 | N9: =L9/1.18 -> 48.739661 | O9: =N9/G9 -> 194.95864 | P9: =IFERROR(ABS(VLOOKUP($A9,ZTRV!$D$2:$G$99407,4,0)),0) -> 0 | Q9: =IFERROR(ABS(VLOOKUP($A9,ZTR1!$D$2:$G$99999,4,0)),0) -> 0 | R9: =IFERROR(ABS(VLOOKUP($A9,ZTR2!$D$2:$G$99939,4,0)),0) -> 0 | S9: =SUM(P9:R9)*G9 -> 0 | T9: =N9-S9 -> 48.739661 | U9: =T9*1.18 -> 57.5128 | V9: =U9/G9 -> 230.0512 | W9: =V9*F9 -> 2300.512 | X9: =I9-U9 -> 16.4872 | Y9: =X9*H9 -> 659.488 | Z9: =J9-V9 -> 65.9488 | AA9: =IFERROR(ABS(VLOOKUP(A9,ZSSD!$D$2:$G$99933,4,0)),AI9) -> 4 | AB9: =IFERROR(IF(VLOOKUP(A9,ZSSD!$D:$H,5,0)="L29",AA9*G9,AA9*L9/100),AA9*L9/100) -> 1 | AC9: 2 | AD9: =2*(T9-AB9)/100 -> 0.95479322 | AE9: =+AB9/G9 -> 4 | AF9: =+AD9/G9 -> 3.8191729 | AG9: =VLOOKUP(A9,ZSSD!D:D,1,0) -> 1408164 | AH9: =VLOOKUP(B9,[2]GRADE!$A:$P,16,0) -> SILVER | AI9: =IF(AH9="SILVER",6.5,IF(AH9="GOLD",8,IF(AH9="INDUSTRIAL",6,IF(AH9="GREEN",7,IF(AH9="BRONZE",5.5,0))))) -> 6.5
A10: 1408184 | B10: =VALUE(LEFT(A10,4)) -> 1408 | C10: =VALUE(RIGHT(A10,3)) -> 184 | D10: =VLOOKUP(C10,Sheet1!$A$2:$K$369991,11,0) -> CAR | E10: MAXIMILE PREMIUM - 20 X 1 L HDPE | F10: =VLOOKUP(C10,'PACK MASTER'!$A$2:$I$512998,9,0)*1000 -> 20 | G10: =VLOOKUP(C10,'PACK MASTER'!$A$2:$G$512998,7,0) -> 1 | H10: =F10/G10 -> 20 | I10: =VLOOKUP($A10,ZMRP!$C$2:$F$99995,4,0) -> 262 | J10: =I10/G10 -> 262 | K10: =VLOOKUP($A10,ZLAM!$C$2:$F$99999,4,0) -> 78.76 | L10: =I10*K10/100 -> 206.3512 | M10: =L10/G10 -> 206.3512 | N10: =L10/1.18 -> 174.8739 | O10: =N10/G10 -> 174.8739 | P10: =IFERROR(ABS(VLOOKUP($A10,ZTRV!$D$2:$G$99407,4,0)),0) -> 0 | Q10: =IFERROR(ABS(VLOOKUP($A10,ZTR1!$D$2:$G$99999,4,0)),0) -> 0 | R10: =IFERROR(ABS(VLOOKUP($A10,ZTR2!$D$2:$G$99939,4,0)),0) -> 0 | S10: =SUM(P10:R10)*G10 -> 0 | T10: =N10-S10 -> 174.8739 | U10: =T10*1.18 -> 206.3512 | V10: =U10/G10 -> 206.3512 | W10: =V10*F10 -> 4127.024 | X10: =I10-U10 -> 55.6488 | Y10: =X10*H10 -> 1112.976 | Z10: =J10-V10 -> 55.6488 | AA10: =IFERROR(ABS(VLOOKUP(A10,ZSSD!$D$2:$G$99933,4,0)),AI10) -> 4 | AB10: =IFERROR(IF(VLOOKUP(A10,ZSSD!$D:$H,5,0)="L29",AA10*G10,AA10*L10/100),AA10*L10/100) -> 4 | AC10: 2 | AD10: =2*(T10-AB10)/100 -> 3.417478 | AE10: =+AB10/G10 -> 4 | AF10: =+AD10/G10 -> 3.417478 | AG10: =VLOOKUP(A10,ZSSD!D:D,1,0) -> 1408184 | AH10: =VLOOKUP(B10,[2]GRADE!$A:$P,16,0) -> SILVER | AI10: =IF(AH10="SILVER",6.5,IF(AH10="GOLD",8,IF(AH10="INDUSTRIAL",6,IF(AH10="GREEN",7,IF(AH10="BRONZE",5.5,0))))) -> 6.5
A11: 1408244 | B11: =VALUE(LEFT(A11,4)) -> 1408 | C11: =VALUE(RIGHT(A11,3)) -> 244 | D11: =VLOOKUP(C11,Sheet1!$A$2:$K$369991,11,0) -> CAR | E11: MAXIMILE PREMIUM - 4 X 6 L HDPE | F11: =VLOOKUP(C11,'PACK MASTER'!$A$2:$I$512998,9,0)*1000 -> 24 | G11: =VLOOKUP(C11,'PACK MASTER'!$A$2:$G$512998,7,0) -> 6 | H11: =F11/G11 -> 4 | I11: =VLOOKUP($A11,ZMRP!$C$2:$F$99995,4,0) -> 1572 | J11: =I11/G11 -> 262 | K11: =VLOOKUP($A11,ZLAM!$C$2:$F$99999,4,0) -> 76.49 | L11: =I11*K11/100 -> 1202.4228 | M11: =L11/G11 -> 200.4038 | N11: =L11/1.18 -> 1019.0024 | O11: =N11/G11 -> 169.83373 | P11: =IFERROR(ABS(VLOOKUP($A11,ZTRV!$D$2:$G$99407,4,0)),0) -> 0 | Q11: =IFERROR(ABS(VLOOKUP($A11,ZTR1!$D$2:$G$99999,4,0)),0) -> 0 | R11: =IFERROR(ABS(VLOOKUP($A11,ZTR2!$D$2:$G$99939,4,0)),0) -> 0 | S11: =SUM(P11:R11)*G11 -> 0 | T11: =N11-S11 -> 1019.0024 | U11: =T11*1.18 -> 1202.4228 | V11: =U11/G11 -> 200.4038 | W11: =V11*F11 -> 4809.6912 | X11: =I11-U11 -> 369.5772 | Y11: =X11*H11 -> 1478.3088 | Z11: =J11-V11 -> 61.5962 | AA11: =IFERROR(ABS(VLOOKUP(A11,ZSSD!$D$2:$G$99933,4,0)),AI11) -> 4 | AB11: =IFERROR(IF(VLOOKUP(A11,ZSSD!$D:$H,5,0)="L29",AA11*G11,AA11*L11/100),AA11*L11/100) -> 24 | AC11: 2 | AD11: =2*(T11-AB11)/100 -> 19.900047 | AE11: =+AB11/G11 -> 4 | AF11: =+AD11/G11 -> 3.3166746 | AG11: =VLOOKUP(A11,ZSSD!D:D,1,0) -> 1408244 | AH11: =VLOOKUP(B11,[2]GRADE!$A:$P,16,0) -> SILVER | AI11: =IF(AH11="SILVER",6.5,IF(AH11="GOLD",8,IF(AH11="INDUSTRIAL",6,IF(AH11="GREEN",7,IF(AH11="BRONZE",5.5,0))))) -> 6.5
A12: 1412184 | B12: =VALUE(LEFT(A12,4)) -> 1412 | C12: =VALUE(RIGHT(A12,3)) -> 184 | D12: =VLOOKUP(C12,Sheet1!$A$2:$K$369991,11,0) -> CAR | E12: MAXIMILE 6K - 20 X 1 L HDPE | F12: =VLOOKUP(C12,'PACK MASTER'!$A$2:$I$512998,9,0)*1000 -> 20 | G12: =VLOOKUP(C12,'PACK MASTER'!$A$2:$G$512998,7,0) -> 1 | H12: =F12/G12 -> 20 | I12: =VLOOKUP($A12,ZMRP!$C$2:$F$99995,4,0) -> 284 | J12: =I12/G12 -> 284 | K12: =VLOOKUP($A12,ZLAM!$C$2:$F$99999,4,0) -> 74.04 | L12: =I12*K12/100 -> 210.2736 | M12: =L12/G12 -> 210.2736 | N12: =L12/1.18 -> 178.19797 | O12: =N12/G12 -> 178.19797 | P12: =IFERROR(ABS(VLOOKUP($A12,ZTRV!$D$2:$G$99407,4,0)),0) -> 0 | Q12: =IFERROR(ABS(VLOOKUP($A12,ZTR1!$D$2:$G$99999,4,0)),0) -> 0 | R12: =IFERROR(ABS(VLOOKUP($A12,ZTR2!$D$2:$G$99939,4,0)),0) -> 0 | S12: =SUM(P12:R12)*G12 -> 0 | T12: =N12-S12 -> 178.19797 | U12: =T12*1.18 -> 210.2736 | V12: =U12/G12 -> 210.2736 | W12: =V12*F12 -> 4205.472 | X12: =I12-U12 -> 73.7264 | Y12: =X12*H12 -> 1474.528 | Z12: =J12-V12 -> 73.7264 | AA12: =IFERROR(ABS(VLOOKUP(A12,ZSSD!$D$2:$G$99933,4,0)),AI12) -> 4 | AB12: =IFERROR(IF(VLOOKUP(A12,ZSSD!$D:$H,5,0)="L29",AA12*G12,AA12*L12/100),AA12*L12/100) -> 4 | AC12: 2 | AD12: =2*(T12-AB12)/100 -> 3.4839593 | AE12: =+AB12/G12 -> 4 | AF12: =+AD12/G12 -> 3.4839593 | AG12: =VLOOKUP(A12,ZSSD!D:D,1,0) -> 1412184 | AH12: =VLOOKUP(B12,[2]GRADE!$A:$P,16,0) -> SILVER | AI12: =IF(AH12="SILVER",6.5,IF(AH12="GOLD",8,IF(AH12="INDUSTRIAL",6,IF(AH12="GREEN",7,IF(AH12="BRONZE",5.5,0))))) -> 6.5
A13: 1412197 | B13: =VALUE(LEFT(A13,4)) -> 1412 | C13: =VALUE(RIGHT(A13,3)) -> 197 | D13: =VLOOKUP(C13,Sheet1!$A$2:$K$369991,11,0) -> CAR | E13: MAXIMILE 6K - 10 X 2 L HDPE | F13: =VLOOKUP(C13,'PACK MASTER'!$A$2:$I$512998,9,0)*1000 -> 20 | G13: =VLOOKUP(C13,'PACK MASTER'!$A$2:$G$512998,7,0) -> 2 | H13: =F13/G13 -> 10 | I13: =VLOOKUP($A13,ZMRP!$C$2:$F$99995,4,0) -> 560 | J13: =I13/G13 -> 280 | K13: =VLOOKUP($A13,ZLAM!$C$2:$F$99999,4,0) -> 74.04 | L13: =I13*K13/100 -> 414.624 | M13: =L13/G13 -> 207.312 | N13: =L13/1.18 -> 351.37627 | O13: =N13/G13 -> 175.68814 | P13: =IFERROR(ABS(VLOOKUP($A13,ZTRV!$D$2:$G$99407,4,0)),0) -> 0 | Q13: =IFERROR(ABS(VLOOKUP($A13,ZTR1!$D$2:$G$99999,4,0)),0) -> 0 | R13: =IFERROR(ABS(VLOOKUP($A13,ZTR2!$D$2:$G$99939,4,0)),0) -> 0 | S13: =SUM(P13:R13)*G13 -> 0 | T13: =N13-S13 -> 351.37627 | U13: =T13*1.18 -> 414.624 | V13: =U13/G13 -> 207.312 | W13: =V13*F13 -> 4146.24 | X13: =I13-U13 -> 145.376 | Y13: =X13*H13 -> 1453.76 | Z13: =J13-V13 -> 72.688 | AA13: =IFERROR(ABS(VLOOKUP(A13,ZSSD!$D$2:$G$99933,4,0)),AI13) -> 4 | AB13: =IFERROR(IF(VLOOKUP(A13,ZSSD!$D:$H,5,0)="L29",AA13*G13,AA13*L13/100),AA13*L13/100) -> 8 | AC13: 2 | AD13: =2*(T13-AB13)/100 -> 6.8675254 | AE13: =+AB13/G13 -> 4 | AF13: =+AD13/G13 -> 3.4337627 | AG13: =VLOOKUP(A13,ZSSD!D:D,1,0) -> 1412197 | AH13: =VLOOKUP(B13,[2]GRADE!$A:$P,16,0) -> SILVER | AI13: =IF(AH13="SILVER",6.5,IF(AH13="GOLD",8,IF(AH13="INDUSTRIAL",6,IF(AH13="GREEN",7,IF(AH13="BRONZE",5.5,0))))) -> 6.5
... A53: 2825022 | B53: =VALUE(LEFT(A53,4)) -> 2825 | C53: =VALUE(RIGHT(A53,3)) -> 22 | D53: =VLOOKUP(C53,Sheet1!$A$2:$K$369991,11,0) -> CAR | E53: SERVO HYPERSPORT F5-10 X 1.2 L PROMO | F53: =VLOOKUP(C53,'PACK MASTER'!$A$2:$I$512998,9,0)*1000 -> 12 | G53: =VLOOKUP(C53,'PACK MASTER'!$A$2:$G$512998,7,0) -> 1.2 | H53: =F53/G53 -> 10 | I53: =VLOOKUP($A53,ZMRP!$C$2:$F$99995,4,0) -> 1054 | J53: =I53/G53 -> 878.33333 | K53: =VLOOKUP($A53,ZLAM!$C$2:$F$99999,4,0) -> 73.5 | L53: =I53*K53/100 -> 774.69 | M53: =L53/G53 -> 645.575 | N53: =L53/1.18 -> 656.51695 | O53: =N53/G53 -> 547.09746 | P53: =IFERROR(ABS(VLOOKUP($A53,ZTRV!$D$2:$G$99407,4,0)),0) -> 40 | Q53: =IFERROR(ABS(VLOOKUP($A53,ZTR1!$D$2:$G$99999,4,0)),0) -> 200 | R53: =IFERROR(ABS(VLOOKUP($A53,ZTR2!$D$2:$G$99939,4,0)),0) -> 0 | S53: =SUM(P53:R53)*G53 -> 288 | T53: =N53-S53 -> 368.51695 | U53: =T53*1.18 -> 434.85 | V53: =U53/G53 -> 362.375 | W53: =V53*F53 -> 4348.5 | X53: =I53-U53 -> 619.15 | Y53: =X53*H53 -> 6191.5 | Z53: =J53-V53 -> 515.95833 | AA53: =IFERROR(ABS(VLOOKUP(A53,ZSSD!$D$2:$G$99933,4,0)),AI53) -> 8 | AB53: =IFERROR(IF(VLOOKUP(A53,ZSSD!$D:$H,5,0)="L29",AA53*G53,AA53*L53/100),AA53*L53/100) -> 61.9752 | AC53: 2 | AD53: =2*(T53-AB53)/100 -> 6.130835 | AE53: =+AB53/G53 -> 51.646 | AF53: =+AD53/G53 -> 5.1090292 | AG53: =VLOOKUP(A53,ZSSD!D:D,1,0) -> 2825022 | AH53: =VLOOKUP(B53,[2]GRADE!$A:$P,16,0) -> GOLD | AI53: =IF(AH53="SILVER",6.5,IF(AH53="GOLD",8,IF(AH53="INDUSTRIAL",6,IF(AH53="GREEN",7,IF(AH53="BRONZE",5.5,0))))) -> 8
A54: 2825030 | B54: 2825 | C54: 30 | D54: CAR | E54: SERVO HYPERSPORT F5-4 X 2.8 L | F54: =VLOOKUP(C54,'PACK MASTER'!$A$2:$I$512998,9,0)*1000 -> 11.2 | G54: =VLOOKUP(C54,'PACK MASTER'!$A$2:$G$512998,7,0) -> 2.8 | H54: =F54/G54 -> 4 | I54: =VLOOKUP($A54,ZMRP!$C$2:$F$99995,4,0) -> 2450 | J54: =I54/G54 -> 875 | K54: =VLOOKUP($A54,ZLAM!$C$2:$F$99999,4,0) -> 73.5 | L54: =I54*K54/100 -> 1800.75 | M54: =L54/G54 -> 643.125 | N54: =L54/1.18 -> 1526.0593 | O54: =N54/G54 -> 545.02119 | P54: =IFERROR(ABS(VLOOKUP($A54,ZTRV!$D$2:$G$99407,4,0)),0) -> 0 | Q54: =IFERROR(ABS(VLOOKUP($A54,ZTR1!$D$2:$G$99999,4,0)),0) -> 0 | R54: =IFERROR(ABS(VLOOKUP($A54,ZTR2!$D$2:$G$99939,4,0)),0) -> 0 | S54: =SUM(P54:R54)*G54 -> 0 | T54: =N54-S54 -> 1526.0593 | U54: =T54*1.18 -> 1800.75 | V54: =U54/G54 -> 643.125 | W54: =V54*F54 -> 7203 | X54: =I54-U54 -> 649.25 | Y54: =X54*H54 -> 2597 | Z54: =J54-V54 -> 231.875 | AA54: =IFERROR(ABS(VLOOKUP(A54,ZSSD!$D$2:$G$99933,4,0)),AI54) -> 8 | AB54: =IFERROR(IF(VLOOKUP(A54,ZSSD!$D:$H,5,0)="L29",AA54*G54,AA54*L54/100),AA54*L54/100) -> 144.06 | AC54: 2 | AD54: =2*(T54-AB54)/100 -> 27.639986 | AE54: =+AB54/G54 -> 51.45 | AF54: =+AD54/G54 -> 9.8714237 | AG54: =VLOOKUP(A54,ZSSD!D:D,1,0) -> #N/A | AH54: =VLOOKUP(B54,[2]GRADE!$A:$P,16,0) -> GOLD | AI54: =IF(AH54="SILVER",6.5,IF(AH54="GOLD",8,IF(AH54="INDUSTRIAL",6,IF(AH54="GREEN",7,IF(AH54="BRONZE",5.5,0))))) -> 8
A55: 2825185 | B55: =VALUE(LEFT(A55,4)) -> 2825 | C55: =VALUE(RIGHT(A55,3)) -> 185 | D55: =VLOOKUP(C55,Sheet1!$A$2:$K$369991,11,0) -> CAR | E55: SERVO HYPERSPORT F5-10 X 1 L | F55: =VLOOKUP(C55,'PACK MASTER'!$A$2:$I$512998,9,0)*1000 -> 10 | G55: =VLOOKUP(C55,'PACK MASTER'!$A$2:$G$512998,7,0) -> 1 | H55: =F55/G55 -> 10 | I55: =VLOOKUP($A55,ZMRP!$C$2:$F$99995,4,0) -> 880 | J55: =I55/G55 -> 880 | K55: =VLOOKUP($A55,ZLAM!$C$2:$F$99999,4,0) -> 73.5 | L55: =I55*K55/100 -> 646.8 | M55: =L55/G55 -> 646.8 | N55: =L55/1.18 -> 548.13559 | O55: =N55/G55 -> 548.13559 | P55: =IFERROR(ABS(VLOOKUP($A55,ZTRV!$D$2:$G$99407,4,0)),0) -> 140 | Q55: =IFERROR(ABS(VLOOKUP($A55,ZTR1!$D$2:$G$99999,4,0)),0) -> 200 | R55: =IFERROR(ABS(VLOOKUP($A55,ZTR2!$D$2:$G$99939,4,0)),0) -> 0 | S55: =SUM(P55:R55)*G55 -> 340 | T55: =N55-S55 -> 208.13559 | U55: =T55*1.18 -> 245.6 | V55: =U55/G55 -> 245.6 | W55: =V55*F55 -> 2456 | X55: =I55-U55 -> 634.4 | Y55: =X55*H55 -> 6344 | Z55: =J55-V55 -> 634.4 | AA55: =IFERROR(ABS(VLOOKUP(A55,ZSSD!$D$2:$G$99933,4,0)),AI55) -> 8 | AB55: =IFERROR(IF(VLOOKUP(A55,ZSSD!$D:$H,5,0)="L29",AA55*G55,AA55*L55/100),AA55*L55/100) -> 51.744 | AC55: 2 | AD55: =2*(T55-AB55)/100 -> 3.1278319 | AE55: =+AB55/G55 -> 51.744 | AF55: =+AD55/G55 -> 3.1278319 | AG55: =VLOOKUP(A55,ZSSD!D:D,1,0) -> 2825185 | AH55: =VLOOKUP(B55,[2]GRADE!$A:$P,16,0) -> GOLD | AI55: =IF(AH55="SILVER",6.5,IF(AH55="GOLD",8,IF(AH55="INDUSTRIAL",6,IF(AH55="GREEN",7,IF(AH55="BRONZE",5.5,0))))) -> 8
A56: 2825195 | B56: 2825 | C56: 195 | D56: =VLOOKUP(C56,Sheet1!$A$2:$K$369991,11,0) -> CAR | E56: SERVO HYPERSPORT F5-4 X 2.5 L | F56: =VLOOKUP(C56,'PACK MASTER'!$A$2:$I$512998,9,0)*1000 -> 10 | G56: =VLOOKUP(C56,'PACK MASTER'!$A$2:$G$512998,7,0) -> 2.5 | H56: =F56/G56 -> 4 | I56: =VLOOKUP($A56,ZMRP!$C$2:$F$99995,4,0) -> 2190 | J56: =I56/G56 -> 876 | K56: =VLOOKUP($A56,ZLAM!$C$2:$F$99999,4,0) -> 73.5 | L56: =I56*K56/100 -> 1609.65 | M56: =L56/G56 -> 643.86 | N56: =L56/1.18 -> 1364.1102 | O56: =N56/G56 -> 545.64407 | P56: =IFERROR(ABS(VLOOKUP($A56,ZTRV!$D$2:$G$99407,4,0)),0) -> 0 | Q56: =IFERROR(ABS(VLOOKUP($A56,ZTR1!$D$2:$G$99999,4,0)),0) -> 0 | R56: =IFERROR(ABS(VLOOKUP($A56,ZTR2!$D$2:$G$99939,4,0)),0) -> 0 | S56: =SUM(P56:R56)*G56 -> 0 | T56: =N56-S56 -> 1364.1102 | U56: =T56*1.18 -> 1609.65 | V56: =U56/G56 -> 643.86 | W56: =V56*F56 -> 6438.6 | X56: =I56-U56 -> 580.35 | Y56: =X56*H56 -> 2321.4 | Z56: =J56-V56 -> 232.14 | AA56: =IFERROR(ABS(VLOOKUP(A56,ZSSD!$D$2:$G$99933,4,0)),AI56) -> 8 | AB56: =IFERROR(IF(VLOOKUP(A56,ZSSD!$D:$H,5,0)="L29",AA56*G56,AA56*L56/100),AA56*L56/100) -> 128.772 | AC56: 2 | AD56: =2*(T56-AB56)/100 -> 24.706763 | AE56: =+AB56/G56 -> 51.5088 | AF56: =+AD56/G56 -> 9.8827054 | AG56: =VLOOKUP(A56,ZSSD!D:D,1,0) -> #N/A | AH56: =VLOOKUP(B56,[2]GRADE!$A:$P,16,0) -> GOLD | AI56: =IF(AH56="SILVER",6.5,IF(AH56="GOLD",8,IF(AH56="INDUSTRIAL",6,IF(AH56="GREEN",7,IF(AH56="BRONZE",5.5,0))))) -> 8
A57: 2825258 | B57: =VALUE(LEFT(A57,4)) -> 2825 | C57: =VALUE(RIGHT(A57,3)) -> 258 | D57: =VLOOKUP(C57,Sheet1!$A$2:$K$369991,11,0) -> CAR | E57: SERVO HYPERSPORT F5-10 X 1 L PROMO | F57: =VLOOKUP(C57,'PACK MASTER'!$A$2:$I$512998,9,0)*1000 -> 10 | G57: =VLOOKUP(C57,'PACK MASTER'!$A$2:$G$512998,7,0) -> 1 | H57: =F57/G57 -> 10 | I57: =VLOOKUP($A57,ZMRP!$C$2:$F$99995,4,0) -> 880 | J57: =I57/G57 -> 880 | K57: =VLOOKUP($A57,ZLAM!$C$2:$F$99999,4,0) -> 73.5 | L57: =I57*K57/100 -> 646.8 | M57: =L57/G57 -> 646.8 | N57: =L57/1.18 -> 548.13559 | O57: =N57/G57 -> 548.13559 | P57: =IFERROR(ABS(VLOOKUP($A57,ZTRV!$D$2:$G$99407,4,0)),0) -> 40 | Q57: =IFERROR(ABS(VLOOKUP($A57,ZTR1!$D$2:$G$99999,4,0)),0) -> 200 | R57: =IFERROR(ABS(VLOOKUP($A57,ZTR2!$D$2:$G$99939,4,0)),0) -> 0 | S57: =SUM(P57:R57)*G57 -> 240 | T57: =N57-S57 -> 308.13559 | U57: =T57*1.18 -> 363.6 | V57: =U57/G57 -> 363.6 | W57: =V57*F57 -> 3636 | X57: =I57-U57 -> 516.4 | Y57: =X57*H57 -> 5164 | Z57: =J57-V57 -> 516.4 | AA57: =IFERROR(ABS(VLOOKUP(A57,ZSSD!$D$2:$G$99933,4,0)),AI57) -> 8 | AB57: =IFERROR(IF(VLOOKUP(A57,ZSSD!$D:$H,5,0)="L29",AA57*G57,AA57*L57/100),AA57*L57/100) -> 51.744 | AC57: 2 | AD57: =2*(T57-AB57)/100 -> 5.1278319 | AE57: =+AB57/G57 -> 51.744 | AF57: =+AD57/G57 -> 5.1278319 | AG57: =VLOOKUP(A57,ZSSD!D:D,1,0) -> 2825258 | AH57: =VLOOKUP(B57,[2]GRADE!$A:$P,16,0) -> GOLD | AI57: =IF(AH57="SILVER",6.5,IF(AH57="GOLD",8,IF(AH57="INDUSTRIAL",6,IF(AH57="GREEN",7,IF(AH57="BRONZE",5.5,0))))) -> 8
A58: 2828152 | B58: 2828 | C58: =VALUE(RIGHT(A58,3)) -> 152 | D58: CAR | E58: SERVO 4T XTRA-20 X 0.9 L | F58: =VLOOKUP(C58,'PACK MASTER'!$A$2:$I$512998,9,0)*1000 -> 18 | G58: =VLOOKUP(C58,'PACK MASTER'!$A$2:$G$512998,7,0) -> 0.9 | H58: =F58/G58 -> 20 | I58: =VLOOKUP($A58,ZMRP!$C$2:$F$99995,4,0) -> 422 | J58: =I58/G58 -> 468.88889 | K58: =VLOOKUP($A58,ZLAM!$C$2:$F$99999,4,0) -> 74.42 | L58: =I58*K58/100 -> 314.0524 | M58: =L58/G58 -> 348.94711 | N58: =L58/1.18 -> 266.1461 | O58: =N58/G58 -> 295.71789 | P58: =IFERROR(ABS(VLOOKUP($A58,ZTRV!$D$2:$G$99407,4,0)),0) -> 48 | Q58: =IFERROR(ABS(VLOOKUP($A58,ZTR1!$D$2:$G$99999,4,0)),0) -> 0 | R58: =IFERROR(ABS(VLOOKUP($A58,ZTR2!$D$2:$G$99939,4,0)),0) -> 0 | S58: =SUM(P58:R58)*G58 -> 43.2 | T58: =N58-S58 -> 222.9461 | U58: =T58*1.18 -> 263.0764 | V58: =U58/G58 -> 292.30711 | W58: =V58*F58 -> 5261.528 | X58: =I58-U58 -> 158.9236 | Y58: =X58*H58 -> 3178.472 | Z58: =J58-V58 -> 176.58178 | AA58: =IFERROR(ABS(VLOOKUP(A58,ZSSD!$D$2:$G$99933,4,0)),AI58) -> 8 | AB58: =IFERROR(IF(VLOOKUP(A58,ZSSD!$D:$H,5,0)="L29",AA58*G58,AA58*L58/100),AA58*L58/100) -> 25.124192 | AC58: 2 | AD58: =2*(T58-AB58)/100 -> 3.9564382 | AE58: =+AB58/G58 -> 27.915769 | AF58: =+AD58/G58 -> 4.3960424 | AG58: =VLOOKUP(A58,ZSSD!D:D,1,0) -> 2828152 | AH58: =VLOOKUP(B58,[2]GRADE!$A:$P,16,0) -> GOLD | AI58: =IF(AH58="SILVER",6.5,IF(AH58="GOLD",8,IF(AH58="INDUSTRIAL",6,IF(AH58="GREEN",7,IF(AH58="BRONZE",5.5,0))))) -> 8
A59: 2828181 | B59: =VALUE(LEFT(A59,4)) -> 2828 | C59: =VALUE(RIGHT(A59,3)) -> 181 | D59: =VLOOKUP(C59,Sheet1!$A$2:$K$369991,11,0) -> CAN | E59: SERVO 4T XTRA-1 L PROMO | F59: =VLOOKUP(C59,'PACK MASTER'!$A$2:$I$512998,9,0)*1000 -> 1 | G59: =VLOOKUP(C59,'PACK MASTER'!$A$2:$G$512998,7,0) -> 1 | H59: =F59/G59 -> 1 | I59: =VLOOKUP($A59,ZMRP!$C$2:$F$99995,4,0) -> 464 | J59: =I59/G59 -> 464 | K59: =VLOOKUP($A59,ZLAM!$C$2:$F$99999,4,0) -> 74.47 | L59: =I59*K59/100 -> 345.5408 | M59: =L59/G59 -> 345.5408 | N59: =L59/1.18 -> 292.83119 | O59: =N59/G59 -> 292.83119 | P59: =IFERROR(ABS(VLOOKUP($A59,ZTRV!$D$2:$G$99407,4,0)),0) -> 43 | Q59: =IFERROR(ABS(VLOOKUP($A59,ZTR1!$D$2:$G$99999,4,0)),0) -> 0 | R59: =IFERROR(ABS(VLOOKUP($A59,ZTR2!$D$2:$G$99939,4,0)),0) -> 0 | S59: =SUM(P59:R59)*G59 -> 43 | T59: =N59-S59 -> 249.83119 | U59: =T59*1.18 -> 294.8008 | V59: =U59/G59 -> 294.8008 | W59: =V59*F59 -> 294.8008 | X59: =I59-U59 -> 169.1992 | Y59: =X59*H59 -> 169.1992 | Z59: =J59-V59 -> 169.1992 | AA59: =IFERROR(ABS(VLOOKUP(A59,ZSSD!$D$2:$G$99933,4,0)),AI59) -> 8 | AB59: =IFERROR(IF(VLOOKUP(A59,ZSSD!$D:$H,5,0)="L29",AA59*G59,AA59*L59/100),AA59*L59/100) -> 27.643264 | AC59: 2 | AD59: =2*(T59-AB59)/100 -> 4.4437584 | AE59: =+AB59/G59 -> 27.643264 | AF59: =+AD59/G59 -> 4.4437584 | AG59: =VLOOKUP(A59,ZSSD!D:D,1,0) -> 2828181 | AH59: =VLOOKUP(B59,[2]GRADE!$A:$P,16,0) -> GOLD | AI59: =IF(AH59="SILVER",6.5,IF(AH59="GOLD",8,IF(AH59="INDUSTRIAL",6,IF(AH59="GREEN",7,IF(AH59="BRONZE",5.5,0))))) -> 8
A60: 2828184 | B60: 2828 | C60: =VALUE(RIGHT(A60,3)) -> 184 | D60: =VLOOKUP(C60,Sheet1!$A$2:$K$369991,11,0) -> CAR | E60: SERVO 4T XTRA-20 X 1 L | F60: =VLOOKUP(C60,'PACK MASTER'!$A$2:$I$512998,9,0)*1000 -> 20 | G60: =VLOOKUP(C60,'PACK MASTER'!$A$2:$G$512998,7,0) -> 1 | H60: =F60/G60 -> 20 | I60: =VLOOKUP($A60,ZMRP!$C$2:$F$99995,4,0) -> 464 | J60: =I60/G60 -> 464 | K60: =VLOOKUP($A60,ZLAM!$C$2:$F$99999,4,0) -> 74.47 | L60: =I60*K60/100 -> 345.5408 | M60: =L60/G60 -> 345.5408 | N60: =L60/1.18 -> 292.83119 | O60: =N60/G60 -> 292.83119 | P60: =IFERROR(ABS(VLOOKUP($A60,ZTRV!$D$2:$G$99407,4,0)),0) -> 48 | Q60: =IFERROR(ABS(VLOOKUP($A60,ZTR1!$D$2:$G$99999,4,0)),0) -> 0 | R60: =IFERROR(ABS(VLOOKUP($A60,ZTR2!$D$2:$G$99939,4,0)),0) -> 0 | S60: =SUM(P60:R60)*G60 -> 48 | T60: =N60-S60 -> 244.83119 | U60: =T60*1.18 -> 288.9008 | V60: =U60/G60 -> 288.9008 | W60: =V60*F60 -> 5778.016 | X60: =I60-U60 -> 175.0992 | Y60: =X60*H60 -> 3501.984 | Z60: =J60-V60 -> 175.0992 | AA60: =IFERROR(ABS(VLOOKUP(A60,ZSSD!$D$2:$G$99933,4,0)),AI60) -> 8 | AB60: =IFERROR(IF(VLOOKUP(A60,ZSSD!$D:$H,5,0)="L29",AA60*G60,AA60*L60/100),AA60*L60/100) -> 27.643264 | AC60: 2 | AD60: =2*(T60-AB60)/100 -> 4.3437584 | AE60: =+AB60/G60 -> 27.643264 | AF60: =+AD60/G60 -> 4.3437584 | AG60: =VLOOKUP(A60,ZSSD!D:D,1,0) -> 2828184 | AH60: =VLOOKUP(B60,[2]GRADE!$A:$P,16,0) -> GOLD | AI60: =IF(AH60="SILVER",6.5,IF(AH60="GOLD",8,IF(AH60="INDUSTRIAL",6,IF(AH60="GREEN",7,IF(AH60="BRONZE",5.5,0))))) -> 8
A61: 2828229 | B61: =VALUE(LEFT(A61,4)) -> 2828 | C61: =VALUE(RIGHT(A61,3)) -> 229 | D61: =VLOOKUP(C61,Sheet1!$A$2:$K$369991,11,0) -> CAR | E61: SERVO 4T XTRA-20 X 1 L PROMO | F61: =VLOOKUP(C61,'PACK MASTER'!$A$2:$I$512998,9,0)*1000 -> 20 | G61: =VLOOKUP(C61,'PACK MASTER'!$A$2:$G$512998,7,0) -> 1 | H61: =F61/G61 -> 20 | I61: =VLOOKUP($A61,ZMRP!$C$2:$F$99995,4,0) -> 464 | J61: =I61/G61 -> 464 | K61: =VLOOKUP($A61,ZLAM!$C$2:$F$99999,4,0) -> 74.47 | L61: =I61*K61/100 -> 345.5408 | M61: =L61/G61 -> 345.5408 | N61: =L61/1.18 -> 292.83119 | O61: =N61/G61 -> 292.83119 | P61: =IFERROR(ABS(VLOOKUP($A61,ZTRV!$D$2:$G$99407,4,0)),0) -> 43 | Q61: =IFERROR(ABS(VLOOKUP($A61,ZTR1!$D$2:$G$99999,4,0)),0) -> 0 | R61: =IFERROR(ABS(VLOOKUP($A61,ZTR2!$D$2:$G$99939,4,0)),0) -> 0 | S61: =SUM(P61:R61)*G61 -> 43 | T61: =N61-S61 -> 249.83119 | U61: =T61*1.18 -> 294.8008 | V61: =U61/G61 -> 294.8008 | W61: =V61*F61 -> 5896.016 | X61: =I61-U61 -> 169.1992 | Y61: =X61*H61 -> 3383.984 | Z61: =J61-V61 -> 169.1992 | AA61: =IFERROR(ABS(VLOOKUP(A61,ZSSD!$D$2:$G$99933,4,0)),AI61) -> 8 | AB61: =IFERROR(IF(VLOOKUP(A61,ZSSD!$D:$H,5,0)="L29",AA61*G61,AA61*L61/100),AA61*L61/100) -> 27.643264 | AC61: 2 | AD61: =2*(T61-AB61)/100 -> 4.4437584 | AE61: =+AB61/G61 -> 27.643264 | AF61: =+AD61/G61 -> 4.4437584 | AG61: =VLOOKUP(A61,ZSSD!D:D,1,0) -> 2828229 | AH61: =VLOOKUP(B61,[2]GRADE!$A:$P,16,0) -> GOLD | AI61: =IF(AH61="SILVER",6.5,IF(AH61="GOLD",8,IF(AH61="INDUSTRIAL",6,IF(AH61="GREEN",7,IF(AH61="BRONZE",5.5,0))))) -> 8
A62: 2828230 | B62: =VALUE(LEFT(A62,4)) -> 2828 | C62: =VALUE(RIGHT(A62,3)) -> 230 | D62: =VLOOKUP(C62,Sheet1!$A$2:$K$369991,11,0) -> CAR | E62: SERVO 4T XTRA-20 X 0.9 L PROMO | F62: =VLOOKUP(C62,'PACK MASTER'!$A$2:$I$512998,9,0)*1000 -> 18 | G62: =VLOOKUP(C62,'PACK MASTER'!$A$2:$G$512998,7,0) -> 0.9 | H62: =F62/G62 -> 20 | I62: =VLOOKUP($A62,ZMRP!$C$2:$F$99995,4,0) -> 422 | J62: =I62/G62 -> 468.88889 | K62: =VLOOKUP($A62,ZLAM!$C$2:$F$99999,4,0) -> 74.42 | L62: =I62*K62/100 -> 314.0524 | M62: =L62/G62 -> 348.94711 | N62: =L62/1.18 -> 266.1461 | O62: =N62/G62 -> 295.71789 | P62: =IFERROR(ABS(VLOOKUP($A62,ZTRV!$D$2:$G$99407,4,0)),0) -> 43 | Q62: =IFERROR(ABS(VLOOKUP($A62,ZTR1!$D$2:$G$99999,4,0)),0) -> 0 | R62: =IFERROR(ABS(VLOOKUP($A62,ZTR2!$D$2:$G$99939,4,0)),0) -> 0 | S62: =SUM(P62:R62)*G62 -> 38.7 | T62: =N62-S62 -> 227.4461 | U62: =T62*1.18 -> 268.3864 | V62: =U62/G62 -> 298.20711 | W62: =V62*F62 -> 5367.728 | X62: =I62-U62 -> 153.6136 | Y62: =X62*H62 -> 3072.272 | Z62: =J62-V62 -> 170.68178 | AA62: =IFERROR(ABS(VLOOKUP(A62,ZSSD!$D$2:$G$99933,4,0)),AI62) -> 8 | AB62: =IFERROR(IF(VLOOKUP(A62,ZSSD!$D:$H,5,0)="L29",AA62*G62,AA62*L62/100),AA62*L62/100) -> 25.124192 | AC62: 2 | AD62: =2*(T62-AB62)/100 -> 4.0464382 | AE62: =+AB62/G62 -> 27.915769 | AF62: =+AD62/G62 -> 4.4960424 | AG62: =VLOOKUP(A62,ZSSD!D:D,1,0) -> 2828230 | AH62: =VLOOKUP(B62,[2]GRADE!$A:$P,16,0) -> GOLD | AI62: =IF(AH62="SILVER",6.5,IF(AH62="GOLD",8,IF(AH62="INDUSTRIAL",6,IF(AH62="GREEN",7,IF(AH62="BRONZE",5.5,0))))) -> 8
A63: 2829152 | B63: =VALUE(LEFT(A63,4)) -> 2829 | C63: =VALUE(RIGHT(A63,3)) -> 152 | D63: =VLOOKUP(C63,Sheet1!$A$2:$K$369991,11,0) -> CAR | E63: SERVO 4T XTRA 10W-30-20 X 0.9 L | F63: =VLOOKUP(C63,'PACK MASTER'!$A$2:$I$512998,9,0)*1000 -> 18 | G63: =VLOOKUP(C63,'PACK MASTER'!$A$2:$G$512998,7,0) -> 0.9 | H63: =F63/G63 -> 20 | I63: =VLOOKUP($A63,ZMRP!$C$2:$F$99995,4,0) -> 422 | J63: =I63/G63 -> 468.88889 | K63: =VLOOKUP($A63,ZLAM!$C$2:$F$99999,4,0) -> 74.42 | L63: =I63*K63/100 -> 314.0524 | M63: =L63/G63 -> 348.94711 | N63: =L63/1.18 -> 266.1461 | O63: =N63/G63 -> 295.71789 | P63: =IFERROR(ABS(VLOOKUP($A63,ZTRV!$D$2:$G$99407,4,0)),0) -> 48 | Q63: =IFERROR(ABS(VLOOKUP($A63,ZTR1!$D$2:$G$99999,4,0)),0) -> 0 | R63: =IFERROR(ABS(VLOOKUP($A63,ZTR2!$D$2:$G$99939,4,0)),0) -> 0 | S63: =SUM(P63:R63)*G63 -> 43.2 | T63: =N63-S63 -> 222.9461 | U63: =T63*1.18 -> 263.0764 | V63: =U63/G63 -> 292.30711 | W63: =V63*F63 -> 5261.528 | X63: =I63-U63 -> 158.9236 | Y63: =X63*H63 -> 3178.472 | Z63: =J63-V63 -> 176.58178 | AA63: =IFERROR(ABS(VLOOKUP(A63,ZSSD!$D$2:$G$99933,4,0)),AI63) -> 8 | AB63: =IFERROR(IF(VLOOKUP(A63,ZSSD!$D:$H,5,0)="L29",AA63*G63,AA63*L63/100),AA63*L63/100) -> 25.124192 | AC63: 2 | AD63: =2*(T63-AB63)/100 -> 3.9564382 | AE63: =+AB63/G63 -> 27.915769 | AF63: =+AD63/G63 -> 4.3960424 | AG63: =VLOOKUP(A63,ZSSD!D:D,1,0) -> 2829152 | AH63: =VLOOKUP(B63,[2]GRADE!$A:$P,16,0) -> GOLD | AI63: =IF(AH63="SILVER",6.5,IF(AH63="GOLD",8,IF(AH63="INDUSTRIAL",6,IF(AH63="GREEN",7,IF(AH63="BRONZE",5.5,0))))) -> 8
A64: 2829184 | B64: =VALUE(LEFT(A64,4)) -> 2829 | C64: =VALUE(RIGHT(A64,3)) -> 184 | D64: =VLOOKUP(C64,Sheet1!$A$2:$K$369991,11,0) -> CAR | E64: SERVO 4T XTRA 10W-30-20 X 1 L | F64: =VLOOKUP(C64,'PACK MASTER'!$A$2:$I$512998,9,0)*1000 -> 20 | G64: =VLOOKUP(C64,'PACK MASTER'!$A$2:$G$512998,7,0) -> 1 | H64: =F64/G64 -> 20 | I64: =VLOOKUP($A64,ZMRP!$C$2:$F$99995,4,0) -> 464 | J64: =I64/G64 -> 464 | K64: =VLOOKUP($A64,ZLAM!$C$2:$F$99999,4,0) -> 74.47 | L64: =I64*K64/100 -> 345.5408 | M64: =L64/G64 -> 345.5408 | N64: =L64/1.18 -> 292.83119 | O64: =N64/G64 -> 292.83119 | P64: =IFERROR(ABS(VLOOKUP($A64,ZTRV!$D$2:$G$99407,4,0)),0) -> 48 | Q64: =IFERROR(ABS(VLOOKUP($A64,ZTR1!$D$2:$G$99999,4,0)),0) -> 0 | R64: =IFERROR(ABS(VLOOKUP($A64,ZTR2!$D$2:$G$99939,4,0)),0) -> 0 | S64: =SUM(P64:R64)*G64 -> 48 | T64: =N64-S64 -> 244.83119 | U64: =T64*1.18 -> 288.9008 | V64: =U64/G64 -> 288.9008 | W64: =V64*F64 -> 5778.016 | X64: =I64-U64 -> 175.0992 | Y64: =X64*H64 -> 3501.984 | Z64: =J64-V64 -> 175.0992 | AA64: =IFERROR(ABS(VLOOKUP(A64,ZSSD!$D$2:$G$99933,4,0)),AI64) -> 8 | AB64: =IFERROR(IF(VLOOKUP(A64,ZSSD!$D:$H,5,0)="L29",AA64*G64,AA64*L64/100),AA64*L64/100) -> 27.643264 | AC64: 2 | AD64: =2*(T64-AB64)/100 -> 4.3437584 | AE64: =+AB64/G64 -> 27.643264 | AF64: =+AD64/G64 -> 4.3437584 | AG64: =VLOOKUP(A64,ZSSD!D:D,1,0) -> 2829184 | AH64: =VLOOKUP(B64,[2]GRADE!$A:$P,16,0) -> GOLD | AI64: =IF(AH64="SILVER",6.5,IF(AH64="GOLD",8,IF(AH64="INDUSTRIAL",6,IF(AH64="GREEN",7,IF(AH64="BRONZE",5.5,0))))) -> 8
A65: 2829229 | B65: =VALUE(LEFT(A65,4)) -> 2829 | C65: =VALUE(RIGHT(A65,3)) -> 229 | D65: =VLOOKUP(C65,Sheet1!$A$2:$K$369991,11,0) -> CAR | E65: SERVO 4T XTRA 10W-30-20 X 1 L PROMO | F65: =VLOOKUP(C65,'PACK MASTER'!$A$2:$I$512998,9,0)*1000 -> 20 | G65: =VLOOKUP(C65,'PACK MASTER'!$A$2:$G$512998,7,0) -> 1 | H65: =F65/G65 -> 20 | I65: =VLOOKUP($A65,ZMRP!$C$2:$F$99995,4,0) -> 464 | J65: =I65/G65 -> 464 | K65: =VLOOKUP($A65,ZLAM!$C$2:$F$99999,4,0) -> 74.47 | L65: =I65*K65/100 -> 345.5408 | M65: =L65/G65 -> 345.5408 | N65: =L65/1.18 -> 292.83119 | O65: =N65/G65 -> 292.83119 | P65: =IFERROR(ABS(VLOOKUP($A65,ZTRV!$D$2:$G$99407,4,0)),0) -> 43 | Q65: =IFERROR(ABS(VLOOKUP($A65,ZTR1!$D$2:$G$99999,4,0)),0) -> 0 | R65: =IFERROR(ABS(VLOOKUP($A65,ZTR2!$D$2:$G$99939,4,0)),0) -> 0 | S65: =SUM(P65:R65)*G65 -> 43 | T65: =N65-S65 -> 249.83119 | U65: =T65*1.18 -> 294.8008 | V65: =U65/G65 -> 294.8008 | W65: =V65*F65 -> 5896.016 | X65: =I65-U65 -> 169.1992 | Y65: =X65*H65 -> 3383.984 | Z65: =J65-V65 -> 169.1992 | AA65: =IFERROR(ABS(VLOOKUP(A65,ZSSD!$D$2:$G$99933,4,0)),AI65) -> 8 | AB65: =IFERROR(IF(VLOOKUP(A65,ZSSD!$D:$H,5,0)="L29",AA65*G65,AA65*L65/100),AA65*L65/100) -> 27.643264 | AC65: 2 | AD65: =2*(T65-AB65)/100 -> 4.4437584 | AE65: =+AB65/G65 -> 27.643264 | AF65: =+AD65/G65 -> 4.4437584 | AG65: =VLOOKUP(A65,ZSSD!D:D,1,0) -> 2829229 | AH65: =VLOOKUP(B65,[2]GRADE!$A:$P,16,0) -> GOLD | AI65: =IF(AH65="SILVER",6.5,IF(AH65="GOLD",8,IF(AH65="INDUSTRIAL",6,IF(AH65="GREEN",7,IF(AH65="BRONZE",5.5,0))))) -> 8
A66: 2829230 | B66: =VALUE(LEFT(A66,4)) -> 2829 | C66: =VALUE(RIGHT(A66,3)) -> 230 | D66: =VLOOKUP(C66,Sheet1!$A$2:$K$369991,11,0) -> CAR | E66: SERVO 4T XTRA 10W-30-20 X 0.9 L PROMO | F66: =VLOOKUP(C66,'PACK MASTER'!$A$2:$I$512998,9,0)*1000 -> 18 | G66: =VLOOKUP(C66,'PACK MASTER'!$A$2:$G$512998,7,0) -> 0.9 | H66: =F66/G66 -> 20 | I66: =VLOOKUP($A66,ZMRP!$C$2:$F$99995,4,0) -> 422 | J66: =I66/G66 -> 468.88889 | K66: =VLOOKUP($A66,ZLAM!$C$2:$F$99999,4,0) -> 74.42 | L66: =I66*K66/100 -> 314.0524 | M66: =L66/G66 -> 348.94711 | N66: =L66/1.18 -> 266.1461 | O66: =N66/G66 -> 295.71789 | P66: =IFERROR(ABS(VLOOKUP($A66,ZTRV!$D$2:$G$99407,4,0)),0) -> 43 | Q66: =IFERROR(ABS(VLOOKUP($A66,ZTR1!$D$2:$G$99999,4,0)),0) -> 0 | R66: =IFERROR(ABS(VLOOKUP($A66,ZTR2!$D$2:$G$99939,4,0)),0) -> 0 | S66: =SUM(P66:R66)*G66 -> 38.7 | T66: =N66-S66 -> 227.4461 | U66: =T66*1.18 -> 268.3864 | V66: =U66/G66 -> 298.20711 | W66: =V66*F66 -> 5367.728 | X66: =I66-U66 -> 153.6136 | Y66: =X66*H66 -> 3072.272 | Z66: =J66-V66 -> 170.68178 | AA66: =IFERROR(ABS(VLOOKUP(A66,ZSSD!$D$2:$G$99933,4,0)),AI66) -> 8 | AB66: =IFERROR(IF(VLOOKUP(A66,ZSSD!$D:$H,5,0)="L29",AA66*G66,AA66*L66/100),AA66*L66/100) -> 25.124192 | AC66: 2 | AD66: =2*(T66-AB66)/100 -> 4.0464382 | AE66: =+AB66/G66 -> 27.915769 | AF66: =+AD66/G66 -> 4.4960424 | AG66: =VLOOKUP(A66,ZSSD!D:D,1,0) -> 2829230 | AH66: =VLOOKUP(B66,[2]GRADE!$A:$P,16,0) -> GOLD | AI66: =IF(AH66="SILVER",6.5,IF(AH66="GOLD",8,IF(AH66="INDUSTRIAL",6,IF(AH66="GREEN",7,IF(AH66="BRONZE",5.5,0))))) -> 8
A67: 2830229 | B67: =VALUE(LEFT(A67,4)) -> 2830 | C67: =VALUE(RIGHT(A67,3)) -> 229 | D67: =VLOOKUP(C67,Sheet1!$A$2:$K$369991,11,0) -> CAR | E67: SERVO 4T XTRA 20W-50-20 X 1 L PROMO | F67: =VLOOKUP(C67,'PACK MASTER'!$A$2:$I$512998,9,0)*1000 -> 20 | G67: =VLOOKUP(C67,'PACK MASTER'!$A$2:$G$512998,7,0) -> 1 | H67: =F67/G67 -> 20 | I67: =VLOOKUP($A67,ZMRP!$C$2:$F$99995,4,0) -> 464 | J67: =I67/G67 -> 464 | K67: =VLOOKUP($A67,ZLAM!$C$2:$F$99999,4,0) -> 74.47 | L67: =I67*K67/100 -> 345.5408 | M67: =L67/G67 -> 345.5408 | N67: =L67/1.18 -> 292.83119 | O67: =N67/G67 -> 292.83119 | P67: =IFERROR(ABS(VLOOKUP($A67,ZTRV!$D$2:$G$99407,4,0)),0) -> 43 | Q67: =IFERROR(ABS(VLOOKUP($A67,ZTR1!$D$2:$G$99999,4,0)),0) -> 0 | R67: =IFERROR(ABS(VLOOKUP($A67,ZTR2!$D$2:$G$99939,4,0)),0) -> 0 | S67: =SUM(P67:R67)*G67 -> 43 | T67: =N67-S67 -> 249.83119 | U67: =T67*1.18 -> 294.8008 | V67: =U67/G67 -> 294.8008 | W67: =V67*F67 -> 5896.016 | X67: =I67-U67 -> 169.1992 | Y67: =X67*H67 -> 3383.984 | Z67: =J67-V67 -> 169.1992 | AA67: =IFERROR(ABS(VLOOKUP(A67,ZSSD!$D$2:$G$99933,4,0)),AI67) -> 8 | AB67: =IFERROR(IF(VLOOKUP(A67,ZSSD!$D:$H,5,0)="L29",AA67*G67,AA67*L67/100),AA67*L67/100) -> 27.643264 | AC67: 2 | AD67: =2*(T67-AB67)/100 -> 4.4437584 | AE67: =+AB67/G67 -> 27.643264 | AF67: =+AD67/G67 -> 4.4437584 | AG67: =VLOOKUP(A67,ZSSD!D:D,1,0) -> 2830229 | AH67: =VLOOKUP(B67,[2]GRADE!$A:$P,16,0) -> GOLD | AI67: =IF(AH67="SILVER",6.5,IF(AH67="GOLD",8,IF(AH67="INDUSTRIAL",6,IF(AH67="GREEN",7,IF(AH67="BRONZE",5.5,0))))) -> 8
A68: 2830230 | B68: =VALUE(LEFT(A68,4)) -> 2830 | C68: =VALUE(RIGHT(A68,3)) -> 230 | D68: =VLOOKUP(C68,Sheet1!$A$2:$K$369991,11,0) -> CAR | E68: SERVO 4T XTRA 20W-50-20 X 0.9 L PROMO | F68: =VLOOKUP(C68,'PACK MASTER'!$A$2:$I$512998,9,0)*1000 -> 18 | G68: =VLOOKUP(C68,'PACK MASTER'!$A$2:$G$512998,7,0) -> 0.9 | H68: =F68/G68 -> 20 | I68: =VLOOKUP($A68,ZMRP!$C$2:$F$99995,4,0) -> 422 | J68: =I68/G68 -> 468.88889 | K68: =VLOOKUP($A68,ZLAM!$C$2:$F$99999,4,0) -> 74.42 | L68: =I68*K68/100 -> 314.0524 | M68: =L68/G68 -> 348.94711 | N68: =L68/1.18 -> 266.1461 | O68: =N68/G68 -> 295.71789 | P68: =IFERROR(ABS(VLOOKUP($A68,ZTRV!$D$2:$G$99407,4,0)),0) -> 43 | Q68: =IFERROR(ABS(VLOOKUP($A68,ZTR1!$D$2:$G$99999,4,0)),0) -> 0 | R68: =IFERROR(ABS(VLOOKUP($A68,ZTR2!$D$2:$G$99939,4,0)),0) -> 0 | S68: =SUM(P68:R68)*G68 -> 38.7 | T68: =N68-S68 -> 227.4461 | U68: =T68*1.18 -> 268.3864 | V68: =U68/G68 -> 298.20711 | W68: =V68*F68 -> 5367.728 | X68: =I68-U68 -> 153.6136 | Y68: =X68*H68 -> 3072.272 | Z68: =J68-V68 -> 170.68178 | AA68: =IFERROR(ABS(VLOOKUP(A68,ZSSD!$D$2:$G$99933,4,0)),AI68) -> 8 | AB68: =IFERROR(IF(VLOOKUP(A68,ZSSD!$D:$H,5,0)="L29",AA68*G68,AA68*L68/100),AA68*L68/100) -> 25.124192 | AC68: 2 | AD68: =2*(T68-AB68)/100 -> 4.0464382 | AE68: =+AB68/G68 -> 27.915769 | AF68: =+AD68/G68 -> 4.4960424 | AG68: =VLOOKUP(A68,ZSSD!D:D,1,0) -> 2830230 | AH68: =VLOOKUP(B68,[2]GRADE!$A:$P,16,0) -> GOLD | AI68: =IF(AH68="SILVER",6.5,IF(AH68="GOLD",8,IF(AH68="INDUSTRIAL",6,IF(AH68="GREEN",7,IF(AH68="BRONZE",5.5,0))))) -> 8
A69: 2844024 | B69: =VALUE(LEFT(A69,4)) -> 2844 | C69: =VALUE(RIGHT(A69,3)) -> 24 | D69: =VLOOKUP(C69,Sheet1!$A$2:$K$369991,11,0) -> CAR | E69: HERO XOTIC+ 10W30-10 X 1.2 L | F69: =VLOOKUP(C69,'PACK MASTER'!$A$2:$I$512998,9,0)*1000 -> 12 | G69: =VLOOKUP(C69,'PACK MASTER'!$A$2:$G$512998,7,0) -> 1.2 | H69: =F69/G69 -> 10 | I69: =VLOOKUP($A69,ZMRP!$C$2:$F$99995,4,0) -> 1150 | J69: =I69/G69 -> 958.33333 | K69: =VLOOKUP($A69,ZLAM!$C$2:$F$99999,4,0) -> 50.28 | L69: =I69*K69/100 -> 578.22 | M69: =L69/G69 -> 481.85 | N69: =L69/1.18 -> 490.01695 | O69: =N69/G69 -> 408.34746 | P69: =IFERROR(ABS(VLOOKUP($A69,ZTRV!$D$2:$G$99407,4,0)),0) -> 0 | Q69: =IFERROR(ABS(VLOOKUP($A69,ZTR1!$D$2:$G$99999,4,0)),0) -> 0 | R69: =IFERROR(ABS(VLOOKUP($A69,ZTR2!$D$2:$G$99939,4,0)),0) -> 0 | S69: =SUM(P69:R69)*G69 -> 0 | T69: =N69-S69 -> 490.01695 | U69: =T69*1.18 -> 578.22 | V69: =U69/G69 -> 481.85 | W69: =V69*F69 -> 5782.2 | X69: =I69-U69 -> 571.78 | Y69: =X69*H69 -> 5717.8 | Z69: =J69-V69 -> 476.48333 | AA69: =IFERROR(ABS(VLOOKUP(A69,ZSSD!$D$2:$G$99933,4,0)),AI69) -> 6.5 | AB69: =IFERROR(IF(VLOOKUP(A69,ZSSD!$D:$H,5,0)="L29",AA69*G69,AA69*L69/100),AA69*L69/100) -> 37.5843 | AC69: 2 | AD69: =2*(T69-AB69)/100 -> 9.048653 | AE69: =+AB69/G69 -> 31.32025 | AF69: =+AD69/G69 -> 7.5405442 | AG69: =VLOOKUP(A69,ZSSD!D:D,1,0) -> #N/A | AH69: =VLOOKUP(B69,[2]GRADE!$A:$P,16,0) -> SILVER | AI69: =IF(AH69="SILVER",6.5,IF(AH69="GOLD",8,IF(AH69="INDUSTRIAL",6,IF(AH69="GREEN",7,IF(AH69="BRONZE",5.5,0))))) -> 6.5
A70: 2889132 | B70: =VALUE(LEFT(A70,4)) -> 2889 | C70: =VALUE(RIGHT(A70,3)) -> 132 | D70: =VLOOKUP(C70,Sheet1!$A$2:$K$369991,11,0) -> CAR | E70: SERVO SCOOTOMTC 4ST 10W30-10X0.8 L PROMO | F70: =VLOOKUP(C70,'PACK MASTER'!$A$2:$I$512998,9,0)*1000 -> 8 | G70: =VLOOKUP(C70,'PACK MASTER'!$A$2:$G$512998,7,0) -> 0.8 | H70: =F70/G70 -> 10 | I70: =VLOOKUP($A70,ZMRP!$C$2:$F$99995,4,0) -> 342 | J70: =I70/G70 -> 427.5 | K70: =VLOOKUP($A70,ZLAM!$C$2:$F$99999,4,0) -> 67.7 | L70: =I70*K70/100 -> 231.534 | M70: =L70/G70 -> 289.4175 | N70: =L70/1.18 -> 196.21525 | O70: =N70/G70 -> 245.26907 | P70: =IFERROR(ABS(VLOOKUP($A70,ZTRV!$D$2:$G$99407,4,0)),0) -> 0 | Q70: =IFERROR(ABS(VLOOKUP($A70,ZTR1!$D$2:$G$99999,4,0)),0) -> 0 | R70: =IFERROR(ABS(VLOOKUP($A70,ZTR2!$D$2:$G$99939,4,0)),0) -> 0 | S70: =SUM(P70:R70)*G70 -> 0 | T70: =N70-S70 -> 196.21525 | U70: =T70*1.18 -> 231.534 | V70: =U70/G70 -> 289.4175 | W70: =V70*F70 -> 2315.34 | X70: =I70-U70 -> 110.466 | Y70: =X70*H70 -> 1104.66 | Z70: =J70-V70 -> 138.0825 | AA70: =IFERROR(ABS(VLOOKUP(A70,ZSSD!$D$2:$G$99933,4,0)),AI70) -> 6.5 | AB70: =IFERROR(IF(VLOOKUP(A70,ZSSD!$D:$H,5,0)="L29",AA70*G70,AA70*L70/100),AA70*L70/100) -> 15.04971 | AC70: 2 | AD70: =2*(T70-AB70)/100 -> 3.6233109 | AE70: =+AB70/G70 -> 18.812138 | AF70: =+AD70/G70 -> 4.5291386 | AG70: =VLOOKUP(A70,ZSSD!D:D,1,0) -> #N/A | AH70: =VLOOKUP(B70,[2]GRADE!$A:$P,16,0) -> SILVER | AI70: =IF(AH70="SILVER",6.5,IF(AH70="GOLD",8,IF(AH70="INDUSTRIAL",6,IF(AH70="GREEN",7,IF(AH70="BRONZE",5.5,0))))) -> 6.5
A71: 2889133 | B71: =VALUE(LEFT(A71,4)) -> 2889 | C71: =VALUE(RIGHT(A71,3)) -> 133 | D71: =VLOOKUP(C71,Sheet1!$A$2:$K$369991,11,0) -> CAR | E71: SERVO S.MC 4ST10W30-20X0.8 L PROMO | F71: =VLOOKUP(C71,'PACK MASTER'!$A$2:$I$512998,9,0)*1000 -> 16 | G71: =VLOOKUP(C71,'PACK MASTER'!$A$2:$G$512998,7,0) -> 0.8 | H71: =F71/G71 -> 20 | I71: =VLOOKUP($A71,ZMRP!$C$2:$F$99995,4,0) -> 342 | J71: =I71/G71 -> 427.5 | K71: =VLOOKUP($A71,ZLAM!$C$2:$F$99999,4,0) -> 67.7 | L71: =I71*K71/100 -> 231.534 | M71: =L71/G71 -> 289.4175 | N71: =L71/1.18 -> 196.21525 | O71: =N71/G71 -> 245.26907 | P71: =IFERROR(ABS(VLOOKUP($A71,ZTRV!$D$2:$G$99407,4,0)),0) -> 0 | Q71: =IFERROR(ABS(VLOOKUP($A71,ZTR1!$D$2:$G$99999,4,0)),0) -> 0 | R71: =IFERROR(ABS(VLOOKUP($A71,ZTR2!$D$2:$G$99939,4,0)),0) -> 0 | S71: =SUM(P71:R71)*G71 -> 0 | T71: =N71-S71 -> 196.21525 | U71: =T71*1.18 -> 231.534 | V71: =U71/G71 -> 289.4175 | W71: =V71*F71 -> 4630.68 | X71: =I71-U71 -> 110.466 | Y71: =X71*H71 -> 2209.32 | Z71: =J71-V71 -> 138.0825 | AA71: =IFERROR(ABS(VLOOKUP(A71,ZSSD!$D$2:$G$99933,4,0)),AI71) -> 6.5 | AB71: =IFERROR(IF(VLOOKUP(A71,ZSSD!$D:$H,5,0)="L29",AA71*G71,AA71*L71/100),AA71*L71/100) -> 15.04971 | AC71: 2 | AD71: =2*(T71-AB71)/100 -> 3.6233109 | AE71: =+AB71/G71 -> 18.812138 | AF71: =+AD71/G71 -> 4.5291386 | AG71: =VLOOKUP(A71,ZSSD!D:D,1,0) -> #N/A | AH71: =VLOOKUP(B71,[2]GRADE!$A:$P,16,0) -> SILVER | AI71: =IF(AH71="SILVER",6.5,IF(AH71="GOLD",8,IF(AH71="INDUSTRIAL",6,IF(AH71="GREEN",7,IF(AH71="BRONZE",5.5,0))))) -> 6.5
A72: 2889156 | B72: =VALUE(LEFT(A72,4)) -> 2889 | C72: =VALUE(RIGHT(A72,3)) -> 156 | D72: =VLOOKUP(C72,Sheet1!$A$2:$K$369991,11,0) -> CAR | E72: SERVO SCOOTOMATIC 4ST 10W-30-20 X 0.8 L | F72: =VLOOKUP(C72,'PACK MASTER'!$A$2:$I$512998,9,0)*1000 -> 16 | G72: =VLOOKUP(C72,'PACK MASTER'!$A$2:$G$512998,7,0) -> 0.8 | H72: =F72/G72 -> 20 | I72: =VLOOKUP($A72,ZMRP!$C$2:$F$99995,4,0) -> 342 | J72: =I72/G72 -> 427.5 | K72: =VLOOKUP($A72,ZLAM!$C$2:$F$99999,4,0) -> 67.7 | L72: =I72*K72/100 -> 231.534 | M72: =L72/G72 -> 289.4175 | N72: =L72/1.18 -> 196.21525 | O72: =N72/G72 -> 245.26907 | P72: =IFERROR(ABS(VLOOKUP($A72,ZTRV!$D$2:$G$99407,4,0)),0) -> 40 | Q72: =IFERROR(ABS(VLOOKUP($A72,ZTR1!$D$2:$G$99999,4,0)),0) -> 0 | R72: =IFERROR(ABS(VLOOKUP($A72,ZTR2!$D$2:$G$99939,4,0)),0) -> 0 | S72: =SUM(P72:R72)*G72 -> 32 | T72: =N72-S72 -> 164.21525 | U72: =T72*1.18 -> 193.774 | V72: =U72/G72 -> 242.2175 | W72: =V72*F72 -> 3875.48 | X72: =I72-U72 -> 148.226 | Y72: =X72*H72 -> 2964.52 | Z72: =J72-V72 -> 185.2825 | AA72: =IFERROR(ABS(VLOOKUP(A72,ZSSD!$D$2:$G$99933,4,0)),AI72) -> 6.5 | AB72: =IFERROR(IF(VLOOKUP(A72,ZSSD!$D:$H,5,0)="L29",AA72*G72,AA72*L72/100),AA72*L72/100) -> 15.04971 | AC72: 2 | AD72: =2*(T72-AB72)/100 -> 2.9833109 | AE72: =+AB72/G72 -> 18.812138 | AF72: =+AD72/G72 -> 3.7291386 | AG72: =VLOOKUP(A72,ZSSD!D:D,1,0) -> #N/A | AH72: =VLOOKUP(B72,[2]GRADE!$A:$P,16,0) -> SILVER | AI72: =IF(AH72="SILVER",6.5,IF(AH72="GOLD",8,IF(AH72="INDUSTRIAL",6,IF(AH72="GREEN",7,IF(AH72="BRONZE",5.5,0))))) -> 6.5
... A184: 5049203 | B184: =VALUE(LEFT(A184,4)) -> 5049 | C184: =VALUE(RIGHT(A184,3)) -> 203 | D184: =VLOOKUP(C184,Sheet1!$A$2:$K$369991,11,0) -> CAR | E184: TMGO GAS ENGINE OIL 15W-40 LL-4 X 3 L | F184: =VLOOKUP(C184,'PACK MASTER'!$A$2:$I$512998,9,0)*1000 -> 12 | G184: =VLOOKUP(C184,'PACK MASTER'!$A$2:$G$512998,7,0) -> 3 | H184: =F184/G184 -> 4 | I184: =VLOOKUP($A184,ZMRP!$C$2:$F$99995,4,0) -> 1039 | J184: =I184/G184 -> 346.33333 | K184: =VLOOKUP($A184,ZLAM!$C$2:$F$99999,4,0) -> 66.67 | L184: =I184*K184/100 -> 692.7013 | M184: =L184/G184 -> 230.90043 | N184: =L184/1.18 -> 587.035 | O184: =N184/G184 -> 195.67833 | P184: =IFERROR(ABS(VLOOKUP($A184,ZTRV!$D$2:$G$99407,4,0)),0) -> 0 | Q184: =IFERROR(ABS(VLOOKUP($A184,ZTR1!$D$2:$G$99999,4,0)),0) -> 0 | R184: =IFERROR(ABS(VLOOKUP($A184,ZTR2!$D$2:$G$99939,4,0)),0) -> 0 | S184: =SUM(P184:R184)*G184 -> 0 | T184: =N184-S184 -> 587.035 | U184: =T184*1.18 -> 692.7013 | V184: =U184/G184 -> 230.90043 | W184: =V184*F184 -> 2770.8052 | X184: =I184-U184 -> 346.2987 | Y184: =X184*H184 -> 1385.1948 | Z184: =J184-V184 -> 115.4329 | AA184: =IFERROR(ABS(VLOOKUP(A184,ZSSD!$D$2:$G$99933,4,0)),AI184) -> 6.5 | AB184: =IFERROR(IF(VLOOKUP(A184,ZSSD!$D:$H,5,0)="L29",AA184*G184,AA184*L184/100),AA184*L184/100) -> 45.025585 | AC184: 2 | AD184: =2*(T184-AB184)/100 -> 10.840188 | AE184: =+AB184/G184 -> 15.008528 | AF184: =+AD184/G184 -> 3.6133961 | AG184: =VLOOKUP(A184,ZSSD!D:D,1,0) -> #N/A | AH184: =VLOOKUP(B184,[2]GRADE!$A:$P,16,0) -> SILVER | AI184: =IF(AH184="SILVER",6.5,IF(AH184="GOLD",8,IF(AH184="INDUSTRIAL",6,IF(AH184="GREEN",7,IF(AH184="BRONZE",5.5,0))))) -> 6.5
A185: 6488184 | B185: 6488 | C185: 184 | D185: =VLOOKUP(C185,Sheet1!$A$2:$K$369991,11,0) -> CAR | E185: SERVO TROPIKOOL-20 X 1 L | F185: =VLOOKUP(C185,'PACK MASTER'!$A$2:$I$512998,9,0)*1000 -> 20 | G185: =VLOOKUP(C185,'PACK MASTER'!$A$2:$G$512998,7,0) -> 1 | H185: =F185/G185 -> 20 | I185: =VLOOKUP($A185,ZMRP!$C$2:$F$99995,4,0) -> 250 | J185: =I185/G185 -> 250 | K185: =VLOOKUP($A185,ZLAM!$C$2:$F$99999,4,0) -> 50 | L185: =I185*K185/100 -> 125 | M185: =L185/G185 -> 125 | N185: =L185/1.18 -> 105.9322 | O185: =N185/G185 -> 105.9322 | P185: =IFERROR(ABS(VLOOKUP($A185,ZTRV!$D$2:$G$99407,4,0)),0) -> 0 | Q185: =IFERROR(ABS(VLOOKUP($A185,ZTR1!$D$2:$G$99999,4,0)),0) -> 0 | R185: =IFERROR(ABS(VLOOKUP($A185,ZTR2!$D$2:$G$99939,4,0)),0) -> 0 | S185: =SUM(P185:R185)*G185 -> 0 | T185: =N185-S185 -> 105.9322 | U185: =T185*1.18 -> 125 | V185: =U185/G185 -> 125 | W185: =V185*F185 -> 2500 | X185: =I185-U185 -> 125 | Y185: =X185*H185 -> 2500 | Z185: =J185-V185 -> 125 | AA185: =IFERROR(ABS(VLOOKUP(A185,ZSSD!$D$2:$G$99933,4,0)),AI185) -> 5.5 | AB185: =IFERROR(IF(VLOOKUP(A185,ZSSD!$D:$H,5,0)="L29",AA185*G185,AA185*L185/100),AA185*L185/100) -> 6.875 | AC185: 2 | AD185: =2*(T185-AB185)/100 -> 1.9811441 | AE185: =+AB185/G185 -> 6.875 | AF185: =+AD185/G185 -> 1.9811441 | AG185: =VLOOKUP(A185,ZSSD!D:D,1,0) -> 6488184 | AH185: =VLOOKUP(B185,[2]GRADE!$A:$P,16,0) -> SILVER | AI185: =IF(AH185="SILVER",6.5,IF(AH185="GOLD",8,IF(AH185="INDUSTRIAL",6,IF(AH185="GREEN",7,IF(AH185="BRONZE",5.5,0))))) -> 6.5
A186: 6489184 | B186: 6489 | C186: 184 | D186: =VLOOKUP(C186,Sheet1!$A$2:$K$369991,11,0) -> CAR | E186: SERVO TROPIKOOL READY-20 X 1 L | F186: =VLOOKUP(C186,'PACK MASTER'!$A$2:$I$512998,9,0)*1000 -> 20 | G186: =VLOOKUP(C186,'PACK MASTER'!$A$2:$G$512998,7,0) -> 1 | H186: =F186/G186 -> 20 | I186: =VLOOKUP($A186,ZMRP!$C$2:$F$99995,4,0) -> 225 | J186: =I186/G186 -> 225 | K186: =VLOOKUP($A186,ZLAM!$C$2:$F$99999,4,0) -> 45 | L186: =I186*K186/100 -> 101.25 | M186: =L186/G186 -> 101.25 | N186: =L186/1.18 -> 85.805085 | O186: =N186/G186 -> 85.805085 | P186: =IFERROR(ABS(VLOOKUP($A186,ZTRV!$D$2:$G$99407,4,0)),0) -> 0 | Q186: =IFERROR(ABS(VLOOKUP($A186,ZTR1!$D$2:$G$99999,4,0)),0) -> 0 | R186: =IFERROR(ABS(VLOOKUP($A186,ZTR2!$D$2:$G$99939,4,0)),0) -> 0 | S186: =SUM(P186:R186)*G186 -> 0 | T186: =N186-S186 -> 85.805085 | U186: =T186*1.18 -> 101.25 | V186: =U186/G186 -> 101.25 | W186: =V186*F186 -> 2025 | X186: =I186-U186 -> 123.75 | Y186: =X186*H186 -> 2475 | Z186: =J186-V186 -> 123.75 | AA186: =IFERROR(ABS(VLOOKUP(A186,ZSSD!$D$2:$G$99933,4,0)),AI186) -> 6.5 | AB186: =IFERROR(IF(VLOOKUP(A186,ZSSD!$D:$H,5,0)="L29",AA186*G186,AA186*L186/100),AA186*L186/100) -> 6.58125 | AC186: 2 | AD186: =2*(T186-AB186)/100 -> 1.5844767 | AE186: =+AB186/G186 -> 6.58125 | AF186: =+AD186/G186 -> 1.5844767 | AG186: =VLOOKUP(A186,ZSSD!D:D,1,0) -> #N/A | AH186: =VLOOKUP(B186,[2]GRADE!$A:$P,16,0) -> SILVER | AI186: =IF(AH186="SILVER",6.5,IF(AH186="GOLD",8,IF(AH186="INDUSTRIAL",6,IF(AH186="GREEN",7,IF(AH186="BRONZE",5.5,0))))) -> 6.5
A187: 7205222 | B187: =VALUE(LEFT(A187,4)) -> 7205 | C187: =VALUE(RIGHT(A187,3)) -> 222 | D187: =VLOOKUP(C187,Sheet1!$A$2:$K$369991,11,0) -> CAR | E187: HYUNDAI SERVO SUPERIOR 0W30-4 X 4 L | F187: =VLOOKUP(C187,'PACK MASTER'!$A$2:$I$512998,9,0)*1000 -> 16 | G187: =VLOOKUP(C187,'PACK MASTER'!$A$2:$G$512998,7,0) -> 4 | H187: =F187/G187 -> 4 | I187: =VLOOKUP($A187,ZMRP!$C$2:$F$99995,4,0) -> 1960 | J187: =I187/G187 -> 490 | K187: =VLOOKUP($A187,ZLAM!$C$2:$F$99999,4,0) -> 82.45 | L187: =I187*K187/100 -> 1616.02 | M187: =L187/G187 -> 404.005 | N187: =L187/1.18 -> 1369.5085 | O187: =N187/G187 -> 342.37712 | P187: =IFERROR(ABS(VLOOKUP($A187,ZTRV!$D$2:$G$99407,4,0)),0) -> 0 | Q187: =IFERROR(ABS(VLOOKUP($A187,ZTR1!$D$2:$G$99999,4,0)),0) -> 0 | R187: =IFERROR(ABS(VLOOKUP($A187,ZTR2!$D$2:$G$99939,4,0)),0) -> 0 | S187: =SUM(P187:R187)*G187 -> 0 | T187: =N187-S187 -> 1369.5085 | U187: =T187*1.18 -> 1616.02 | V187: =U187/G187 -> 404.005 | W187: =V187*F187 -> 6464.08 | X187: =I187-U187 -> 343.98 | Y187: =X187*H187 -> 1375.92 | Z187: =J187-V187 -> 85.995 | AA187: =IFERROR(ABS(VLOOKUP(A187,ZSSD!$D$2:$G$99933,4,0)),AI187) -> 5.5 | AB187: =IFERROR(IF(VLOOKUP(A187,ZSSD!$D:$H,5,0)="L29",AA187*G187,AA187*L187/100),AA187*L187/100) -> 88.8811 | AC187: 2 | AD187: =2*(T187-AB187)/100 -> 25.612547 | AE187: =+AB187/G187 -> 22.220275 | AF187: =+AD187/G187 -> 6.4031369 | AG187: =VLOOKUP(A187,ZSSD!D:D,1,0) -> 7205222 | AH187: =VLOOKUP(B187,[2]GRADE!$A:$P,16,0) -> SILVER | AI187: =IF(AH187="SILVER",6.5,IF(AH187="GOLD",8,IF(AH187="INDUSTRIAL",6,IF(AH187="GREEN",7,IF(AH187="BRONZE",5.5,0))))) -> 6.5
A188: 7209213 | B188: =VALUE(LEFT(A188,4)) -> 7209 | C188: =VALUE(RIGHT(A188,3)) -> 213 | D188: =VLOOKUP(C188,Sheet1!$A$2:$K$369991,11,0) -> CAR | E188: HY SERVO SYNTH 0W-30 SP/C3-4 X 3.5 L | F188: =VLOOKUP(C188,'PACK MASTER'!$A$2:$I$512998,9,0)*1000 -> 14 | G188: =VLOOKUP(C188,'PACK MASTER'!$A$2:$G$512998,7,0) -> 3.5 | H188: =F188/G188 -> 4 | I188: =VLOOKUP($A188,ZMRP!$C$2:$F$99995,4,0) -> 3885 | J188: =I188/G188 -> 1110 | K188: =VLOOKUP($A188,ZLAM!$C$2:$F$99999,4,0) -> 80.59 | L188: =I188*K188/100 -> 3130.9215 | M188: =L188/G188 -> 894.549 | N188: =L188/1.18 -> 2653.3233 | O188: =N188/G188 -> 758.09237 | P188: =IFERROR(ABS(VLOOKUP($A188,ZTRV!$D$2:$G$99407,4,0)),0) -> 0 | Q188: =IFERROR(ABS(VLOOKUP($A188,ZTR1!$D$2:$G$99999,4,0)),0) -> 0 | R188: =IFERROR(ABS(VLOOKUP($A188,ZTR2!$D$2:$G$99939,4,0)),0) -> 0 | S188: =SUM(P188:R188)*G188 -> 0 | T188: =N188-S188 -> 2653.3233 | U188: =T188*1.18 -> 3130.9215 | V188: =U188/G188 -> 894.549 | W188: =V188*F188 -> 12523.686 | X188: =I188-U188 -> 754.0785 | Y188: =X188*H188 -> 3016.314 | Z188: =J188-V188 -> 215.451 | AA188: =IFERROR(ABS(VLOOKUP(A188,ZSSD!$D$2:$G$99933,4,0)),AI188) -> 5.5 | AB188: =IFERROR(IF(VLOOKUP(A188,ZSSD!$D:$H,5,0)="L29",AA188*G188,AA188*L188/100),AA188*L188/100) -> 172.20068 | AC188: 2 | AD188: =2*(T188-AB188)/100 -> 49.622452 | AE188: =+AB188/G188 -> 49.200195 | AF188: =+AD188/G188 -> 14.177844 | AG188: =VLOOKUP(A188,ZSSD!D:D,1,0) -> 7209213 | AH188: =VLOOKUP(B188,[2]GRADE!$A:$P,16,0) -> SILVER | AI188: =IF(AH188="SILVER",6.5,IF(AH188="GOLD",8,IF(AH188="INDUSTRIAL",6,IF(AH188="GREEN",7,IF(AH188="BRONZE",5.5,0))))) -> 6.5
A189: 7211213 | B189: =VALUE(LEFT(A189,4)) -> 7211 | C189: =VALUE(RIGHT(A189,3)) -> 213 | D189: =VLOOKUP(C189,Sheet1!$A$2:$K$369991,11,0) -> CAR | E189: SERVO GREENMILE-4 X 3.5 L | F189: =VLOOKUP(C189,'PACK MASTER'!$A$2:$I$512998,9,0)*1000 -> 14 | G189: =VLOOKUP(C189,'PACK MASTER'!$A$2:$G$512998,7,0) -> 3.5 | H189: =F189/G189 -> 4 | I189: =VLOOKUP($A189,ZMRP!$C$2:$F$99995,4,0) -> 1628 | J189: =I189/G189 -> 465.14286 | K189: =VLOOKUP($A189,ZLAM!$C$2:$F$99999,4,0) -> 78.66 | L189: =I189*K189/100 -> 1280.5848 | M189: =L189/G189 -> 365.88137 | N189: =L189/1.18 -> 1085.2414 | O189: =N189/G189 -> 310.06896 | P189: =IFERROR(ABS(VLOOKUP($A189,ZTRV!$D$2:$G$99407,4,0)),0) -> 58 | Q189: =IFERROR(ABS(VLOOKUP($A189,ZTR1!$D$2:$G$99999,4,0)),0) -> 0 | R189: =IFERROR(ABS(VLOOKUP($A189,ZTR2!$D$2:$G$99939,4,0)),0) -> 0 | S189: =SUM(P189:R189)*G189 -> 203 | T189: =N189-S189 -> 882.24136 | U189: =T189*1.18 -> 1041.0448 | V189: =U189/G189 -> 297.44137 | W189: =V189*F189 -> 4164.1792 | X189: =I189-U189 -> 586.9552 | Y189: =X189*H189 -> 2347.8208 | Z189: =J189-V189 -> 167.70149 | AA189: =IFERROR(ABS(VLOOKUP(A189,ZSSD!$D$2:$G$99933,4,0)),AI189) -> 7 | AB189: =IFERROR(IF(VLOOKUP(A189,ZSSD!$D:$H,5,0)="L29",AA189*G189,AA189*L189/100),AA189*L189/100) -> 89.640936 | AC189: 2 | AD189: =2*(T189-AB189)/100 -> 15.852008 | AE189: =+AB189/G189 -> 25.611696 | AF189: =+AD189/G189 -> 4.5291453 | AG189: =VLOOKUP(A189,ZSSD!D:D,1,0) -> 7211213 | AH189: =VLOOKUP(B189,[2]GRADE!$A:$P,16,0) -> GREEN | AI189: =IF(AH189="SILVER",6.5,IF(AH189="GOLD",8,IF(AH189="INDUSTRIAL",6,IF(AH189="GREEN",7,IF(AH189="BRONZE",5.5,0))))) -> 7
A190: 7226184 | B190: =VALUE(LEFT(A190,4)) -> 7226 | C190: =VALUE(RIGHT(A190,3)) -> 184 | D190: =VLOOKUP(C190,Sheet1!$A$2:$K$369991,11,0) -> CAR | E190: SERVO MKM TRACTOR OIL-20 X 1 L | F190: =VLOOKUP(C190,'PACK MASTER'!$A$2:$I$512998,9,0)*1000 -> 20 | G190: =VLOOKUP(C190,'PACK MASTER'!$A$2:$G$512998,7,0) -> 1 | H190: =F190/G190 -> 20 | I190: =VLOOKUP($A190,ZMRP!$C$2:$F$99995,4,0) -> 369 | J190: =I190/G190 -> 369 | K190: =VLOOKUP($A190,ZLAM!$C$2:$F$99999,4,0) -> 81.75 | L190: =I190*K190/100 -> 301.6575 | M190: =L190/G190 -> 301.6575 | N190: =L190/1.18 -> 255.64195 | O190: =N190/G190 -> 255.64195 | P190: =IFERROR(ABS(VLOOKUP($A190,ZTRV!$D$2:$G$99407,4,0)),0) -> 43 | Q190: =IFERROR(ABS(VLOOKUP($A190,ZTR1!$D$2:$G$99999,4,0)),0) -> 0 | R190: =IFERROR(ABS(VLOOKUP($A190,ZTR2!$D$2:$G$99939,4,0)),0) -> 0 | S190: =SUM(P190:R190)*G190 -> 43 | T190: =N190-S190 -> 212.64195 | U190: =T190*1.18 -> 250.9175 | V190: =U190/G190 -> 250.9175 | W190: =V190*F190 -> 5018.35 | X190: =I190-U190 -> 118.0825 | Y190: =X190*H190 -> 2361.65 | Z190: =J190-V190 -> 118.0825 | AA190: =IFERROR(ABS(VLOOKUP(A190,ZSSD!$D$2:$G$99933,4,0)),AI190) -> 6.5 | AB190: =IFERROR(IF(VLOOKUP(A190,ZSSD!$D:$H,5,0)="L29",AA190*G190,AA190*L190/100),AA190*L190/100) -> 19.607738 | AC190: 2 | AD190: =2*(T190-AB190)/100 -> 3.8606842 | AE190: =+AB190/G190 -> 19.607738 | AF190: =+AD190/G190 -> 3.8606842 | AG190: =VLOOKUP(A190,ZSSD!D:D,1,0) -> #N/A | AH190: =VLOOKUP(B190,[2]GRADE!$A:$P,16,0) -> SILVER | AI190: =IF(AH190="SILVER",6.5,IF(AH190="GOLD",8,IF(AH190="INDUSTRIAL",6,IF(AH190="GREEN",7,IF(AH190="BRONZE",5.5,0))))) -> 6.5
A191: 7226251 | B191: =VALUE(LEFT(A191,4)) -> 7226 | C191: =VALUE(RIGHT(A191,3)) -> 251 | D191: =VLOOKUP(C191,Sheet1!$A$2:$K$369991,11,0) -> BUC | E191: SERVO MKM TRACTOR OIL-7.5 L | F191: =VLOOKUP(C191,'PACK MASTER'!$A$2:$I$512998,9,0)*1000 -> 7.5 | G191: =VLOOKUP(C191,'PACK MASTER'!$A$2:$G$512998,7,0) -> 7.5 | H191: =F191/G191 -> 1 | I191: =VLOOKUP($A191,ZMRP!$C$2:$F$99995,4,0) -> 2629 | J191: =I191/G191 -> 350.53333 | K191: =VLOOKUP($A191,ZLAM!$C$2:$F$99999,4,0) -> 82.53 | L191: =I191*K191/100 -> 2169.7137 | M191: =L191/G191 -> 289.29516 | N191: =L191/1.18 -> 1838.7404 | O191: =N191/G191 -> 245.16539 | P191: =IFERROR(ABS(VLOOKUP($A191,ZTRV!$D$2:$G$99407,4,0)),0) -> 30 | Q191: =IFERROR(ABS(VLOOKUP($A191,ZTR1!$D$2:$G$99999,4,0)),0) -> 0 | R191: =IFERROR(ABS(VLOOKUP($A191,ZTR2!$D$2:$G$99939,4,0)),0) -> 0 | S191: =SUM(P191:R191)*G191 -> 225 | T191: =N191-S191 -> 1613.7404 | U191: =T191*1.18 -> 1904.2137 | V191: =U191/G191 -> 253.89516 | W191: =V191*F191 -> 1904.2137 | X191: =I191-U191 -> 724.7863 | Y191: =X191*H191 -> 724.7863 | Z191: =J191-V191 -> 96.638173 | AA191: =IFERROR(ABS(VLOOKUP(A191,ZSSD!$D$2:$G$99933,4,0)),AI191) -> 6.5 | AB191: =IFERROR(IF(VLOOKUP(A191,ZSSD!$D:$H,5,0)="L29",AA191*G191,AA191*L191/100),AA191*L191/100) -> 141.03139 | AC191: 2 | AD191: =2*(T191-AB191)/100 -> 29.454181 | AE191: =+AB191/G191 -> 18.804185 | AF191: =+AD191/G191 -> 3.9272241 | AG191: =VLOOKUP(A191,ZSSD!D:D,1,0) -> #N/A | AH191: =VLOOKUP(B191,[2]GRADE!$A:$P,16,0) -> SILVER | AI191: =IF(AH191="SILVER",6.5,IF(AH191="GOLD",8,IF(AH191="INDUSTRIAL",6,IF(AH191="GREEN",7,IF(AH191="BRONZE",5.5,0))))) -> 6.5
A192: 7227184 | B192: =VALUE(LEFT(A192,4)) -> 7227 | C192: =VALUE(RIGHT(A192,3)) -> 184 | D192: =VLOOKUP(C192,Sheet1!$A$2:$K$369991,11,0) -> CAR | E192: SERVO TRACTOR GREEN-20 X 1 L | F192: =VLOOKUP(C192,'PACK MASTER'!$A$2:$I$512998,9,0)*1000 -> 20 | G192: =VLOOKUP(C192,'PACK MASTER'!$A$2:$G$512998,7,0) -> 1 | H192: =F192/G192 -> 20 | I192: =VLOOKUP($A192,ZMRP!$C$2:$F$99995,4,0) -> 415 | J192: =I192/G192 -> 415 | K192: =VLOOKUP($A192,ZLAM!$C$2:$F$99999,4,0) -> 74.22 | L192: =I192*K192/100 -> 308.013 | M192: =L192/G192 -> 308.013 | N192: =L192/1.18 -> 261.02797 | O192: =N192/G192 -> 261.02797 | P192: =IFERROR(ABS(VLOOKUP($A192,ZTRV!$D$2:$G$99407,4,0)),0) -> 53 | Q192: =IFERROR(ABS(VLOOKUP($A192,ZTR1!$D$2:$G$99999,4,0)),0) -> 0 | R192: =IFERROR(ABS(VLOOKUP($A192,ZTR2!$D$2:$G$99939,4,0)),0) -> 0 | S192: =SUM(P192:R192)*G192 -> 53 | T192: =N192-S192 -> 208.02797 | U192: =T192*1.18 -> 245.473 | V192: =U192/G192 -> 245.473 | W192: =V192*F192 -> 4909.46 | X192: =I192-U192 -> 169.527 | Y192: =X192*H192 -> 3390.54 | Z192: =J192-V192 -> 169.527 | AA192: =IFERROR(ABS(VLOOKUP(A192,ZSSD!$D$2:$G$99933,4,0)),AI192) -> 7 | AB192: =IFERROR(IF(VLOOKUP(A192,ZSSD!$D:$H,5,0)="L29",AA192*G192,AA192*L192/100),AA192*L192/100) -> 21.56091 | AC192: 2 | AD192: =2*(T192-AB192)/100 -> 3.7293411 | AE192: =+AB192/G192 -> 21.56091 | AF192: =+AD192/G192 -> 3.7293411 | AG192: =VLOOKUP(A192,ZSSD!D:D,1,0) -> 7227184 | AH192: =VLOOKUP(B192,[2]GRADE!$A:$P,16,0) -> GREEN | AI192: =IF(AH192="SILVER",6.5,IF(AH192="GOLD",8,IF(AH192="INDUSTRIAL",6,IF(AH192="GREEN",7,IF(AH192="BRONZE",5.5,0))))) -> 7
A193: 7227251 | B193: =VALUE(LEFT(A193,4)) -> 7227 | C193: =VALUE(RIGHT(A193,3)) -> 251 | D193: =VLOOKUP(C193,Sheet1!$A$2:$K$369991,11,0) -> BUC | E193: SERVO TRACTOR GREEN-7.5 L | F193: =VLOOKUP(C193,'PACK MASTER'!$A$2:$I$512998,9,0)*1000 -> 7.5 | G193: =VLOOKUP(C193,'PACK MASTER'!$A$2:$G$512998,7,0) -> 7.5 | H193: =F193/G193 -> 1 | I193: =VLOOKUP($A193,ZMRP!$C$2:$F$99995,4,0) -> 3073 | J193: =I193/G193 -> 409.73333 | K193: =VLOOKUP($A193,ZLAM!$C$2:$F$99999,4,0) -> 74.2 | L193: =I193*K193/100 -> 2280.166 | M193: =L193/G193 -> 304.02213 | N193: =L193/1.18 -> 1932.3441 | O193: =N193/G193 -> 257.64588 | P193: =IFERROR(ABS(VLOOKUP($A193,ZTRV!$D$2:$G$99407,4,0)),0) -> 58 | Q193: =IFERROR(ABS(VLOOKUP($A193,ZTR1!$D$2:$G$99999,4,0)),0) -> 0 | R193: =IFERROR(ABS(VLOOKUP($A193,ZTR2!$D$2:$G$99939,4,0)),0) -> 0 | S193: =SUM(P193:R193)*G193 -> 435 | T193: =N193-S193 -> 1497.3441 | U193: =T193*1.18 -> 1766.866 | V193: =U193/G193 -> 235.58213 | W193: =V193*F193 -> 1766.866 | X193: =I193-U193 -> 1306.134 | Y193: =X193*H193 -> 1306.134 | Z193: =J193-V193 -> 174.1512 | AA193: =IFERROR(ABS(VLOOKUP(A193,ZSSD!$D$2:$G$99933,4,0)),AI193) -> 7 | AB193: =IFERROR(IF(VLOOKUP(A193,ZSSD!$D:$H,5,0)="L29",AA193*G193,AA193*L193/100),AA193*L193/100) -> 159.61162 | AC193: 2 | AD193: =2*(T193-AB193)/100 -> 26.754649 | AE193: =+AB193/G193 -> 21.281549 | AF193: =+AD193/G193 -> 3.5672865 | AG193: =VLOOKUP(A193,ZSSD!D:D,1,0) -> 7227251 | AH193: =VLOOKUP(B193,[2]GRADE!$A:$P,16,0) -> GREEN | AI193: =IF(AH193="SILVER",6.5,IF(AH193="GOLD",8,IF(AH193="INDUSTRIAL",6,IF(AH193="GREEN",7,IF(AH193="BRONZE",5.5,0))))) -> 7
A194: 7227252 | B194: =VALUE(LEFT(A194,4)) -> 7227 | C194: =VALUE(RIGHT(A194,3)) -> 252 | D194: =VLOOKUP(C194,Sheet1!$A$2:$K$369991,11,0) -> BUC | E194: SERVO TRACTOR GREEN-8.5 L | F194: =VLOOKUP(C194,'PACK MASTER'!$A$2:$I$512998,9,0)*1000 -> 8.5 | G194: =VLOOKUP(C194,'PACK MASTER'!$A$2:$G$512998,7,0) -> 8.5 | H194: =F194/G194 -> 1 | I194: =VLOOKUP($A194,ZMRP!$C$2:$F$99995,4,0) -> 3468 | J194: =I194/G194 -> 408 | K194: =VLOOKUP($A194,ZLAM!$C$2:$F$99999,4,0) -> 74.25 | L194: =I194*K194/100 -> 2574.99 | M194: =L194/G194 -> 302.94 | N194: =L194/1.18 -> 2182.1949 | O194: =N194/G194 -> 256.72881 | P194: =IFERROR(ABS(VLOOKUP($A194,ZTRV!$D$2:$G$99407,4,0)),0) -> 58 | Q194: =IFERROR(ABS(VLOOKUP($A194,ZTR1!$D$2:$G$99999,4,0)),0) -> 0 | R194: =IFERROR(ABS(VLOOKUP($A194,ZTR2!$D$2:$G$99939,4,0)),0) -> 0 | S194: =SUM(P194:R194)*G194 -> 493 | T194: =N194-S194 -> 1689.1949 | U194: =T194*1.18 -> 1993.25 | V194: =U194/G194 -> 234.5 | W194: =V194*F194 -> 1993.25 | X194: =I194-U194 -> 1474.75 | Y194: =X194*H194 -> 1474.75 | Z194: =J194-V194 -> 173.5 | AA194: =IFERROR(ABS(VLOOKUP(A194,ZSSD!$D$2:$G$99933,4,0)),AI194) -> 7 | AB194: =IFERROR(IF(VLOOKUP(A194,ZSSD!$D:$H,5,0)="L29",AA194*G194,AA194*L194/100),AA194*L194/100) -> 180.2493 | AC194: 2 | AD194: =2*(T194-AB194)/100 -> 30.178912 | AE194: =+AB194/G194 -> 21.2058 | AF194: =+AD194/G194 -> 3.5504603 | AG194: =VLOOKUP(A194,ZSSD!D:D,1,0) -> 7227252 | AH194: =VLOOKUP(B194,[2]GRADE!$A:$P,16,0) -> GREEN | AI194: =IF(AH194="SILVER",6.5,IF(AH194="GOLD",8,IF(AH194="INDUSTRIAL",6,IF(AH194="GREEN",7,IF(AH194="BRONZE",5.5,0))))) -> 7
A195: 7231256 | B195: =VALUE(LEFT(A195,4)) -> 7231 | C195: =VALUE(RIGHT(A195,3)) -> 256 | D195: =VLOOKUP(C195,Sheet1!$A$2:$K$369991,11,0) -> BUC | E195: SERVO RAFTAAR-15 L | F195: =VLOOKUP(C195,'PACK MASTER'!$A$2:$I$512998,9,0)*1000 -> 15 | G195: =VLOOKUP(C195,'PACK MASTER'!$A$2:$G$512998,7,0) -> 15 | H195: =F195/G195 -> 1 | I195: =VLOOKUP($A195,ZMRP!$C$2:$F$99995,4,0) -> 5625 | J195: =I195/G195 -> 375 | K195: =VLOOKUP($A195,ZLAM!$C$2:$F$99999,4,0) -> 80.07 | L195: =I195*K195/100 -> 4503.9375 | M195: =L195/G195 -> 300.2625 | N195: =L195/1.18 -> 3816.8962 | O195: =N195/G195 -> 254.45975 | P195: =IFERROR(ABS(VLOOKUP($A195,ZTRV!$D$2:$G$99407,4,0)),0) -> 48 | Q195: =IFERROR(ABS(VLOOKUP($A195,ZTR1!$D$2:$G$99999,4,0)),0) -> 0 | R195: =IFERROR(ABS(VLOOKUP($A195,ZTR2!$D$2:$G$99939,4,0)),0) -> 0 | S195: =SUM(P195:R195)*G195 -> 720 | T195: =N195-S195 -> 3096.8962 | U195: =T195*1.18 -> 3654.3375 | V195: =U195/G195 -> 243.6225 | W195: =V195*F195 -> 3654.3375 | X195: =I195-U195 -> 1970.6625 | Y195: =X195*H195 -> 1970.6625 | Z195: =J195-V195 -> 131.3775 | AA195: =IFERROR(ABS(VLOOKUP(A195,ZSSD!$D$2:$G$99933,4,0)),AI195) -> 7 | AB195: =IFERROR(IF(VLOOKUP(A195,ZSSD!$D:$H,5,0)="L29",AA195*G195,AA195*L195/100),AA195*L195/100) -> 315.27562 | AC195: 2 | AD195: =2*(T195-AB195)/100 -> 55.632411 | AE195: =+AB195/G195 -> 21.018375 | AF195: =+AD195/G195 -> 3.7088274 | AG195: =VLOOKUP(A195,ZSSD!D:D,1,0) -> 7231256 | AH195: =VLOOKUP(B195,[2]GRADE!$A:$P,16,0) -> GREEN | AI195: =IF(AH195="SILVER",6.5,IF(AH195="GOLD",8,IF(AH195="INDUSTRIAL",6,IF(AH195="GREEN",7,IF(AH195="BRONZE",5.5,0))))) -> 7
A196: 7232184 | B196: =VALUE(LEFT(A196,4)) -> 7232 | C196: =VALUE(RIGHT(A196,3)) -> 184 | D196: =VLOOKUP(C196,Sheet1!$A$2:$K$369991,11,0) -> CAR | E196: HYUNDAI SERVO COOLANT 50-20 X 1 L | F196: =VLOOKUP(C196,'PACK MASTER'!$A$2:$I$512998,9,0)*1000 -> 20 | G196: =VLOOKUP(C196,'PACK MASTER'!$A$2:$G$512998,7,0) -> 1 | H196: =F196/G196 -> 20 | I196: =VLOOKUP($A196,ZMRP!$C$2:$F$99995,4,0) -> 301 | J196: =I196/G196 -> 301 | K196: =VLOOKUP($A196,ZLAM!$C$2:$F$99999,4,0) -> 85.38 | L196: =I196*K196/100 -> 256.9938 | M196: =L196/G196 -> 256.9938 | N196: =L196/1.18 -> 217.79136 | O196: =N196/G196 -> 217.79136 | P196: =IFERROR(ABS(VLOOKUP($A196,ZTRV!$D$2:$G$99407,4,0)),0) -> 0 | Q196: =IFERROR(ABS(VLOOKUP($A196,ZTR1!$D$2:$G$99999,4,0)),0) -> 0 | R196: =IFERROR(ABS(VLOOKUP($A196,ZTR2!$D$2:$G$99939,4,0)),0) -> 0 | S196: =SUM(P196:R196)*G196 -> 0 | T196: =N196-S196 -> 217.79136 | U196: =T196*1.18 -> 256.9938 | V196: =U196/G196 -> 256.9938 | W196: =V196*F196 -> 5139.876 | X196: =I196-U196 -> 44.0062 | Y196: =X196*H196 -> 880.124 | Z196: =J196-V196 -> 44.0062 | AA196: =IFERROR(ABS(VLOOKUP(A196,ZSSD!$D$2:$G$99933,4,0)),AI196) -> 5.5 | AB196: =IFERROR(IF(VLOOKUP(A196,ZSSD!$D:$H,5,0)="L29",AA196*G196,AA196*L196/100),AA196*L196/100) -> 14.134659 | AC196: 2 | AD196: =2*(T196-AB196)/100 -> 4.0731339 | AE196: =+AB196/G196 -> 14.134659 | AF196: =+AD196/G196 -> 4.0731339 | AG196: =VLOOKUP(A196,ZSSD!D:D,1,0) -> 7232184 | AH196: =VLOOKUP(B196,[2]GRADE!$A:$P,16,0) -> SILVER | AI196: =IF(AH196="SILVER",6.5,IF(AH196="GOLD",8,IF(AH196="INDUSTRIAL",6,IF(AH196="GREEN",7,IF(AH196="BRONZE",5.5,0))))) -> 6.5
A197: 7264222 | B197: =VALUE(LEFT(A197,4)) -> 7264 | C197: =VALUE(RIGHT(A197,3)) -> 222 | D197: =VLOOKUP(C197,Sheet1!$A$2:$K$369991,11,0) -> CAR | E197: SERVO MG HECTOR PETROL EO-4 X 4 L | F197: =VLOOKUP(C197,'PACK MASTER'!$A$2:$I$512998,9,0)*1000 -> 16 | G197: =VLOOKUP(C197,'PACK MASTER'!$A$2:$G$512998,7,0) -> 4 | H197: =F197/G197 -> 4 | I197: =VLOOKUP($A197,ZMRP!$C$2:$F$99995,4,0) -> 1760 | J197: =I197/G197 -> 440 | K197: =VLOOKUP($A197,ZLAM!$C$2:$F$99999,4,0) -> 84.43 | L197: =I197*K197/100 -> 1485.968 | M197: =L197/G197 -> 371.492 | N197: =L197/1.18 -> 1259.2949 | O197: =N197/G197 -> 314.82373 | P197: =IFERROR(ABS(VLOOKUP($A197,ZTRV!$D$2:$G$99407,4,0)),0) -> 14.83 | Q197: =IFERROR(ABS(VLOOKUP($A197,ZTR1!$D$2:$G$99999,4,0)),0) -> 0 | R197: =IFERROR(ABS(VLOOKUP($A197,ZTR2!$D$2:$G$99939,4,0)),0) -> 0 | S197: =SUM(P197:R197)*G197 -> 59.32 | T197: =N197-S197 -> 1199.9749 | U197: =T197*1.18 -> 1415.9704 | V197: =U197/G197 -> 353.9926 | W197: =V197*F197 -> 5663.8816 | X197: =I197-U197 -> 344.0296 | Y197: =X197*H197 -> 1376.1184 | Z197: =J197-V197 -> 86.0074 | AA197: =IFERROR(ABS(VLOOKUP(A197,ZSSD!$D$2:$G$99933,4,0)),AI197) -> 10 | AB197: =IFERROR(IF(VLOOKUP(A197,ZSSD!$D:$H,5,0)="L29",AA197*G197,AA197*L197/100),AA197*L197/100) -> 40 | AC197: 2 | AD197: =2*(T197-AB197)/100 -> 23.199498 | AE197: =+AB197/G197 -> 10 | AF197: =+AD197/G197 -> 5.7998746 | AG197: =VLOOKUP(A197,ZSSD!D:D,1,0) -> 7264222 | AH197: =VLOOKUP(B197,[2]GRADE!$A:$P,16,0) -> SILVER | AI197: =IF(AH197="SILVER",6.5,IF(AH197="GOLD",8,IF(AH197="INDUSTRIAL",6,IF(AH197="GREEN",7,IF(AH197="BRONZE",5.5,0))))) -> 6.5
A198: 7265234 | B198: =VALUE(LEFT(A198,4)) -> 7265 | C198: =VALUE(RIGHT(A198,3)) -> 234 | D198: =VLOOKUP(C198,Sheet1!$A$2:$K$369991,11,0) -> CAR | E198: SERVO MG GLOSTER DIESEL EO-4 X 5 L LUBE | F198: =VLOOKUP(C198,'PACK MASTER'!$A$2:$I$512998,9,0)*1000 -> 20 | G198: =VLOOKUP(C198,'PACK MASTER'!$A$2:$G$512998,7,0) -> 5 | H198: =F198/G198 -> 4 | I198: =VLOOKUP($A198,ZMRP!$C$2:$F$99995,4,0) -> 3215 | J198: =I198/G198 -> 643 | K198: =VLOOKUP($A198,ZLAM!$C$2:$F$99999,4,0) -> 83.76 | L198: =I198*K198/100 -> 2692.884 | M198: =L198/G198 -> 538.5768 | N198: =L198/1.18 -> 2282.1051 | O198: =N198/G198 -> 456.42102 | P198: =IFERROR(ABS(VLOOKUP($A198,ZTRV!$D$2:$G$99407,4,0)),0) -> 22.44 | Q198: =IFERROR(ABS(VLOOKUP($A198,ZTR1!$D$2:$G$99999,4,0)),0) -> 0 | R198: =IFERROR(ABS(VLOOKUP($A198,ZTR2!$D$2:$G$99939,4,0)),0) -> 0 | S198: =SUM(P198:R198)*G198 -> 112.2 | T198: =N198-S198 -> 2169.9051 | U198: =T198*1.18 -> 2560.488 | V198: =U198/G198 -> 512.0976 | W198: =V198*F198 -> 10241.952 | X198: =I198-U198 -> 654.512 | Y198: =X198*H198 -> 2618.048 | Z198: =J198-V198 -> 130.9024 | AA198: =IFERROR(ABS(VLOOKUP(A198,ZSSD!$D$2:$G$99933,4,0)),AI198) -> 10 | AB198: =IFERROR(IF(VLOOKUP(A198,ZSSD!$D:$H,5,0)="L29",AA198*G198,AA198*L198/100),AA198*L198/100) -> 50 | AC198: 2 | AD198: =2*(T198-AB198)/100 -> 42.398102 | AE198: =+AB198/G198 -> 10 | AF198: =+AD198/G198 -> 8.4796203 | AG198: =VLOOKUP(A198,ZSSD!D:D,1,0) -> 7265234 | AH198: =VLOOKUP(B198,[2]GRADE!$A:$P,16,0) -> SILVER | AI198: =IF(AH198="SILVER",6.5,IF(AH198="GOLD",8,IF(AH198="INDUSTRIAL",6,IF(AH198="GREEN",7,IF(AH198="BRONZE",5.5,0))))) -> 6.5
... A294: 7489253 | B294: =VALUE(LEFT(A294,4)) -> 7489 | C294: =VALUE(RIGHT(A294,3)) -> 253 | D294: =VLOOKUP(C294,Sheet1!$A$2:$K$369991,11,0) -> BUC | E294: SERVO PRIDE XL PLUS 15W40-15L PROMO | F294: =VLOOKUP(C294,'PACK MASTER'!$A$2:$I$512998,9,0)*1000 -> 15 | G294: =VLOOKUP(C294,'PACK MASTER'!$A$2:$G$512998,7,0) -> 15 | H294: =F294/G294 -> 1 | I294: =VLOOKUP($A294,ZMRP!$C$2:$F$99995,4,0) -> 5675 | J294: =I294/G294 -> 378.33333 | K294: =VLOOKUP($A294,ZLAM!$C$2:$F$99999,4,0) -> 79.36 | L294: =I294*K294/100 -> 4503.68 | M294: =L294/G294 -> 300.24533 | N294: =L294/1.18 -> 3816.678 | O294: =N294/G294 -> 254.4452 | P294: =IFERROR(ABS(VLOOKUP($A294,ZTRV!$D$2:$G$99407,4,0)),0) -> 53 | Q294: =IFERROR(ABS(VLOOKUP($A294,ZTR1!$D$2:$G$99999,4,0)),0) -> 0 | R294: =IFERROR(ABS(VLOOKUP($A294,ZTR2!$D$2:$G$99939,4,0)),0) -> 0 | S294: =SUM(P294:R294)*G294 -> 795 | T294: =N294-S294 -> 3021.678 | U294: =T294*1.18 -> 3565.58 | V294: =U294/G294 -> 237.70533 | W294: =V294*F294 -> 3565.58 | X294: =I294-U294 -> 2109.42 | Y294: =X294*H294 -> 2109.42 | Z294: =J294-V294 -> 140.628 | AA294: =IFERROR(ABS(VLOOKUP(A294,ZSSD!$D$2:$G$99933,4,0)),AI294) -> 6.5 | AB294: =IFERROR(IF(VLOOKUP(A294,ZSSD!$D:$H,5,0)="L29",AA294*G294,AA294*L294/100),AA294*L294/100) -> 292.7392 | AC294: 2 | AD294: =2*(T294-AB294)/100 -> 54.578775 | AE294: =+AB294/G294 -> 19.515947 | AF294: =+AD294/G294 -> 3.638585 | AG294: =VLOOKUP(A294,ZSSD!D:D,1,0) -> #N/A | AH294: =VLOOKUP(B294,[2]GRADE!$A:$P,16,0) -> SILVER | AI294: =IF(AH294="SILVER",6.5,IF(AH294="GOLD",8,IF(AH294="INDUSTRIAL",6,IF(AH294="GREEN",7,IF(AH294="BRONZE",5.5,0))))) -> 6.5
A295: 7489254 | B295: 7489 | C295: 254 | D295: =VLOOKUP(C295,Sheet1!$A$2:$K$369991,11,0) -> BUC | E295: SERVO PRIDE XL PLUS 15W40-18 L | F295: =VLOOKUP(C295,'PACK MASTER'!$A$2:$I$512998,9,0)*1000 -> 18 | G295: =VLOOKUP(C295,'PACK MASTER'!$A$2:$G$512998,7,0) -> 18 | H295: =F295/G295 -> 1 | I295: =VLOOKUP($A295,ZMRP!$C$2:$F$99995,4,0) -> 7000 | J295: =I295/G295 -> 388.88889 | K295: =VLOOKUP($A295,ZLAM!$C$2:$F$99999,4,0) -> 76.43 | L295: =I295*K295/100 -> 5350.1 | M295: =L295/G295 -> 297.22778 | N295: =L295/1.18 -> 4533.9831 | O295: =N295/G295 -> 251.88795 | P295: =IFERROR(ABS(VLOOKUP($A295,ZTRV!$D$2:$G$99407,4,0)),0) -> 0 | Q295: =IFERROR(ABS(VLOOKUP($A295,ZTR1!$D$2:$G$99999,4,0)),0) -> 0 | R295: =IFERROR(ABS(VLOOKUP($A295,ZTR2!$D$2:$G$99939,4,0)),0) -> 0 | S295: =SUM(P295:R295)*G295 -> 0 | T295: =N295-S295 -> 4533.9831 | U295: =T295*1.18 -> 5350.1 | V295: =U295/G295 -> 297.22778 | W295: =V295*F295 -> 5350.1 | X295: =I295-U295 -> 1649.9 | Y295: =X295*H295 -> 1649.9 | Z295: =J295-V295 -> 91.661111 | AA295: =IFERROR(ABS(VLOOKUP(A295,ZSSD!$D$2:$G$99933,4,0)),AI295) -> 6.5 | AB295: =IFERROR(IF(VLOOKUP(A295,ZSSD!$D:$H,5,0)="L29",AA295*G295,AA295*L295/100),AA295*L295/100) -> 347.7565 | AC295: 2 | AD295: =2*(T295-AB295)/100 -> 83.724531 | AE295: =+AB295/G295 -> 19.319806 | AF295: =+AD295/G295 -> 4.6513628 | AG295: =VLOOKUP(A295,ZSSD!D:D,1,0) -> #N/A | AH295: =VLOOKUP(B295,[2]GRADE!$A:$P,16,0) -> SILVER | AI295: =IF(AH295="SILVER",6.5,IF(AH295="GOLD",8,IF(AH295="INDUSTRIAL",6,IF(AH295="GREEN",7,IF(AH295="BRONZE",5.5,0))))) -> 6.5
A296: 7489256 | B296: =VALUE(LEFT(A296,4)) -> 7489 | C296: =VALUE(RIGHT(A296,3)) -> 256 | D296: =VLOOKUP(C296,Sheet1!$A$2:$K$369991,11,0) -> BUC | E296: SERVO PRIDE XL PLUS 15W40-15 L | F296: =VLOOKUP(C296,'PACK MASTER'!$A$2:$I$512998,9,0)*1000 -> 15 | G296: =VLOOKUP(C296,'PACK MASTER'!$A$2:$G$512998,7,0) -> 15 | H296: =F296/G296 -> 1 | I296: =VLOOKUP($A296,ZMRP!$C$2:$F$99995,4,0) -> 5675 | J296: =I296/G296 -> 378.33333 | K296: =VLOOKUP($A296,ZLAM!$C$2:$F$99999,4,0) -> 79.36 | L296: =I296*K296/100 -> 4503.68 | M296: =L296/G296 -> 300.24533 | N296: =L296/1.18 -> 3816.678 | O296: =N296/G296 -> 254.4452 | P296: =IFERROR(ABS(VLOOKUP($A296,ZTRV!$D$2:$G$99407,4,0)),0) -> 53 | Q296: =IFERROR(ABS(VLOOKUP($A296,ZTR1!$D$2:$G$99999,4,0)),0) -> 0 | R296: =IFERROR(ABS(VLOOKUP($A296,ZTR2!$D$2:$G$99939,4,0)),0) -> 0 | S296: =SUM(P296:R296)*G296 -> 795 | T296: =N296-S296 -> 3021.678 | U296: =T296*1.18 -> 3565.58 | V296: =U296/G296 -> 237.70533 | W296: =V296*F296 -> 3565.58 | X296: =I296-U296 -> 2109.42 | Y296: =X296*H296 -> 2109.42 | Z296: =J296-V296 -> 140.628 | AA296: =IFERROR(ABS(VLOOKUP(A296,ZSSD!$D$2:$G$99933,4,0)),AI296) -> 6.5 | AB296: =IFERROR(IF(VLOOKUP(A296,ZSSD!$D:$H,5,0)="L29",AA296*G296,AA296*L296/100),AA296*L296/100) -> 292.7392 | AC296: 2 | AD296: =2*(T296-AB296)/100 -> 54.578775 | AE296: =+AB296/G296 -> 19.515947 | AF296: =+AD296/G296 -> 3.638585 | AG296: =VLOOKUP(A296,ZSSD!D:D,1,0) -> #N/A | AH296: =VLOOKUP(B296,[2]GRADE!$A:$P,16,0) -> SILVER | AI296: =IF(AH296="SILVER",6.5,IF(AH296="GOLD",8,IF(AH296="INDUSTRIAL",6,IF(AH296="GREEN",7,IF(AH296="BRONZE",5.5,0))))) -> 6.5
A297: 7489265 | B297: =VALUE(LEFT(A297,4)) -> 7489 | C297: =VALUE(RIGHT(A297,3)) -> 265 | D297: =VLOOKUP(C297,Sheet1!$A$2:$K$369991,11,0) -> BUC | E297: SERVO PRIDE XL PLUS 15W40-20 L | F297: =VLOOKUP(C297,'PACK MASTER'!$A$2:$I$512998,9,0)*1000 -> 20 | G297: =VLOOKUP(C297,'PACK MASTER'!$A$2:$G$512998,7,0) -> 20 | H297: =F297/G297 -> 1 | I297: =VLOOKUP($A297,ZMRP!$C$2:$F$99995,4,0) -> 7500 | J297: =I297/G297 -> 375 | K297: =VLOOKUP($A297,ZLAM!$C$2:$F$99999,4,0) -> 79.85 | L297: =I297*K297/100 -> 5988.75 | M297: =L297/G297 -> 299.4375 | N297: =L297/1.18 -> 5075.2119 | O297: =N297/G297 -> 253.76059 | P297: =IFERROR(ABS(VLOOKUP($A297,ZTRV!$D$2:$G$99407,4,0)),0) -> 48 | Q297: =IFERROR(ABS(VLOOKUP($A297,ZTR1!$D$2:$G$99999,4,0)),0) -> 0 | R297: =IFERROR(ABS(VLOOKUP($A297,ZTR2!$D$2:$G$99939,4,0)),0) -> 0 | S297: =SUM(P297:R297)*G297 -> 960 | T297: =N297-S297 -> 4115.2119 | U297: =T297*1.18 -> 4855.95 | V297: =U297/G297 -> 242.7975 | W297: =V297*F297 -> 4855.95 | X297: =I297-U297 -> 2644.05 | Y297: =X297*H297 -> 2644.05 | Z297: =J297-V297 -> 132.2025 | AA297: =IFERROR(ABS(VLOOKUP(A297,ZSSD!$D$2:$G$99933,4,0)),AI297) -> 6.5 | AB297: =IFERROR(IF(VLOOKUP(A297,ZSSD!$D:$H,5,0)="L29",AA297*G297,AA297*L297/100),AA297*L297/100) -> 389.26875 | AC297: 2 | AD297: =2*(T297-AB297)/100 -> 74.518862 | AE297: =+AB297/G297 -> 19.463438 | AF297: =+AD297/G297 -> 3.7259431 | AG297: =VLOOKUP(A297,ZSSD!D:D,1,0) -> #N/A | AH297: =VLOOKUP(B297,[2]GRADE!$A:$P,16,0) -> SILVER | AI297: =IF(AH297="SILVER",6.5,IF(AH297="GOLD",8,IF(AH297="INDUSTRIAL",6,IF(AH297="GREEN",7,IF(AH297="BRONZE",5.5,0))))) -> 6.5
A298: 7489269 | B298: =VALUE(LEFT(A298,4)) -> 7489 | C298: =VALUE(RIGHT(A298,3)) -> 269 | D298: =VLOOKUP(C298,Sheet1!$A$2:$K$369991,11,0) -> BUC | E298: SERVO PRIDE XL PLUS 15W40 -20L PROMO | F298: =VLOOKUP(C298,'PACK MASTER'!$A$2:$I$512998,9,0)*1000 -> 20 | G298: =VLOOKUP(C298,'PACK MASTER'!$A$2:$G$512998,7,0) -> 20 | H298: =F298/G298 -> 1 | I298: =VLOOKUP($A298,ZMRP!$C$2:$F$99995,4,0) -> 7500 | J298: =I298/G298 -> 375 | K298: =VLOOKUP($A298,ZLAM!$C$2:$F$99999,4,0) -> 79.85 | L298: =I298*K298/100 -> 5988.75 | M298: =L298/G298 -> 299.4375 | N298: =L298/1.18 -> 5075.2119 | O298: =N298/G298 -> 253.76059 | P298: =IFERROR(ABS(VLOOKUP($A298,ZTRV!$D$2:$G$99407,4,0)),0) -> 0 | Q298: =IFERROR(ABS(VLOOKUP($A298,ZTR1!$D$2:$G$99999,4,0)),0) -> 0 | R298: =IFERROR(ABS(VLOOKUP($A298,ZTR2!$D$2:$G$99939,4,0)),0) -> 0 | S298: =SUM(P298:R298)*G298 -> 0 | T298: =N298-S298 -> 5075.2119 | U298: =T298*1.18 -> 5988.75 | V298: =U298/G298 -> 299.4375 | W298: =V298*F298 -> 5988.75 | X298: =I298-U298 -> 1511.25 | Y298: =X298*H298 -> 1511.25 | Z298: =J298-V298 -> 75.5625 | AA298: =IFERROR(ABS(VLOOKUP(A298,ZSSD!$D$2:$G$99933,4,0)),AI298) -> 6.5 | AB298: =IFERROR(IF(VLOOKUP(A298,ZSSD!$D:$H,5,0)="L29",AA298*G298,AA298*L298/100),AA298*L298/100) -> 389.26875 | AC298: 2 | AD298: =2*(T298-AB298)/100 -> 93.718862 | AE298: =+AB298/G298 -> 19.463438 | AF298: =+AD298/G298 -> 4.6859431 | AG298: =VLOOKUP(A298,ZSSD!D:D,1,0) -> #N/A | AH298: =VLOOKUP(B298,[2]GRADE!$A:$P,16,0) -> SILVER | AI298: =IF(AH298="SILVER",6.5,IF(AH298="GOLD",8,IF(AH298="INDUSTRIAL",6,IF(AH298="GREEN",7,IF(AH298="BRONZE",5.5,0))))) -> 6.5
A299: 7489272 | B299: =VALUE(LEFT(A299,4)) -> 7489 | C299: =VALUE(RIGHT(A299,3)) -> 272 | D299: =VLOOKUP(C299,Sheet1!$A$2:$K$369991,11,0) -> BUC | E299: SERVO PRIDE XL PLUS 15W40-(13+2)L | F299: =VLOOKUP(C299,'PACK MASTER'!$A$2:$I$512998,9,0)*1000 -> 15 | G299: =VLOOKUP(C299,'PACK MASTER'!$A$2:$G$512998,7,0) -> 15 | H299: =F299/G299 -> 1 | I299: =VLOOKUP($A299,ZMRP!$C$2:$F$99995,4,0) -> 5675 | J299: =I299/G299 -> 378.33333 | K299: =VLOOKUP($A299,ZLAM!$C$2:$F$99999,4,0) -> 79.36 | L299: =I299*K299/100 -> 4503.68 | M299: =L299/G299 -> 300.24533 | N299: =L299/1.18 -> 3816.678 | O299: =N299/G299 -> 254.4452 | P299: =IFERROR(ABS(VLOOKUP($A299,ZTRV!$D$2:$G$99407,4,0)),0) -> 0 | Q299: =IFERROR(ABS(VLOOKUP($A299,ZTR1!$D$2:$G$99999,4,0)),0) -> 0 | R299: =IFERROR(ABS(VLOOKUP($A299,ZTR2!$D$2:$G$99939,4,0)),0) -> 0 | S299: =SUM(P299:R299)*G299 -> 0 | T299: =N299-S299 -> 3816.678 | U299: =T299*1.18 -> 4503.68 | V299: =U299/G299 -> 300.24533 | W299: =V299*F299 -> 4503.68 | X299: =I299-U299 -> 1171.32 | Y299: =X299*H299 -> 1171.32 | Z299: =J299-V299 -> 78.088 | AA299: =IFERROR(ABS(VLOOKUP(A299,ZSSD!$D$2:$G$99933,4,0)),AI299) -> 6.5 | AB299: =IFERROR(IF(VLOOKUP(A299,ZSSD!$D:$H,5,0)="L29",AA299*G299,AA299*L299/100),AA299*L299/100) -> 292.7392 | AC299: 2 | AD299: =2*(T299-AB299)/100 -> 70.478775 | AE299: =+AB299/G299 -> 19.515947 | AF299: =+AD299/G299 -> 4.698585 | AG299: =VLOOKUP(A299,ZSSD!D:D,1,0) -> #N/A | AH299: =VLOOKUP(B299,[2]GRADE!$A:$P,16,0) -> SILVER | AI299: =IF(AH299="SILVER",6.5,IF(AH299="GOLD",8,IF(AH299="INDUSTRIAL",6,IF(AH299="GREEN",7,IF(AH299="BRONZE",5.5,0))))) -> 6.5
A300: 7489734 | B300: =VALUE(LEFT(A300,4)) -> 7489 | C300: =VALUE(RIGHT(A300,3)) -> 734 | D300: =VLOOKUP(C300,Sheet1!$A$2:$K$369991,11,0) -> CAR | E300: SERVO PRIDE XL PLUS 15W40-4x5L - HDPE OL | F300: =VLOOKUP(C300,'PACK MASTER'!$A$2:$I$512998,9,0)*1000 -> 20 | G300: =VLOOKUP(C300,'PACK MASTER'!$A$2:$G$512998,7,0) -> 5 | H300: =F300/G300 -> 4 | I300: =VLOOKUP($A300,ZMRP!$C$2:$F$99995,4,0) -> 1433 | J300: =I300/G300 -> 286.6 | K300: =VLOOKUP($A300,ZLAM!$C$2:$F$99999,4,0) -> 87.72 | L300: =I300*K300/100 -> 1257.0276 | M300: =L300/G300 -> 251.40552 | N300: =L300/1.18 -> 1065.2776 | O300: =N300/G300 -> 213.05553 | P300: =IFERROR(ABS(VLOOKUP($A300,ZTRV!$D$2:$G$99407,4,0)),0) -> 0 | Q300: =IFERROR(ABS(VLOOKUP($A300,ZTR1!$D$2:$G$99999,4,0)),0) -> 0 | R300: =IFERROR(ABS(VLOOKUP($A300,ZTR2!$D$2:$G$99939,4,0)),0) -> 0 | S300: =SUM(P300:R300)*G300 -> 0 | T300: =N300-S300 -> 1065.2776 | U300: =T300*1.18 -> 1257.0276 | V300: =U300/G300 -> 251.40552 | W300: =V300*F300 -> 5028.1104 | X300: =I300-U300 -> 175.9724 | Y300: =X300*H300 -> 703.8896 | Z300: =J300-V300 -> 35.19448 | AA300: =IFERROR(ABS(VLOOKUP(A300,ZSSD!$D$2:$G$99933,4,0)),AI300) -> 6.5 | AB300: =IFERROR(IF(VLOOKUP(A300,ZSSD!$D:$H,5,0)="L29",AA300*G300,AA300*L300/100),AA300*L300/100) -> 81.706794 | AC300: 2 | AD300: =2*(T300-AB300)/100 -> 19.671417 | AE300: =+AB300/G300 -> 16.341359 | AF300: =+AD300/G300 -> 3.9342833 | AG300: =VLOOKUP(A300,ZSSD!D:D,1,0) -> #N/A | AH300: =VLOOKUP(B300,[2]GRADE!$A:$P,16,0) -> SILVER | AI300: =IF(AH300="SILVER",6.5,IF(AH300="GOLD",8,IF(AH300="INDUSTRIAL",6,IF(AH300="GREEN",7,IF(AH300="BRONZE",5.5,0))))) -> 6.5
A301: 7494174 | B301: =VALUE(LEFT(A301,4)) -> 7494 | C301: =VALUE(RIGHT(A301,3)) -> 174 | D301: =VLOOKUP(C301,Sheet1!$A$2:$K$369991,11,0) -> CAR | E301: SERVO SUP.MULT.GRD 20W-40-40X1/2L | F301: =VLOOKUP(C301,'PACK MASTER'!$A$2:$I$512998,9,0)*1000 -> 20 | G301: =VLOOKUP(C301,'PACK MASTER'!$A$2:$G$512998,7,0) -> 0.5 | H301: =F301/G301 -> 40 | I301: =VLOOKUP($A301,ZMRP!$C$2:$F$99995,4,0) -> 176 | J301: =I301/G301 -> 352 | K301: =VLOOKUP($A301,ZLAM!$C$2:$F$99999,4,0) -> 81.01 | L301: =I301*K301/100 -> 142.5776 | M301: =L301/G301 -> 285.1552 | N301: =L301/1.18 -> 120.82847 | O301: =N301/G301 -> 241.65695 | P301: =IFERROR(ABS(VLOOKUP($A301,ZTRV!$D$2:$G$99407,4,0)),0) -> 0 | Q301: =IFERROR(ABS(VLOOKUP($A301,ZTR1!$D$2:$G$99999,4,0)),0) -> 0 | R301: =IFERROR(ABS(VLOOKUP($A301,ZTR2!$D$2:$G$99939,4,0)),0) -> 0 | S301: =SUM(P301:R301)*G301 -> 0 | T301: =N301-S301 -> 120.82847 | U301: =T301*1.18 -> 142.5776 | V301: =U301/G301 -> 285.1552 | W301: =V301*F301 -> 5703.104 | X301: =I301-U301 -> 33.4224 | Y301: =X301*H301 -> 1336.896 | Z301: =J301-V301 -> 66.8448 | AA301: =IFERROR(ABS(VLOOKUP(A301,ZSSD!$D$2:$G$99933,4,0)),AI301) -> 6.5 | AB301: =IFERROR(IF(VLOOKUP(A301,ZSSD!$D:$H,5,0)="L29",AA301*G301,AA301*L301/100),AA301*L301/100) -> 9.267544 | AC301: 2 | AD301: =2*(T301-AB301)/100 -> 2.2312186 | AE301: =+AB301/G301 -> 18.535088 | AF301: =+AD301/G301 -> 4.4624372 | AG301: =VLOOKUP(A301,ZSSD!D:D,1,0) -> #N/A | AH301: =VLOOKUP(B301,[2]GRADE!$A:$P,16,0) -> SILVER | AI301: =IF(AH301="SILVER",6.5,IF(AH301="GOLD",8,IF(AH301="INDUSTRIAL",6,IF(AH301="GREEN",7,IF(AH301="BRONZE",5.5,0))))) -> 6.5
A302: 7494178 | B302: =VALUE(LEFT(A302,4)) -> 7494 | C302: =VALUE(RIGHT(A302,3)) -> 178 | D302: =VLOOKUP(C302,Sheet1!$A$2:$K$369991,11,0) -> CAR | E302: SERVO SUP.MULT.GRD 20W-40-20 x 1/2L-LINE | F302: =VLOOKUP(C302,'PACK MASTER'!$A$2:$I$512998,9,0)*1000 -> 10 | G302: =VLOOKUP(C302,'PACK MASTER'!$A$2:$G$512998,7,0) -> 0.5 | H302: =F302/G302 -> 20 | I302: =VLOOKUP($A302,ZMRP!$C$2:$F$99995,4,0) -> 172 | J302: =I302/G302 -> 344 | K302: =VLOOKUP($A302,ZLAM!$C$2:$F$99999,4,0) -> 80.47 | L302: =I302*K302/100 -> 138.4084 | M302: =L302/G302 -> 276.8168 | N302: =L302/1.18 -> 117.29525 | O302: =N302/G302 -> 234.59051 | P302: =IFERROR(ABS(VLOOKUP($A302,ZTRV!$D$2:$G$99407,4,0)),0) -> 0 | Q302: =IFERROR(ABS(VLOOKUP($A302,ZTR1!$D$2:$G$99999,4,0)),0) -> 0 | R302: =IFERROR(ABS(VLOOKUP($A302,ZTR2!$D$2:$G$99939,4,0)),0) -> 0 | S302: =SUM(P302:R302)*G302 -> 0 | T302: =N302-S302 -> 117.29525 | U302: =T302*1.18 -> 138.4084 | V302: =U302/G302 -> 276.8168 | W302: =V302*F302 -> 2768.168 | X302: =I302-U302 -> 33.5916 | Y302: =X302*H302 -> 671.832 | Z302: =J302-V302 -> 67.1832 | AA302: =IFERROR(ABS(VLOOKUP(A302,ZSSD!$D$2:$G$99933,4,0)),AI302) -> 6.5 | AB302: =IFERROR(IF(VLOOKUP(A302,ZSSD!$D:$H,5,0)="L29",AA302*G302,AA302*L302/100),AA302*L302/100) -> 8.996546 | AC302: 2 | AD302: =2*(T302-AB302)/100 -> 2.1659742 | AE302: =+AB302/G302 -> 17.993092 | AF302: =+AD302/G302 -> 4.3319483 | AG302: =VLOOKUP(A302,ZSSD!D:D,1,0) -> #N/A | AH302: =VLOOKUP(B302,[2]GRADE!$A:$P,16,0) -> SILVER | AI302: =IF(AH302="SILVER",6.5,IF(AH302="GOLD",8,IF(AH302="INDUSTRIAL",6,IF(AH302="GREEN",7,IF(AH302="BRONZE",5.5,0))))) -> 6.5
A303: 7494184 | B303: =VALUE(LEFT(A303,4)) -> 7494 | C303: =VALUE(RIGHT(A303,3)) -> 184 | D303: =VLOOKUP(C303,Sheet1!$A$2:$K$369991,11,0) -> CAR | E303: SERVO SUP.MULT.GRD 20W-40-20 X 1 L | F303: =VLOOKUP(C303,'PACK MASTER'!$A$2:$I$512998,9,0)*1000 -> 20 | G303: =VLOOKUP(C303,'PACK MASTER'!$A$2:$G$512998,7,0) -> 1 | H303: =F303/G303 -> 20 | I303: =VLOOKUP($A303,ZMRP!$C$2:$F$99995,4,0) -> 330 | J303: =I303/G303 -> 330 | K303: =VLOOKUP($A303,ZLAM!$C$2:$F$99999,4,0) -> 80.09 | L303: =I303*K303/100 -> 264.297 | M303: =L303/G303 -> 264.297 | N303: =L303/1.18 -> 223.98051 | O303: =N303/G303 -> 223.98051 | P303: =IFERROR(ABS(VLOOKUP($A303,ZTRV!$D$2:$G$99407,4,0)),0) -> 0 | Q303: =IFERROR(ABS(VLOOKUP($A303,ZTR1!$D$2:$G$99999,4,0)),0) -> 0 | R303: =IFERROR(ABS(VLOOKUP($A303,ZTR2!$D$2:$G$99939,4,0)),0) -> 0 | S303: =SUM(P303:R303)*G303 -> 0 | T303: =N303-S303 -> 223.98051 | U303: =T303*1.18 -> 264.297 | V303: =U303/G303 -> 264.297 | W303: =V303*F303 -> 5285.94 | X303: =I303-U303 -> 65.703 | Y303: =X303*H303 -> 1314.06 | Z303: =J303-V303 -> 65.703 | AA303: =IFERROR(ABS(VLOOKUP(A303,ZSSD!$D$2:$G$99933,4,0)),AI303) -> 6.5 | AB303: =IFERROR(IF(VLOOKUP(A303,ZSSD!$D:$H,5,0)="L29",AA303*G303,AA303*L303/100),AA303*L303/100) -> 17.179305 | AC303: 2 | AD303: =2*(T303-AB303)/100 -> 4.1360241 | AE303: =+AB303/G303 -> 17.179305 | AF303: =+AD303/G303 -> 4.1360241 | AG303: =VLOOKUP(A303,ZSSD!D:D,1,0) -> #N/A | AH303: =VLOOKUP(B303,[2]GRADE!$A:$P,16,0) -> SILVER | AI303: =IF(AH303="SILVER",6.5,IF(AH303="GOLD",8,IF(AH303="INDUSTRIAL",6,IF(AH303="GREEN",7,IF(AH303="BRONZE",5.5,0))))) -> 6.5
A304: 7494188 | B304: =VALUE(LEFT(A304,4)) -> 7494 | C304: =VALUE(RIGHT(A304,3)) -> 188 | D304: =VLOOKUP(C304,Sheet1!$A$2:$K$369991,11,0) -> CAR | E304: SERVO SUP.MULT.GRD 20W-40-20x1L- LINER | F304: =VLOOKUP(C304,'PACK MASTER'!$A$2:$I$512998,9,0)*1000 -> 20 | G304: =VLOOKUP(C304,'PACK MASTER'!$A$2:$G$512998,7,0) -> 1 | H304: =F304/G304 -> 20 | I304: =VLOOKUP($A304,ZMRP!$C$2:$F$99995,4,0) -> 330 | J304: =I304/G304 -> 330 | K304: =VLOOKUP($A304,ZLAM!$C$2:$F$99999,4,0) -> 78.83 | L304: =I304*K304/100 -> 260.139 | M304: =L304/G304 -> 260.139 | N304: =L304/1.18 -> 220.45678 | O304: =N304/G304 -> 220.45678 | P304: =IFERROR(ABS(VLOOKUP($A304,ZTRV!$D$2:$G$99407,4,0)),0) -> 0 | Q304: =IFERROR(ABS(VLOOKUP($A304,ZTR1!$D$2:$G$99999,4,0)),0) -> 0 | R304: =IFERROR(ABS(VLOOKUP($A304,ZTR2!$D$2:$G$99939,4,0)),0) -> 0 | S304: =SUM(P304:R304)*G304 -> 0 | T304: =N304-S304 -> 220.45678 | U304: =T304*1.18 -> 260.139 | V304: =U304/G304 -> 260.139 | W304: =V304*F304 -> 5202.78 | X304: =I304-U304 -> 69.861 | Y304: =X304*H304 -> 1397.22 | Z304: =J304-V304 -> 69.861 | AA304: =IFERROR(ABS(VLOOKUP(A304,ZSSD!$D$2:$G$99933,4,0)),AI304) -> 6.5 | AB304: =IFERROR(IF(VLOOKUP(A304,ZSSD!$D:$H,5,0)="L29",AA304*G304,AA304*L304/100),AA304*L304/100) -> 16.909035 | AC304: 2 | AD304: =2*(T304-AB304)/100 -> 4.0709549 | AE304: =+AB304/G304 -> 16.909035 | AF304: =+AD304/G304 -> 4.0709549 | AG304: =VLOOKUP(A304,ZSSD!D:D,1,0) -> #N/A | AH304: =VLOOKUP(B304,[2]GRADE!$A:$P,16,0) -> SILVER | AI304: =IF(AH304="SILVER",6.5,IF(AH304="GOLD",8,IF(AH304="INDUSTRIAL",6,IF(AH304="GREEN",7,IF(AH304="BRONZE",5.5,0))))) -> 6.5
A305: 7494207 | B305: =VALUE(LEFT(A305,4)) -> 7494 | C305: =VALUE(RIGHT(A305,3)) -> 207 | D305: =VLOOKUP(C305,Sheet1!$A$2:$K$369991,11,0) -> CAR | E305: SERVO SUP.MULT.GRD 20W-40-20x(0.9+0.1)L | F305: =VLOOKUP(C305,'PACK MASTER'!$A$2:$I$512998,9,0)*1000 -> 20 | G305: =VLOOKUP(C305,'PACK MASTER'!$A$2:$G$512998,7,0) -> 1 | H305: =F305/G305 -> 20 | I305: =VLOOKUP($A305,ZMRP!$C$2:$F$99995,4,0) -> 330 | J305: =I305/G305 -> 330 | K305: =VLOOKUP($A305,ZLAM!$C$2:$F$99999,4,0) -> 80.09 | L305: =I305*K305/100 -> 264.297 | M305: =L305/G305 -> 264.297 | N305: =L305/1.18 -> 223.98051 | O305: =N305/G305 -> 223.98051 | P305: =IFERROR(ABS(VLOOKUP($A305,ZTRV!$D$2:$G$99407,4,0)),0) -> 0 | Q305: =IFERROR(ABS(VLOOKUP($A305,ZTR1!$D$2:$G$99999,4,0)),0) -> 0 | R305: =IFERROR(ABS(VLOOKUP($A305,ZTR2!$D$2:$G$99939,4,0)),0) -> 0 | S305: =SUM(P305:R305)*G305 -> 0 | T305: =N305-S305 -> 223.98051 | U305: =T305*1.18 -> 264.297 | V305: =U305/G305 -> 264.297 | W305: =V305*F305 -> 5285.94 | X305: =I305-U305 -> 65.703 | Y305: =X305*H305 -> 1314.06 | Z305: =J305-V305 -> 65.703 | AA305: =IFERROR(ABS(VLOOKUP(A305,ZSSD!$D$2:$G$99933,4,0)),AI305) -> 6.5 | AB305: =IFERROR(IF(VLOOKUP(A305,ZSSD!$D:$H,5,0)="L29",AA305*G305,AA305*L305/100),AA305*L305/100) -> 17.179305 | AC305: 2 | AD305: =2*(T305-AB305)/100 -> 4.1360241 | AE305: =+AB305/G305 -> 17.179305 | AF305: =+AD305/G305 -> 4.1360241 | AG305: =VLOOKUP(A305,ZSSD!D:D,1,0) -> #N/A | AH305: =VLOOKUP(B305,[2]GRADE!$A:$P,16,0) -> SILVER | AI305: =IF(AH305="SILVER",6.5,IF(AH305="GOLD",8,IF(AH305="INDUSTRIAL",6,IF(AH305="GREEN",7,IF(AH305="BRONZE",5.5,0))))) -> 6.5
A306: 7494215 | B306: =VALUE(LEFT(A306,4)) -> 7494 | C306: =VALUE(RIGHT(A306,3)) -> 215 | D306: =VLOOKUP(C306,Sheet1!$A$2:$K$369991,11,0) -> CAR | E306: SERVO SUP.MULT.GRD 20W-40-4X(4.5+0.5)L | F306: =VLOOKUP(C306,'PACK MASTER'!$A$2:$I$512998,9,0)*1000 -> 20 | G306: =VLOOKUP(C306,'PACK MASTER'!$A$2:$G$512998,7,0) -> 5 | H306: =F306/G306 -> 4 | I306: =VLOOKUP($A306,ZMRP!$C$2:$F$99995,4,0) -> 1600 | J306: =I306/G306 -> 320 | K306: =VLOOKUP($A306,ZLAM!$C$2:$F$99999,4,0) -> 82.44 | L306: =I306*K306/100 -> 1319.04 | M306: =L306/G306 -> 263.808 | N306: =L306/1.18 -> 1117.8305 | O306: =N306/G306 -> 223.5661 | P306: =IFERROR(ABS(VLOOKUP($A306,ZTRV!$D$2:$G$99407,4,0)),0) -> 0 | Q306: =IFERROR(ABS(VLOOKUP($A306,ZTR1!$D$2:$G$99999,4,0)),0) -> 0 | R306: =IFERROR(ABS(VLOOKUP($A306,ZTR2!$D$2:$G$99939,4,0)),0) -> 0 | S306: =SUM(P306:R306)*G306 -> 0 | T306: =N306-S306 -> 1117.8305 | U306: =T306*1.18 -> 1319.04 | V306: =U306/G306 -> 263.808 | W306: =V306*F306 -> 5276.16 | X306: =I306-U306 -> 280.96 | Y306: =X306*H306 -> 1123.84 | Z306: =J306-V306 -> 56.192 | AA306: =IFERROR(ABS(VLOOKUP(A306,ZSSD!$D$2:$G$99933,4,0)),AI306) -> 6.5 | AB306: =IFERROR(IF(VLOOKUP(A306,ZSSD!$D:$H,5,0)="L29",AA306*G306,AA306*L306/100),AA306*L306/100) -> 85.7376 | AC306: 2 | AD306: =2*(T306-AB306)/100 -> 20.641858 | AE306: =+AB306/G306 -> 17.14752 | AF306: =+AD306/G306 -> 4.1283716 | AG306: =VLOOKUP(A306,ZSSD!D:D,1,0) -> #N/A | AH306: =VLOOKUP(B306,[2]GRADE!$A:$P,16,0) -> SILVER | AI306: =IF(AH306="SILVER",6.5,IF(AH306="GOLD",8,IF(AH306="INDUSTRIAL",6,IF(AH306="GREEN",7,IF(AH306="BRONZE",5.5,0))))) -> 6.5
A307: 7494229 | B307: =VALUE(LEFT(A307,4)) -> 7494 | C307: =VALUE(RIGHT(A307,3)) -> 229 | D307: =VLOOKUP(C307,Sheet1!$A$2:$K$369991,11,0) -> CAR | E307: SERVO SUP.MULT.GRD 20W-40-20 X 1 L PROMO | F307: =VLOOKUP(C307,'PACK MASTER'!$A$2:$I$512998,9,0)*1000 -> 20 | G307: =VLOOKUP(C307,'PACK MASTER'!$A$2:$G$512998,7,0) -> 1 | H307: =F307/G307 -> 20 | I307: =VLOOKUP($A307,ZMRP!$C$2:$F$99995,4,0) -> 330 | J307: =I307/G307 -> 330 | K307: =VLOOKUP($A307,ZLAM!$C$2:$F$99999,4,0) -> 80.09 | L307: =I307*K307/100 -> 264.297 | M307: =L307/G307 -> 264.297 | N307: =L307/1.18 -> 223.98051 | O307: =N307/G307 -> 223.98051 | P307: =IFERROR(ABS(VLOOKUP($A307,ZTRV!$D$2:$G$99407,4,0)),0) -> 0 | Q307: =IFERROR(ABS(VLOOKUP($A307,ZTR1!$D$2:$G$99999,4,0)),0) -> 0 | R307: =IFERROR(ABS(VLOOKUP($A307,ZTR2!$D$2:$G$99939,4,0)),0) -> 0 | S307: =SUM(P307:R307)*G307 -> 0 | T307: =N307-S307 -> 223.98051 | U307: =T307*1.18 -> 264.297 | V307: =U307/G307 -> 264.297 | W307: =V307*F307 -> 5285.94 | X307: =I307-U307 -> 65.703 | Y307: =X307*H307 -> 1314.06 | Z307: =J307-V307 -> 65.703 | AA307: =IFERROR(ABS(VLOOKUP(A307,ZSSD!$D$2:$G$99933,4,0)),AI307) -> 6.5 | AB307: =IFERROR(IF(VLOOKUP(A307,ZSSD!$D:$H,5,0)="L29",AA307*G307,AA307*L307/100),AA307*L307/100) -> 17.179305 | AC307: 2 | AD307: =2*(T307-AB307)/100 -> 4.1360241 | AE307: =+AB307/G307 -> 17.179305 | AF307: =+AD307/G307 -> 4.1360241 | AG307: =VLOOKUP(A307,ZSSD!D:D,1,0) -> #N/A | AH307: =VLOOKUP(B307,[2]GRADE!$A:$P,16,0) -> SILVER | AI307: =IF(AH307="SILVER",6.5,IF(AH307="GOLD",8,IF(AH307="INDUSTRIAL",6,IF(AH307="GREEN",7,IF(AH307="BRONZE",5.5,0))))) -> 6.5
... A324: 7511184 | B324: =VALUE(LEFT(A324,4)) -> 7511 | C324: =VALUE(RIGHT(A324,3)) -> 184 | D324: =VLOOKUP(C324,Sheet1!$A$2:$K$369991,11,0) -> CAR | E324: SERVO GEAR SUPER 80W-90 - 20 X 1 L HDPE | F324: =VLOOKUP(C324,'PACK MASTER'!$A$2:$I$512998,9,0)*1000 -> 20 | G324: =VLOOKUP(C324,'PACK MASTER'!$A$2:$G$512998,7,0) -> 1 | H324: =F324/G324 -> 20 | I324: =VLOOKUP($A324,ZMRP!$C$2:$F$99995,4,0) -> 390 | J324: =I324/G324 -> 390 | K324: =VLOOKUP($A324,ZLAM!$C$2:$F$99999,4,0) -> 76.99 | L324: =I324*K324/100 -> 300.261 | M324: =L324/G324 -> 300.261 | N324: =L324/1.18 -> 254.45847 | O324: =N324/G324 -> 254.45847 | P324: =IFERROR(ABS(VLOOKUP($A324,ZTRV!$D$2:$G$99407,4,0)),0) -> 28 | Q324: =IFERROR(ABS(VLOOKUP($A324,ZTR1!$D$2:$G$99999,4,0)),0) -> 0 | R324: =IFERROR(ABS(VLOOKUP($A324,ZTR2!$D$2:$G$99939,4,0)),0) -> 0 | S324: =SUM(P324:R324)*G324 -> 28 | T324: =N324-S324 -> 226.45847 | U324: =T324*1.18 -> 267.221 | V324: =U324/G324 -> 267.221 | W324: =V324*F324 -> 5344.42 | X324: =I324-U324 -> 122.779 | Y324: =X324*H324 -> 2455.58 | Z324: =J324-V324 -> 122.779 | AA324: =IFERROR(ABS(VLOOKUP(A324,ZSSD!$D$2:$G$99933,4,0)),AI324) -> 6.5 | AB324: =IFERROR(IF(VLOOKUP(A324,ZSSD!$D:$H,5,0)="L29",AA324*G324,AA324*L324/100),AA324*L324/100) -> 19.516965 | AC324: 2 | AD324: =2*(T324-AB324)/100 -> 4.1388302 | AE324: =+AB324/G324 -> 19.516965 | AF324: =+AD324/G324 -> 4.1388302 | AG324: =VLOOKUP(A324,ZSSD!D:D,1,0) -> #N/A | AH324: =VLOOKUP(B324,[2]GRADE!$A:$P,16,0) -> SILVER | AI324: =IF(AH324="SILVER",6.5,IF(AH324="GOLD",8,IF(AH324="INDUSTRIAL",6,IF(AH324="GREEN",7,IF(AH324="BRONZE",5.5,0))))) -> 6.5
A325: 7511195 | B325: 7511 | C325: 195 | D325: =VLOOKUP(C325,Sheet1!$A$2:$K$369991,11,0) -> CAR | E325: SERVO GEAR SUPER 80W-90-4 X 2.5 L | F325: =VLOOKUP(C325,'PACK MASTER'!$A$2:$I$512998,9,0)*1000 -> 10 | G325: =VLOOKUP(C325,'PACK MASTER'!$A$2:$G$512998,7,0) -> 2.5 | H325: =F325/G325 -> 4 | I325: =VLOOKUP($A325,ZMRP!$C$2:$F$99995,4,0) -> 960 | J325: =I325/G325 -> 384 | K325: =VLOOKUP($A325,ZLAM!$C$2:$F$99999,4,0) -> 72 | L325: =I325*K325/100 -> 691.2 | M325: =L325/G325 -> 276.48 | N325: =L325/1.18 -> 585.76271 | O325: =N325/G325 -> 234.30508 | P325: =IFERROR(ABS(VLOOKUP($A325,ZTRV!$D$2:$G$99407,4,0)),0) -> 33 | Q325: =IFERROR(ABS(VLOOKUP($A325,ZTR1!$D$2:$G$99999,4,0)),0) -> 0 | R325: =IFERROR(ABS(VLOOKUP($A325,ZTR2!$D$2:$G$99939,4,0)),0) -> 0 | S325: =SUM(P325:R325)*G325 -> 82.5 | T325: =N325-S325 -> 503.26271 | U325: =T325*1.18 -> 593.85 | V325: =U325/G325 -> 237.54 | W325: =V325*F325 -> 2375.4 | X325: =I325-U325 -> 366.15 | Y325: =X325*H325 -> 1464.6 | Z325: =J325-V325 -> 146.46 | AA325: =IFERROR(ABS(VLOOKUP(A325,ZSSD!$D$2:$G$99933,4,0)),AI325) -> 6.5 | AB325: =IFERROR(IF(VLOOKUP(A325,ZSSD!$D:$H,5,0)="L29",AA325*G325,AA325*L325/100),AA325*L325/100) -> 44.928 | AC325: 2 | AD325: =2*(T325-AB325)/100 -> 9.1666942 | AE325: =+AB325/G325 -> 17.9712 | AF325: =+AD325/G325 -> 3.6666777 | AG325: =VLOOKUP(A325,ZSSD!D:D,1,0) -> #N/A | AH325: =VLOOKUP(B325,[2]GRADE!$A:$P,16,0) -> SILVER | AI325: =IF(AH325="SILVER",6.5,IF(AH325="GOLD",8,IF(AH325="INDUSTRIAL",6,IF(AH325="GREEN",7,IF(AH325="BRONZE",5.5,0))))) -> 6.5
A326: 7511234 | B326: =VALUE(LEFT(A326,4)) -> 7511 | C326: =VALUE(RIGHT(A326,3)) -> 234 | D326: =VLOOKUP(C326,Sheet1!$A$2:$K$369991,11,0) -> CAR | E326: SERVO GEAR SUPER 80W-90 - 4 X 5 L HDPE | F326: =VLOOKUP(C326,'PACK MASTER'!$A$2:$I$512998,9,0)*1000 -> 20 | G326: =VLOOKUP(C326,'PACK MASTER'!$A$2:$G$512998,7,0) -> 5 | H326: =F326/G326 -> 4 | I326: =VLOOKUP($A326,ZMRP!$C$2:$F$99995,4,0) -> 1875 | J326: =I326/G326 -> 375 | K326: =VLOOKUP($A326,ZLAM!$C$2:$F$99999,4,0) -> 77.72 | L326: =I326*K326/100 -> 1457.25 | M326: =L326/G326 -> 291.45 | N326: =L326/1.18 -> 1234.9576 | O326: =N326/G326 -> 246.99153 | P326: =IFERROR(ABS(VLOOKUP($A326,ZTRV!$D$2:$G$99407,4,0)),0) -> 33 | Q326: =IFERROR(ABS(VLOOKUP($A326,ZTR1!$D$2:$G$99999,4,0)),0) -> 0 | R326: =IFERROR(ABS(VLOOKUP($A326,ZTR2!$D$2:$G$99939,4,0)),0) -> 0 | S326: =SUM(P326:R326)*G326 -> 165 | T326: =N326-S326 -> 1069.9576 | U326: =T326*1.18 -> 1262.55 | V326: =U326/G326 -> 252.51 | W326: =V326*F326 -> 5050.2 | X326: =I326-U326 -> 612.45 | Y326: =X326*H326 -> 2449.8 | Z326: =J326-V326 -> 122.49 | AA326: =IFERROR(ABS(VLOOKUP(A326,ZSSD!$D$2:$G$99933,4,0)),AI326) -> 6.5 | AB326: =IFERROR(IF(VLOOKUP(A326,ZSSD!$D:$H,5,0)="L29",AA326*G326,AA326*L326/100),AA326*L326/100) -> 94.72125 | AC326: 2 | AD326: =2*(T326-AB326)/100 -> 19.504728 | AE326: =+AB326/G326 -> 18.94425 | AF326: =+AD326/G326 -> 3.9009455 | AG326: =VLOOKUP(A326,ZSSD!D:D,1,0) -> #N/A | AH326: =VLOOKUP(B326,[2]GRADE!$A:$P,16,0) -> SILVER | AI326: =IF(AH326="SILVER",6.5,IF(AH326="GOLD",8,IF(AH326="INDUSTRIAL",6,IF(AH326="GREEN",7,IF(AH326="BRONZE",5.5,0))))) -> 6.5
A327: 7511240 | B327: =VALUE(LEFT(A327,4)) -> 7511 | C327: =VALUE(RIGHT(A327,3)) -> 240 | D327: =VLOOKUP(C327,Sheet1!$A$2:$K$369991,11,0) -> CAR | E327: SERVO GEAR SUPER 80W-90-4 X 5 L PROMO | F327: =VLOOKUP(C327,'PACK MASTER'!$A$2:$I$512998,9,0)*1000 -> 20 | G327: =VLOOKUP(C327,'PACK MASTER'!$A$2:$G$512998,7,0) -> 5 | H327: =F327/G327 -> 4 | I327: =VLOOKUP($A327,ZMRP!$C$2:$F$99995,4,0) -> 1875 | J327: =I327/G327 -> 375 | K327: =VLOOKUP($A327,ZLAM!$C$2:$F$99999,4,0) -> 77.72 | L327: =I327*K327/100 -> 1457.25 | M327: =L327/G327 -> 291.45 | N327: =L327/1.18 -> 1234.9576 | O327: =N327/G327 -> 246.99153 | P327: =IFERROR(ABS(VLOOKUP($A327,ZTRV!$D$2:$G$99407,4,0)),0) -> 33 | Q327: =IFERROR(ABS(VLOOKUP($A327,ZTR1!$D$2:$G$99999,4,0)),0) -> 0 | R327: =IFERROR(ABS(VLOOKUP($A327,ZTR2!$D$2:$G$99939,4,0)),0) -> 0 | S327: =SUM(P327:R327)*G327 -> 165 | T327: =N327-S327 -> 1069.9576 | U327: =T327*1.18 -> 1262.55 | V327: =U327/G327 -> 252.51 | W327: =V327*F327 -> 5050.2 | X327: =I327-U327 -> 612.45 | Y327: =X327*H327 -> 2449.8 | Z327: =J327-V327 -> 122.49 | AA327: =IFERROR(ABS(VLOOKUP(A327,ZSSD!$D$2:$G$99933,4,0)),AI327) -> 6.5 | AB327: =IFERROR(IF(VLOOKUP(A327,ZSSD!$D:$H,5,0)="L29",AA327*G327,AA327*L327/100),AA327*L327/100) -> 94.72125 | AC327: 2 | AD327: =2*(T327-AB327)/100 -> 19.504728 | AE327: =+AB327/G327 -> 18.94425 | AF327: =+AD327/G327 -> 3.9009455 | AG327: =VLOOKUP(A327,ZSSD!D:D,1,0) -> #N/A | AH327: =VLOOKUP(B327,[2]GRADE!$A:$P,16,0) -> SILVER | AI327: =IF(AH327="SILVER",6.5,IF(AH327="GOLD",8,IF(AH327="INDUSTRIAL",6,IF(AH327="GREEN",7,IF(AH327="BRONZE",5.5,0))))) -> 6.5
A328: 7511242 | B328: =VALUE(LEFT(A328,4)) -> 7511 | C328: =VALUE(RIGHT(A328,3)) -> 242 | D328: =VLOOKUP(C328,Sheet1!$A$2:$K$369991,11,0) -> BUC | E328: SERVO GEAR SUPER 80W-90-10 L | F328: =VLOOKUP(C328,'PACK MASTER'!$A$2:$I$512998,9,0)*1000 -> 10 | G328: =VLOOKUP(C328,'PACK MASTER'!$A$2:$G$512998,7,0) -> 10 | H328: =F328/G328 -> 1 | I328: =VLOOKUP($A328,ZMRP!$C$2:$F$99995,4,0) -> 3600 | J328: =I328/G328 -> 360 | K328: =VLOOKUP($A328,ZLAM!$C$2:$F$99999,4,0) -> 79.59 | L328: =I328*K328/100 -> 2865.24 | M328: =L328/G328 -> 286.524 | N328: =L328/1.18 -> 2428.1695 | O328: =N328/G328 -> 242.81695 | P328: =IFERROR(ABS(VLOOKUP($A328,ZTRV!$D$2:$G$99407,4,0)),0) -> 33 | Q328: =IFERROR(ABS(VLOOKUP($A328,ZTR1!$D$2:$G$99999,4,0)),0) -> 0 | R328: =IFERROR(ABS(VLOOKUP($A328,ZTR2!$D$2:$G$99939,4,0)),0) -> 0 | S328: =SUM(P328:R328)*G328 -> 330 | T328: =N328-S328 -> 2098.1695 | U328: =T328*1.18 -> 2475.84 | V328: =U328/G328 -> 247.584 | W328: =V328*F328 -> 2475.84 | X328: =I328-U328 -> 1124.16 | Y328: =X328*H328 -> 1124.16 | Z328: =J328-V328 -> 112.416 | AA328: =IFERROR(ABS(VLOOKUP(A328,ZSSD!$D$2:$G$99933,4,0)),AI328) -> 6.5 | AB328: =IFERROR(IF(VLOOKUP(A328,ZSSD!$D:$H,5,0)="L29",AA328*G328,AA328*L328/100),AA328*L328/100) -> 186.2406 | AC328: 2 | AD328: =2*(T328-AB328)/100 -> 38.238578 | AE328: =+AB328/G328 -> 18.62406 | AF328: =+AD328/G328 -> 3.8238578 | AG328: =VLOOKUP(A328,ZSSD!D:D,1,0) -> #N/A | AH328: =VLOOKUP(B328,[2]GRADE!$A:$P,16,0) -> SILVER | AI328: =IF(AH328="SILVER",6.5,IF(AH328="GOLD",8,IF(AH328="INDUSTRIAL",6,IF(AH328="GREEN",7,IF(AH328="BRONZE",5.5,0))))) -> 6.5
A329: 7511251 | B329: =VALUE(LEFT(A329,4)) -> 7511 | C329: =VALUE(RIGHT(A329,3)) -> 251 | D329: =VLOOKUP(C329,Sheet1!$A$2:$K$369991,11,0) -> BUC | E329: SERVO GEAR SUPER 80W-90-7.5 L | F329: =VLOOKUP(C329,'PACK MASTER'!$A$2:$I$512998,9,0)*1000 -> 7.5 | G329: =VLOOKUP(C329,'PACK MASTER'!$A$2:$G$512998,7,0) -> 7.5 | H329: =F329/G329 -> 1 | I329: =VLOOKUP($A329,ZMRP!$C$2:$F$99995,4,0) -> 2763 | J329: =I329/G329 -> 368.4 | K329: =VLOOKUP($A329,ZLAM!$C$2:$F$99999,4,0) -> 78.16 | L329: =I329*K329/100 -> 2159.5608 | M329: =L329/G329 -> 287.94144 | N329: =L329/1.18 -> 1830.1363 | O329: =N329/G329 -> 244.01817 | P329: =IFERROR(ABS(VLOOKUP($A329,ZTRV!$D$2:$G$99407,4,0)),0) -> 33 | Q329: =IFERROR(ABS(VLOOKUP($A329,ZTR1!$D$2:$G$99999,4,0)),0) -> 0 | R329: =IFERROR(ABS(VLOOKUP($A329,ZTR2!$D$2:$G$99939,4,0)),0) -> 0 | S329: =SUM(P329:R329)*G329 -> 247.5 | T329: =N329-S329 -> 1582.6363 | U329: =T329*1.18 -> 1867.5108 | V329: =U329/G329 -> 249.00144 | W329: =V329*F329 -> 1867.5108 | X329: =I329-U329 -> 895.4892 | Y329: =X329*H329 -> 895.4892 | Z329: =J329-V329 -> 119.39856 | AA329: =IFERROR(ABS(VLOOKUP(A329,ZSSD!$D$2:$G$99933,4,0)),AI329) -> 6.5 | AB329: =IFERROR(IF(VLOOKUP(A329,ZSSD!$D:$H,5,0)="L29",AA329*G329,AA329*L329/100),AA329*L329/100) -> 140.37145 | AC329: 2 | AD329: =2*(T329-AB329)/100 -> 28.845296 | AE329: =+AB329/G329 -> 18.716194 | AF329: =+AD329/G329 -> 3.8460395 | AG329: =VLOOKUP(A329,ZSSD!D:D,1,0) -> #N/A | AH329: =VLOOKUP(B329,[2]GRADE!$A:$P,16,0) -> SILVER | AI329: =IF(AH329="SILVER",6.5,IF(AH329="GOLD",8,IF(AH329="INDUSTRIAL",6,IF(AH329="GREEN",7,IF(AH329="BRONZE",5.5,0))))) -> 6.5
A330: 7511265 | B330: =VALUE(LEFT(A330,4)) -> 7511 | C330: =VALUE(RIGHT(A330,3)) -> 265 | D330: =VLOOKUP(C330,Sheet1!$A$2:$K$369991,11,0) -> BUC | E330: SERVO GEAR SUPER 80W-90 - 20 L BUC | F330: =VLOOKUP(C330,'PACK MASTER'!$A$2:$I$512998,9,0)*1000 -> 20 | G330: =VLOOKUP(C330,'PACK MASTER'!$A$2:$G$512998,7,0) -> 20 | H330: =F330/G330 -> 1 | I330: =VLOOKUP($A330,ZMRP!$C$2:$F$99995,4,0) -> 7200 | J330: =I330/G330 -> 360 | K330: =VLOOKUP($A330,ZLAM!$C$2:$F$99999,4,0) -> 79.59 | L330: =I330*K330/100 -> 5730.48 | M330: =L330/G330 -> 286.524 | N330: =L330/1.18 -> 4856.339 | O330: =N330/G330 -> 242.81695 | P330: =IFERROR(ABS(VLOOKUP($A330,ZTRV!$D$2:$G$99407,4,0)),0) -> 48 | Q330: =IFERROR(ABS(VLOOKUP($A330,ZTR1!$D$2:$G$99999,4,0)),0) -> 0 | R330: =IFERROR(ABS(VLOOKUP($A330,ZTR2!$D$2:$G$99939,4,0)),0) -> 0 | S330: =SUM(P330:R330)*G330 -> 960 | T330: =N330-S330 -> 3896.339 | U330: =T330*1.18 -> 4597.68 | V330: =U330/G330 -> 229.884 | W330: =V330*F330 -> 4597.68 | X330: =I330-U330 -> 2602.32 | Y330: =X330*H330 -> 2602.32 | Z330: =J330-V330 -> 130.116 | AA330: =IFERROR(ABS(VLOOKUP(A330,ZSSD!$D$2:$G$99933,4,0)),AI330) -> 6.5 | AB330: =IFERROR(IF(VLOOKUP(A330,ZSSD!$D:$H,5,0)="L29",AA330*G330,AA330*L330/100),AA330*L330/100) -> 372.4812 | AC330: 2 | AD330: =2*(T330-AB330)/100 -> 70.477156 | AE330: =+AB330/G330 -> 18.62406 | AF330: =+AD330/G330 -> 3.5238578 | AG330: =VLOOKUP(A330,ZSSD!D:D,1,0) -> #N/A | AH330: =VLOOKUP(B330,[2]GRADE!$A:$P,16,0) -> SILVER | AI330: =IF(AH330="SILVER",6.5,IF(AH330="GOLD",8,IF(AH330="INDUSTRIAL",6,IF(AH330="GREEN",7,IF(AH330="BRONZE",5.5,0))))) -> 6.5
A331: 7511269 | B331: =VALUE(LEFT(A331,4)) -> 7511 | C331: =VALUE(RIGHT(A331,3)) -> 269 | D331: =VLOOKUP(C331,Sheet1!$A$2:$K$369991,11,0) -> BUC | E331: SERVO GEAR SUPER 80W-90-20 L PROMO | F331: =VLOOKUP(C331,'PACK MASTER'!$A$2:$I$512998,9,0)*1000 -> 20 | G331: =VLOOKUP(C331,'PACK MASTER'!$A$2:$G$512998,7,0) -> 20 | H331: =F331/G331 -> 1 | I331: =VLOOKUP($A331,ZMRP!$C$2:$F$99995,4,0) -> 7200 | J331: =I331/G331 -> 360 | K331: =VLOOKUP($A331,ZLAM!$C$2:$F$99999,4,0) -> 79.59 | L331: =I331*K331/100 -> 5730.48 | M331: =L331/G331 -> 286.524 | N331: =L331/1.18 -> 4856.339 | O331: =N331/G331 -> 242.81695 | P331: =IFERROR(ABS(VLOOKUP($A331,ZTRV!$D$2:$G$99407,4,0)),0) -> 48 | Q331: =IFERROR(ABS(VLOOKUP($A331,ZTR1!$D$2:$G$99999,4,0)),0) -> 0 | R331: =IFERROR(ABS(VLOOKUP($A331,ZTR2!$D$2:$G$99939,4,0)),0) -> 0 | S331: =SUM(P331:R331)*G331 -> 960 | T331: =N331-S331 -> 3896.339 | U331: =T331*1.18 -> 4597.68 | V331: =U331/G331 -> 229.884 | W331: =V331*F331 -> 4597.68 | X331: =I331-U331 -> 2602.32 | Y331: =X331*H331 -> 2602.32 | Z331: =J331-V331 -> 130.116 | AA331: =IFERROR(ABS(VLOOKUP(A331,ZSSD!$D$2:$G$99933,4,0)),AI331) -> 6.5 | AB331: =IFERROR(IF(VLOOKUP(A331,ZSSD!$D:$H,5,0)="L29",AA331*G331,AA331*L331/100),AA331*L331/100) -> 372.4812 | AC331: 2 | AD331: =2*(T331-AB331)/100 -> 70.477156 | AE331: =+AB331/G331 -> 18.62406 | AF331: =+AD331/G331 -> 3.5238578 | AG331: =VLOOKUP(A331,ZSSD!D:D,1,0) -> #N/A | AH331: =VLOOKUP(B331,[2]GRADE!$A:$P,16,0) -> SILVER | AI331: =IF(AH331="SILVER",6.5,IF(AH331="GOLD",8,IF(AH331="INDUSTRIAL",6,IF(AH331="GREEN",7,IF(AH331="BRONZE",5.5,0))))) -> 6.5
A332: 7511684 | B332: =VALUE(LEFT(A332,4)) -> 7511 | C332: =VALUE(RIGHT(A332,3)) -> 684 | D332: =VLOOKUP(C332,Sheet1!$A$2:$K$369991,11,0) -> CAR | E332: SERVO GEAR SUPER 80W-90 - 20 X 1 L HDPE | F332: =VLOOKUP(C332,'PACK MASTER'!$A$2:$I$512998,9,0)*1000 -> 20 | G332: =VLOOKUP(C332,'PACK MASTER'!$A$2:$G$512998,7,0) -> 1 | H332: =F332/G332 -> 20 | I332: =VLOOKUP($A332,ZMRP!$C$2:$F$99995,4,0) -> 250 | J332: =I332/G332 -> 250 | K332: =VLOOKUP($A332,ZLAM!$C$2:$F$99999,4,0) -> 88.5 | L332: =I332*K332/100 -> 221.25 | M332: =L332/G332 -> 221.25 | N332: =L332/1.18 -> 187.5 | O332: =N332/G332 -> 187.5 | P332: =IFERROR(ABS(VLOOKUP($A332,ZTRV!$D$2:$G$99407,4,0)),0) -> 0 | Q332: =IFERROR(ABS(VLOOKUP($A332,ZTR1!$D$2:$G$99999,4,0)),0) -> 0 | R332: =IFERROR(ABS(VLOOKUP($A332,ZTR2!$D$2:$G$99939,4,0)),0) -> 0 | S332: =SUM(P332:R332)*G332 -> 0 | T332: =N332-S332 -> 187.5 | U332: =T332*1.18 -> 221.25 | V332: =U332/G332 -> 221.25 | W332: =V332*F332 -> 4425 | X332: =I332-U332 -> 28.75 | Y332: =X332*H332 -> 575 | Z332: =J332-V332 -> 28.75 | AA332: =IFERROR(ABS(VLOOKUP(A332,ZSSD!$D$2:$G$99933,4,0)),AI332) -> 6.5 | AB332: =IFERROR(IF(VLOOKUP(A332,ZSSD!$D:$H,5,0)="L29",AA332*G332,AA332*L332/100),AA332*L332/100) -> 14.38125 | AC332: 2 | AD332: =2*(T332-AB332)/100 -> 3.462375 | AE332: =+AB332/G332 -> 14.38125 | AF332: =+AD332/G332 -> 3.462375 | AG332: =VLOOKUP(A332,ZSSD!D:D,1,0) -> #N/A | AH332: =VLOOKUP(B332,[2]GRADE!$A:$P,16,0) -> SILVER | AI332: =IF(AH332="SILVER",6.5,IF(AH332="GOLD",8,IF(AH332="INDUSTRIAL",6,IF(AH332="GREEN",7,IF(AH332="BRONZE",5.5,0))))) -> 6.5
A333: 7513174 | B333: =VALUE(LEFT(A333,4)) -> 7513 | C333: =VALUE(RIGHT(A333,3)) -> 174 | D333: =VLOOKUP(C333,Sheet1!$A$2:$K$369991,11,0) -> CAR | E333: SERVO SUPER MG 20W-40-40X1/2L | F333: =VLOOKUP(C333,'PACK MASTER'!$A$2:$I$512998,9,0)*1000 -> 20 | G333: =VLOOKUP(C333,'PACK MASTER'!$A$2:$G$512998,7,0) -> 0.5 | H333: =F333/G333 -> 40 | I333: =VLOOKUP($A333,ZMRP!$C$2:$F$99995,4,0) -> 118 | J333: =I333/G333 -> 236 | K333: =VLOOKUP($A333,ZLAM!$C$2:$F$99999,4,0) -> 83.33 | L333: =I333*K333/100 -> 98.3294 | M333: =L333/G333 -> 196.6588 | N333: =L333/1.18 -> 83.33 | O333: =N333/G333 -> 166.66 | P333: =IFERROR(ABS(VLOOKUP($A333,ZTRV!$D$2:$G$99407,4,0)),0) -> 0 | Q333: =IFERROR(ABS(VLOOKUP($A333,ZTR1!$D$2:$G$99999,4,0)),0) -> 0 | R333: =IFERROR(ABS(VLOOKUP($A333,ZTR2!$D$2:$G$99939,4,0)),0) -> 0 | S333: =SUM(P333:R333)*G333 -> 0 | T333: =N333-S333 -> 83.33 | U333: =T333*1.18 -> 98.3294 | V333: =U333/G333 -> 196.6588 | W333: =V333*F333 -> 3933.176 | X333: =I333-U333 -> 19.6706 | Y333: =X333*H333 -> 786.824 | Z333: =J333-V333 -> 39.3412 | AA333: =IFERROR(ABS(VLOOKUP(A333,ZSSD!$D$2:$G$99933,4,0)),AI333) -> 6.5 | AB333: =IFERROR(IF(VLOOKUP(A333,ZSSD!$D:$H,5,0)="L29",AA333*G333,AA333*L333/100),AA333*L333/100) -> 6.391411 | AC333: 2 | AD333: =2*(T333-AB333)/100 -> 1.5387718 | AE333: =+AB333/G333 -> 12.782822 | AF333: =+AD333/G333 -> 3.0775436 | AG333: =VLOOKUP(A333,ZSSD!D:D,1,0) -> #N/A | AH333: =VLOOKUP(B333,[2]GRADE!$A:$P,16,0) -> SILVER | AI333: =IF(AH333="SILVER",6.5,IF(AH333="GOLD",8,IF(AH333="INDUSTRIAL",6,IF(AH333="GREEN",7,IF(AH333="BRONZE",5.5,0))))) -> 6.5
A334: 7513234 | B334: =VALUE(LEFT(A334,4)) -> 7513 | C334: =VALUE(RIGHT(A334,3)) -> 234 | D334: =VLOOKUP(C334,Sheet1!$A$2:$K$369991,11,0) -> CAR | E334: SERVO SUPER MG 20W-40-4x5L - HDPE | F334: =VLOOKUP(C334,'PACK MASTER'!$A$2:$I$512998,9,0)*1000 -> 20 | G334: =VLOOKUP(C334,'PACK MASTER'!$A$2:$G$512998,7,0) -> 5 | H334: =F334/G334 -> 4 | I334: =VLOOKUP($A334,ZMRP!$C$2:$F$99995,4,0) -> 1075 | J334: =I334/G334 -> 215 | K334: =VLOOKUP($A334,ZLAM!$C$2:$F$99999,4,0) -> 86.96 | L334: =I334*K334/100 -> 934.82 | M334: =L334/G334 -> 186.964 | N334: =L334/1.18 -> 792.22034 | O334: =N334/G334 -> 158.44407 | P334: =IFERROR(ABS(VLOOKUP($A334,ZTRV!$D$2:$G$99407,4,0)),0) -> 0 | Q334: =IFERROR(ABS(VLOOKUP($A334,ZTR1!$D$2:$G$99999,4,0)),0) -> 0 | R334: =IFERROR(ABS(VLOOKUP($A334,ZTR2!$D$2:$G$99939,4,0)),0) -> 0 | S334: =SUM(P334:R334)*G334 -> 0 | T334: =N334-S334 -> 792.22034 | U334: =T334*1.18 -> 934.82 | V334: =U334/G334 -> 186.964 | W334: =V334*F334 -> 3739.28 | X334: =I334-U334 -> 140.18 | Y334: =X334*H334 -> 560.72 | Z334: =J334-V334 -> 28.036 | AA334: =IFERROR(ABS(VLOOKUP(A334,ZSSD!$D$2:$G$99933,4,0)),AI334) -> 6.5 | AB334: =IFERROR(IF(VLOOKUP(A334,ZSSD!$D:$H,5,0)="L29",AA334*G334,AA334*L334/100),AA334*L334/100) -> 60.7633 | AC334: 2 | AD334: =2*(T334-AB334)/100 -> 14.629141 | AE334: =+AB334/G334 -> 12.15266 | AF334: =+AD334/G334 -> 2.9258282 | AG334: =VLOOKUP(A334,ZSSD!D:D,1,0) -> #N/A | AH334: =VLOOKUP(B334,[2]GRADE!$A:$P,16,0) -> SILVER | AI334: =IF(AH334="SILVER",6.5,IF(AH334="GOLD",8,IF(AH334="INDUSTRIAL",6,IF(AH334="GREEN",7,IF(AH334="BRONZE",5.5,0))))) -> 6.5
A335: 7515052 | B335: 7515 | C335: 52 | D335: =VLOOKUP(C335,Sheet1!$A$2:$K$369991,11,0) -> BUC | E335: SERVO GEAR SUPER 85W-140-12 L BUC | F335: =VLOOKUP(C335,'PACK MASTER'!$A$2:$I$512998,9,0)*1000 -> 12 | G335: =VLOOKUP(C335,'PACK MASTER'!$A$2:$G$512998,7,0) -> 12 | H335: =F335/G335 -> 1 | I335: =VLOOKUP($A335,ZMRP!$C$2:$F$99995,4,0) -> 4890 | J335: =I335/G335 -> 407.5 | K335: =VLOOKUP($A335,ZLAM!$C$2:$F$99999,4,0) -> 75 | L335: =I335*K335/100 -> 3667.5 | M335: =L335/G335 -> 305.625 | N335: =L335/1.18 -> 3108.0508 | O335: =N335/G335 -> 259.00424 | P335: =IFERROR(ABS(VLOOKUP($A335,ZTRV!$D$2:$G$99407,4,0)),0) -> 33 | Q335: =IFERROR(ABS(VLOOKUP($A335,ZTR1!$D$2:$G$99999,4,0)),0) -> 0 | R335: =IFERROR(ABS(VLOOKUP($A335,ZTR2!$D$2:$G$99939,4,0)),0) -> 0 | S335: =SUM(P335:R335)*G335 -> 396 | T335: =N335-S335 -> 2712.0508 | U335: =T335*1.18 -> 3200.22 | V335: =U335/G335 -> 266.685 | W335: =V335*F335 -> 3200.22 | X335: =I335-U335 -> 1689.78 | Y335: =X335*H335 -> 1689.78 | Z335: =J335-V335 -> 140.815 | AA335: =IFERROR(ABS(VLOOKUP(A335,ZSSD!$D$2:$G$99933,4,0)),AI335) -> 6.5 | AB335: =IFERROR(IF(VLOOKUP(A335,ZSSD!$D:$H,5,0)="L29",AA335*G335,AA335*L335/100),AA335*L335/100) -> 238.3875 | AC335: 2 | AD335: =2*(T335-AB335)/100 -> 49.473267 | AE335: =+AB335/G335 -> 19.865625 | AF335: =+AD335/G335 -> 4.1227722 | AG335: =VLOOKUP(A335,ZSSD!D:D,1,0) -> #N/A | AH335: =VLOOKUP(B335,[2]GRADE!$A:$P,16,0) -> SILVER | AI335: =IF(AH335="SILVER",6.5,IF(AH335="GOLD",8,IF(AH335="INDUSTRIAL",6,IF(AH335="GREEN",7,IF(AH335="BRONZE",5.5,0))))) -> 6.5
A336: 7515184 | B336: =VALUE(LEFT(A336,4)) -> 7515 | C336: =VALUE(RIGHT(A336,3)) -> 184 | D336: =VLOOKUP(C336,Sheet1!$A$2:$K$369991,11,0) -> CAR | E336: SERVO GEAR SUPER 85W-140 - 20 X 1 L HDPE | F336: =VLOOKUP(C336,'PACK MASTER'!$A$2:$I$512998,9,0)*1000 -> 20 | G336: =VLOOKUP(C336,'PACK MASTER'!$A$2:$G$512998,7,0) -> 1 | H336: =F336/G336 -> 20 | I336: =VLOOKUP($A336,ZMRP!$C$2:$F$99995,4,0) -> 445 | J336: =I336/G336 -> 445 | K336: =VLOOKUP($A336,ZLAM!$C$2:$F$99999,4,0) -> 74.59 | L336: =I336*K336/100 -> 331.9255 | M336: =L336/G336 -> 331.9255 | N336: =L336/1.18 -> 281.2928 | O336: =N336/G336 -> 281.2928 | P336: =IFERROR(ABS(VLOOKUP($A336,ZTRV!$D$2:$G$99407,4,0)),0) -> 28 | Q336: =IFERROR(ABS(VLOOKUP($A336,ZTR1!$D$2:$G$99999,4,0)),0) -> 0 | R336: =IFERROR(ABS(VLOOKUP($A336,ZTR2!$D$2:$G$99939,4,0)),0) -> 0 | S336: =SUM(P336:R336)*G336 -> 28 | T336: =N336-S336 -> 253.2928 | U336: =T336*1.18 -> 298.8855 | V336: =U336/G336 -> 298.8855 | W336: =V336*F336 -> 5977.71 | X336: =I336-U336 -> 146.1145 | Y336: =X336*H336 -> 2922.29 | Z336: =J336-V336 -> 146.1145 | AA336: =IFERROR(ABS(VLOOKUP(A336,ZSSD!$D$2:$G$99933,4,0)),AI336) -> 6.5 | AB336: =IFERROR(IF(VLOOKUP(A336,ZSSD!$D:$H,5,0)="L29",AA336*G336,AA336*L336/100),AA336*L336/100) -> 21.575158 | AC336: 2 | AD336: =2*(T336-AB336)/100 -> 4.6343528 | AE336: =+AB336/G336 -> 21.575158 | AF336: =+AD336/G336 -> 4.6343528 | AG336: =VLOOKUP(A336,ZSSD!D:D,1,0) -> #N/A | AH336: =VLOOKUP(B336,[2]GRADE!$A:$P,16,0) -> SILVER | AI336: =IF(AH336="SILVER",6.5,IF(AH336="GOLD",8,IF(AH336="INDUSTRIAL",6,IF(AH336="GREEN",7,IF(AH336="BRONZE",5.5,0))))) -> 6.5
A337: 7515234 | B337: =VALUE(LEFT(A337,4)) -> 7515 | C337: =VALUE(RIGHT(A337,3)) -> 234 | D337: =VLOOKUP(C337,Sheet1!$A$2:$K$369991,11,0) -> CAR | E337: SERVO GEAR SUPER 85W-140 - 4 X 5 L HDPE | F337: =VLOOKUP(C337,'PACK MASTER'!$A$2:$I$512998,9,0)*1000 -> 20 | G337: =VLOOKUP(C337,'PACK MASTER'!$A$2:$G$512998,7,0) -> 5 | H337: =F337/G337 -> 4 | I337: =VLOOKUP($A337,ZMRP!$C$2:$F$99995,4,0) -> 2025 | J337: =I337/G337 -> 405 | K337: =VLOOKUP($A337,ZLAM!$C$2:$F$99999,4,0) -> 79.2 | L337: =I337*K337/100 -> 1603.8 | M337: =L337/G337 -> 320.76 | N337: =L337/1.18 -> 1359.1525 | O337: =N337/G337 -> 271.83051 | P337: =IFERROR(ABS(VLOOKUP($A337,ZTRV!$D$2:$G$99407,4,0)),0) -> 38 | Q337: =IFERROR(ABS(VLOOKUP($A337,ZTR1!$D$2:$G$99999,4,0)),0) -> 0 | R337: =IFERROR(ABS(VLOOKUP($A337,ZTR2!$D$2:$G$99939,4,0)),0) -> 0 | S337: =SUM(P337:R337)*G337 -> 190 | T337: =N337-S337 -> 1169.1525 | U337: =T337*1.18 -> 1379.6 | V337: =U337/G337 -> 275.92 | W337: =V337*F337 -> 5518.4 | X337: =I337-U337 -> 645.4 | Y337: =X337*H337 -> 2581.6 | Z337: =J337-V337 -> 129.08 | AA337: =IFERROR(ABS(VLOOKUP(A337,ZSSD!$D$2:$G$99933,4,0)),AI337) -> 6.5 | AB337: =IFERROR(IF(VLOOKUP(A337,ZSSD!$D:$H,5,0)="L29",AA337*G337,AA337*L337/100),AA337*L337/100) -> 104.247 | AC337: 2 | AD337: =2*(T337-AB337)/100 -> 21.298111 | AE337: =+AB337/G337 -> 20.8494 | AF337: =+AD337/G337 -> 4.2596222 | AG337: =VLOOKUP(A337,ZSSD!D:D,1,0) -> #N/A | AH337: =VLOOKUP(B337,[2]GRADE!$A:$P,16,0) -> SILVER | AI337: =IF(AH337="SILVER",6.5,IF(AH337="GOLD",8,IF(AH337="INDUSTRIAL",6,IF(AH337="GREEN",7,IF(AH337="BRONZE",5.5,0))))) -> 6.5
A338: 7515240 | B338: =VALUE(LEFT(A338,4)) -> 7515 | C338: =VALUE(RIGHT(A338,3)) -> 240 | D338: =VLOOKUP(C338,Sheet1!$A$2:$K$369991,11,0) -> CAR | E338: SERVO GEAR SUPER 85W-140-4 X 5 L PROMO | F338: =VLOOKUP(C338,'PACK MASTER'!$A$2:$I$512998,9,0)*1000 -> 20 | G338: =VLOOKUP(C338,'PACK MASTER'!$A$2:$G$512998,7,0) -> 5 | H338: =F338/G338 -> 4 | I338: =VLOOKUP($A338,ZMRP!$C$2:$F$99995,4,0) -> 2025 | J338: =I338/G338 -> 405 | K338: =VLOOKUP($A338,ZLAM!$C$2:$F$99999,4,0) -> 79.2 | L338: =I338*K338/100 -> 1603.8 | M338: =L338/G338 -> 320.76 | N338: =L338/1.18 -> 1359.1525 | O338: =N338/G338 -> 271.83051 | P338: =IFERROR(ABS(VLOOKUP($A338,ZTRV!$D$2:$G$99407,4,0)),0) -> 33 | Q338: =IFERROR(ABS(VLOOKUP($A338,ZTR1!$D$2:$G$99999,4,0)),0) -> 0 | R338: =IFERROR(ABS(VLOOKUP($A338,ZTR2!$D$2:$G$99939,4,0)),0) -> 0 | S338: =SUM(P338:R338)*G338 -> 165 | T338: =N338-S338 -> 1194.1525 | U338: =T338*1.18 -> 1409.1 | V338: =U338/G338 -> 281.82 | W338: =V338*F338 -> 5636.4 | X338: =I338-U338 -> 615.9 | Y338: =X338*H338 -> 2463.6 | Z338: =J338-V338 -> 123.18 | AA338: =IFERROR(ABS(VLOOKUP(A338,ZSSD!$D$2:$G$99933,4,0)),AI338) -> 6.5 | AB338: =IFERROR(IF(VLOOKUP(A338,ZSSD!$D:$H,5,0)="L29",AA338*G338,AA338*L338/100),AA338*L338/100) -> 104.247 | AC338: 2 | AD338: =2*(T338-AB338)/100 -> 21.798111 | AE338: =+AB338/G338 -> 20.8494 | AF338: =+AD338/G338 -> 4.3596222 | AG338: =VLOOKUP(A338,ZSSD!D:D,1,0) -> #N/A | AH338: =VLOOKUP(B338,[2]GRADE!$A:$P,16,0) -> SILVER | AI338: =IF(AH338="SILVER",6.5,IF(AH338="GOLD",8,IF(AH338="INDUSTRIAL",6,IF(AH338="GREEN",7,IF(AH338="BRONZE",5.5,0))))) -> 6.5
A339: 7515242 | B339: =VALUE(LEFT(A339,4)) -> 7515 | C339: =VALUE(RIGHT(A339,3)) -> 242 | D339: =VLOOKUP(C339,Sheet1!$A$2:$K$369991,11,0) -> BUC | E339: SERVO GEAR SUPER 85W-140-10 L | F339: =VLOOKUP(C339,'PACK MASTER'!$A$2:$I$512998,9,0)*1000 -> 10 | G339: =VLOOKUP(C339,'PACK MASTER'!$A$2:$G$512998,7,0) -> 10 | H339: =F339/G339 -> 1 | I339: =VLOOKUP($A339,ZMRP!$C$2:$F$99995,4,0) -> 4050 | J339: =I339/G339 -> 405 | K339: =VLOOKUP($A339,ZLAM!$C$2:$F$99999,4,0) -> 78.79 | L339: =I339*K339/100 -> 3190.995 | M339: =L339/G339 -> 319.0995 | N339: =L339/1.18 -> 2704.2331 | O339: =N339/G339 -> 270.42331 | P339: =IFERROR(ABS(VLOOKUP($A339,ZTRV!$D$2:$G$99407,4,0)),0) -> 33 | Q339: =IFERROR(ABS(VLOOKUP($A339,ZTR1!$D$2:$G$99999,4,0)),0) -> 0 | R339: =IFERROR(ABS(VLOOKUP($A339,ZTR2!$D$2:$G$99939,4,0)),0) -> 0 | S339: =SUM(P339:R339)*G339 -> 330 | T339: =N339-S339 -> 2374.2331 | U339: =T339*1.18 -> 2801.595 | V339: =U339/G339 -> 280.1595 | W339: =V339*F339 -> 2801.595 | X339: =I339-U339 -> 1248.405 | Y339: =X339*H339 -> 1248.405 | Z339: =J339-V339 -> 124.8405 | AA339: =IFERROR(ABS(VLOOKUP(A339,ZSSD!$D$2:$G$99933,4,0)),AI339) -> 6.5 | AB339: =IFERROR(IF(VLOOKUP(A339,ZSSD!$D:$H,5,0)="L29",AA339*G339,AA339*L339/100),AA339*L339/100) -> 207.41467 | AC339: 2 | AD339: =2*(T339-AB339)/100 -> 43.336368 | AE339: =+AB339/G339 -> 20.741467 | AF339: =+AD339/G339 -> 4.3336368 | AG339: =VLOOKUP(A339,ZSSD!D:D,1,0) -> #N/A | AH339: =VLOOKUP(B339,[2]GRADE!$A:$P,16,0) -> SILVER | AI339: =IF(AH339="SILVER",6.5,IF(AH339="GOLD",8,IF(AH339="INDUSTRIAL",6,IF(AH339="GREEN",7,IF(AH339="BRONZE",5.5,0))))) -> 6.5
A340: 7515251 | B340: =VALUE(LEFT(A340,4)) -> 7515 | C340: =VALUE(RIGHT(A340,3)) -> 251 | D340: =VLOOKUP(C340,Sheet1!$A$2:$K$369991,11,0) -> BUC | E340: SERVO GEAR SUPER 85W-140-7.5 L | F340: =VLOOKUP(C340,'PACK MASTER'!$A$2:$I$512998,9,0)*1000 -> 7.5 | G340: =VLOOKUP(C340,'PACK MASTER'!$A$2:$G$512998,7,0) -> 7.5 | H340: =F340/G340 -> 1 | I340: =VLOOKUP($A340,ZMRP!$C$2:$F$99995,4,0) -> 3033 | J340: =I340/G340 -> 404.4 | K340: =VLOOKUP($A340,ZLAM!$C$2:$F$99999,4,0) -> 79.11 | L340: =I340*K340/100 -> 2399.4063 | M340: =L340/G340 -> 319.92084 | N340: =L340/1.18 -> 2033.3952 | O340: =N340/G340 -> 271.11936 | P340: =IFERROR(ABS(VLOOKUP($A340,ZTRV!$D$2:$G$99407,4,0)),0) -> 33 | Q340: =IFERROR(ABS(VLOOKUP($A340,ZTR1!$D$2:$G$99999,4,0)),0) -> 0 | R340: =IFERROR(ABS(VLOOKUP($A340,ZTR2!$D$2:$G$99939,4,0)),0) -> 0 | S340: =SUM(P340:R340)*G340 -> 247.5 | T340: =N340-S340 -> 1785.8952 | U340: =T340*1.18 -> 2107.3563 | V340: =U340/G340 -> 280.98084 | W340: =V340*F340 -> 2107.3563 | X340: =I340-U340 -> 925.6437 | Y340: =X340*H340 -> 925.6437 | Z340: =J340-V340 -> 123.41916 | AA340: =IFERROR(ABS(VLOOKUP(A340,ZSSD!$D$2:$G$99933,4,0)),AI340) -> 6.5 | AB340: =IFERROR(IF(VLOOKUP(A340,ZSSD!$D:$H,5,0)="L29",AA340*G340,AA340*L340/100),AA340*L340/100) -> 155.96141 | AC340: 2 | AD340: =2*(T340-AB340)/100 -> 32.598675 | AE340: =+AB340/G340 -> 20.794855 | AF340: =+AD340/G340 -> 4.34649 | AG340: =VLOOKUP(A340,ZSSD!D:D,1,0) -> #N/A | AH340: =VLOOKUP(B340,[2]GRADE!$A:$P,16,0) -> SILVER | AI340: =IF(AH340="SILVER",6.5,IF(AH340="GOLD",8,IF(AH340="INDUSTRIAL",6,IF(AH340="GREEN",7,IF(AH340="BRONZE",5.5,0))))) -> 6.5
A341: 7515265 | B341: =VALUE(LEFT(A341,4)) -> 7515 | C341: =VALUE(RIGHT(A341,3)) -> 265 | D341: =VLOOKUP(C341,Sheet1!$A$2:$K$369991,11,0) -> BUC | E341: SERVO GEAR SUPER 85W-140-20 L BUC | F341: =VLOOKUP(C341,'PACK MASTER'!$A$2:$I$512998,9,0)*1000 -> 20 | G341: =VLOOKUP(C341,'PACK MASTER'!$A$2:$G$512998,7,0) -> 20 | H341: =F341/G341 -> 1 | I341: =VLOOKUP($A341,ZMRP!$C$2:$F$99995,4,0) -> 7950 | J341: =I341/G341 -> 397.5 | K341: =VLOOKUP($A341,ZLAM!$C$2:$F$99999,4,0) -> 79.59 | L341: =I341*K341/100 -> 6327.405 | M341: =L341/G341 -> 316.37025 | N341: =L341/1.18 -> 5362.2076 | O341: =N341/G341 -> 268.11038 | P341: =IFERROR(ABS(VLOOKUP($A341,ZTRV!$D$2:$G$99407,4,0)),0) -> 48 | Q341: =IFERROR(ABS(VLOOKUP($A341,ZTR1!$D$2:$G$99999,4,0)),0) -> 0 | R341: =IFERROR(ABS(VLOOKUP($A341,ZTR2!$D$2:$G$99939,4,0)),0) -> 0 | S341: =SUM(P341:R341)*G341 -> 960 | T341: =N341-S341 -> 4402.2076 | U341: =T341*1.18 -> 5194.605 | V341: =U341/G341 -> 259.73025 | W341: =V341*F341 -> 5194.605 | X341: =I341-U341 -> 2755.395 | Y341: =X341*H341 -> 2755.395 | Z341: =J341-V341 -> 137.76975 | AA341: =IFERROR(ABS(VLOOKUP(A341,ZSSD!$D$2:$G$99933,4,0)),AI341) -> 6.5 | AB341: =IFERROR(IF(VLOOKUP(A341,ZSSD!$D:$H,5,0)="L29",AA341*G341,AA341*L341/100),AA341*L341/100) -> 411.28132 | AC341: 2 | AD341: =2*(T341-AB341)/100 -> 79.818526 | AE341: =+AB341/G341 -> 20.564066 | AF341: =+AD341/G341 -> 3.9909263 | AG341: =VLOOKUP(A341,ZSSD!D:D,1,0) -> #N/A | AH341: =VLOOKUP(B341,[2]GRADE!$A:$P,16,0) -> SILVER | AI341: =IF(AH341="SILVER",6.5,IF(AH341="GOLD",8,IF(AH341="INDUSTRIAL",6,IF(AH341="GREEN",7,IF(AH341="BRONZE",5.5,0))))) -> 6.5
A342: 7515269 | B342: =VALUE(LEFT(A342,4)) -> 7515 | C342: =VALUE(RIGHT(A342,3)) -> 269 | D342: =VLOOKUP(C342,Sheet1!$A$2:$K$369991,11,0) -> BUC | E342: SERVO GEAR SUPER 85W-140-20 L PROMO | F342: =VLOOKUP(C342,'PACK MASTER'!$A$2:$I$512998,9,0)*1000 -> 20 | G342: =VLOOKUP(C342,'PACK MASTER'!$A$2:$G$512998,7,0) -> 20 | H342: =F342/G342 -> 1 | I342: =VLOOKUP($A342,ZMRP!$C$2:$F$99995,4,0) -> 7950 | J342: =I342/G342 -> 397.5 | K342: =VLOOKUP($A342,ZLAM!$C$2:$F$99999,4,0) -> 79.59 | L342: =I342*K342/100 -> 6327.405 | M342: =L342/G342 -> 316.37025 | N342: =L342/1.18 -> 5362.2076 | O342: =N342/G342 -> 268.11038 | P342: =IFERROR(ABS(VLOOKUP($A342,ZTRV!$D$2:$G$99407,4,0)),0) -> 48 | Q342: =IFERROR(ABS(VLOOKUP($A342,ZTR1!$D$2:$G$99999,4,0)),0) -> 0 | R342: =IFERROR(ABS(VLOOKUP($A342,ZTR2!$D$2:$G$99939,4,0)),0) -> 0 | S342: =SUM(P342:R342)*G342 -> 960 | T342: =N342-S342 -> 4402.2076 | U342: =T342*1.18 -> 5194.605 | V342: =U342/G342 -> 259.73025 | W342: =V342*F342 -> 5194.605 | X342: =I342-U342 -> 2755.395 | Y342: =X342*H342 -> 2755.395 | Z342: =J342-V342 -> 137.76975 | AA342: =IFERROR(ABS(VLOOKUP(A342,ZSSD!$D$2:$G$99933,4,0)),AI342) -> 6.5 | AB342: =IFERROR(IF(VLOOKUP(A342,ZSSD!$D:$H,5,0)="L29",AA342*G342,AA342*L342/100),AA342*L342/100) -> 411.28132 | AC342: 2 | AD342: =2*(T342-AB342)/100 -> 79.818526 | AE342: =+AB342/G342 -> 20.564066 | AF342: =+AD342/G342 -> 3.9909263 | AG342: =VLOOKUP(A342,ZSSD!D:D,1,0) -> #N/A | AH342: =VLOOKUP(B342,[2]GRADE!$A:$P,16,0) -> SILVER | AI342: =IF(AH342="SILVER",6.5,IF(AH342="GOLD",8,IF(AH342="INDUSTRIAL",6,IF(AH342="GREEN",7,IF(AH342="BRONZE",5.5,0))))) -> 6.5
A343: 7515765 | B343: =VALUE(LEFT(A343,4)) -> 7515 | C343: =VALUE(RIGHT(A343,3)) -> 765 | D343: =VLOOKUP(C343,Sheet1!$A$2:$K$369991,11,0) -> BUC | E343: SERVO GEAR SUPER 85W-140 - 20 L BUC - OL | F343: =VLOOKUP(C343,'PACK MASTER'!$A$2:$I$512998,9,0)*1000 -> 20 | G343: =VLOOKUP(C343,'PACK MASTER'!$A$2:$G$512998,7,0) -> 20 | H343: =F343/G343 -> 1 | I343: =VLOOKUP($A343,ZMRP!$C$2:$F$99995,4,0) -> 5315 | J343: =I343/G343 -> 265.75 | K343: =VLOOKUP($A343,ZLAM!$C$2:$F$99999,4,0) -> 87.72 | L343: =I343*K343/100 -> 4662.318 | M343: =L343/G343 -> 233.1159 | N343: =L343/1.18 -> 3951.1169 | O343: =N343/G343 -> 197.55585 | P343: =IFERROR(ABS(VLOOKUP($A343,ZTRV!$D$2:$G$99407,4,0)),0) -> 0 | Q343: =IFERROR(ABS(VLOOKUP($A343,ZTR1!$D$2:$G$99999,4,0)),0) -> 0 | R343: =IFERROR(ABS(VLOOKUP($A343,ZTR2!$D$2:$G$99939,4,0)),0) -> 0 | S343: =SUM(P343:R343)*G343 -> 0 | T343: =N343-S343 -> 3951.1169 | U343: =T343*1.18 -> 4662.318 | V343: =U343/G343 -> 233.1159 | W343: =V343*F343 -> 4662.318 | X343: =I343-U343 -> 652.682 | Y343: =X343*H343 -> 652.682 | Z343: =J343-V343 -> 32.6341 | AA343: =IFERROR(ABS(VLOOKUP(A343,ZSSD!$D$2:$G$99933,4,0)),AI343) -> 6.5 | AB343: =IFERROR(IF(VLOOKUP(A343,ZSSD!$D:$H,5,0)="L29",AA343*G343,AA343*L343/100),AA343*L343/100) -> 303.05067 | AC343: 2 | AD343: =2*(T343-AB343)/100 -> 72.961326 | AE343: =+AB343/G343 -> 15.152534 | AF343: =+AD343/G343 -> 3.6480663 | AG343: =VLOOKUP(A343,ZSSD!D:D,1,0) -> #N/A | AH343: =VLOOKUP(B343,[2]GRADE!$A:$P,16,0) -> SILVER | AI343: =IF(AH343="SILVER",6.5,IF(AH343="GOLD",8,IF(AH343="INDUSTRIAL",6,IF(AH343="GREEN",7,IF(AH343="BRONZE",5.5,0))))) -> 6.5
A344: 7530228 | B344: =VALUE(LEFT(A344,4)) -> 7530 | C344: =VALUE(RIGHT(A344,3)) -> 228 | D344: =VLOOKUP(C344,Sheet1!$A$2:$K$369991,11,0) -> CAR | E344: SERVO CHHAKADA ENG OIL 20W-40-20X1.2L LI | F344: =VLOOKUP(C344,'PACK MASTER'!$A$2:$I$512998,9,0)*1000 -> 24 | G344: =VLOOKUP(C344,'PACK MASTER'!$A$2:$G$512998,7,0) -> 1.2 | H344: =F344/G344 -> 20 | I344: =VLOOKUP($A344,ZMRP!$C$2:$F$99995,4,0) -> 378 | J344: =I344/G344 -> 315 | K344: =VLOOKUP($A344,ZLAM!$C$2:$F$99999,4,0) -> 81.35 | L344: =I344*K344/100 -> 307.503 | M344: =L344/G344 -> 256.2525 | N344: =L344/1.18 -> 260.59576 | O344: =N344/G344 -> 217.16314 | P344: =IFERROR(ABS(VLOOKUP($A344,ZTRV!$D$2:$G$99407,4,0)),0) -> 0 | Q344: =IFERROR(ABS(VLOOKUP($A344,ZTR1!$D$2:$G$99999,4,0)),0) -> 0 | R344: =IFERROR(ABS(VLOOKUP($A344,ZTR2!$D$2:$G$99939,4,0)),0) -> 0 | S344: =SUM(P344:R344)*G344 -> 0 | T344: =N344-S344 -> 260.59576 | U344: =T344*1.18 -> 307.503 | V344: =U344/G344 -> 256.2525 | W344: =V344*F344 -> 6150.06 | X344: =I344-U344 -> 70.497 | Y344: =X344*H344 -> 1409.94 | Z344: =J344-V344 -> 58.7475 | AA344: =IFERROR(ABS(VLOOKUP(A344,ZSSD!$D$2:$G$99933,4,0)),AI344) -> 6.5 | AB344: =IFERROR(IF(VLOOKUP(A344,ZSSD!$D:$H,5,0)="L29",AA344*G344,AA344*L344/100),AA344*L344/100) -> 19.987695 | AC344: 2 | AD344: =2*(T344-AB344)/100 -> 4.8121614 | AE344: =+AB344/G344 -> 16.656412 | AF344: =+AD344/G344 -> 4.0101345 | AG344: =VLOOKUP(A344,ZSSD!D:D,1,0) -> #N/A | AH344: =VLOOKUP(B344,[2]GRADE!$A:$P,16,0) -> SILVER | AI344: =IF(AH344="SILVER",6.5,IF(AH344="GOLD",8,IF(AH344="INDUSTRIAL",6,IF(AH344="GREEN",7,IF(AH344="BRONZE",5.5,0))))) -> 6.5
A345: 7553175 | B345: =VALUE(LEFT(A345,4)) -> 7553 | C345: =VALUE(RIGHT(A345,3)) -> 175 | D345: =VLOOKUP(C345,Sheet1!$A$2:$K$369991,11,0) -> CAR | E345: SERVO TILLER SUPER 20W-40-20 X 1/2 L | F345: =VLOOKUP(C345,'PACK MASTER'!$A$2:$I$512998,9,0)*1000 -> 10 | G345: =VLOOKUP(C345,'PACK MASTER'!$A$2:$G$512998,7,0) -> 0.5 | H345: =F345/G345 -> 20 | I345: =VLOOKUP($A345,ZMRP!$C$2:$F$99995,4,0) -> 188 | J345: =I345/G345 -> 376 | K345: =VLOOKUP($A345,ZLAM!$C$2:$F$99999,4,0) -> 68.61 | L345: =I345*K345/100 -> 128.9868 | M345: =L345/G345 -> 257.9736 | N345: =L345/1.18 -> 109.31085 | O345: =N345/G345 -> 218.62169 | P345: =IFERROR(ABS(VLOOKUP($A345,ZTRV!$D$2:$G$99407,4,0)),0) -> 0 | Q345: =IFERROR(ABS(VLOOKUP($A345,ZTR1!$D$2:$G$99999,4,0)),0) -> 0 | R345: =IFERROR(ABS(VLOOKUP($A345,ZTR2!$D$2:$G$99939,4,0)),0) -> 0 | S345: =SUM(P345:R345)*G345 -> 0 | T345: =N345-S345 -> 109.31085 | U345: =T345*1.18 -> 128.9868 | V345: =U345/G345 -> 257.9736 | W345: =V345*F345 -> 2579.736 | X345: =I345-U345 -> 59.0132 | Y345: =X345*H345 -> 1180.264 | Z345: =J345-V345 -> 118.0264 | AA345: =IFERROR(ABS(VLOOKUP(A345,ZSSD!$D$2:$G$99933,4,0)),AI345) -> 6.5 | AB345: =IFERROR(IF(VLOOKUP(A345,ZSSD!$D:$H,5,0)="L29",AA345*G345,AA345*L345/100),AA345*L345/100) -> 8.384142 | AC345: 2 | AD345: =2*(T345-AB345)/100 -> 2.0185341 | AE345: =+AB345/G345 -> 16.768284 | AF345: =+AD345/G345 -> 4.0370682 | AG345: =VLOOKUP(A345,ZSSD!D:D,1,0) -> #N/A | AH345: =VLOOKUP(B345,[2]GRADE!$A:$P,16,0) -> SILVER | AI345: =IF(AH345="SILVER",6.5,IF(AH345="GOLD",8,IF(AH345="INDUSTRIAL",6,IF(AH345="GREEN",7,IF(AH345="BRONZE",5.5,0))))) -> 6.5
A346: 7553184 | B346: =VALUE(LEFT(A346,4)) -> 7553 | C346: =VALUE(RIGHT(A346,3)) -> 184 | D346: =VLOOKUP(C346,Sheet1!$A$2:$K$369991,11,0) -> CAR | E346: SERVO TILLER SUPER 20W-40-20 X 1 L | F346: =VLOOKUP(C346,'PACK MASTER'!$A$2:$I$512998,9,0)*1000 -> 20 | G346: =VLOOKUP(C346,'PACK MASTER'!$A$2:$G$512998,7,0) -> 1 | H346: =F346/G346 -> 20 | I346: =VLOOKUP($A346,ZMRP!$C$2:$F$99995,4,0) -> 355 | J346: =I346/G346 -> 355 | K346: =VLOOKUP($A346,ZLAM!$C$2:$F$99999,4,0) -> 70.71 | L346: =I346*K346/100 -> 251.0205 | M346: =L346/G346 -> 251.0205 | N346: =L346/1.18 -> 212.72924 | O346: =N346/G346 -> 212.72924 | P346: =IFERROR(ABS(VLOOKUP($A346,ZTRV!$D$2:$G$99407,4,0)),0) -> 0 | Q346: =IFERROR(ABS(VLOOKUP($A346,ZTR1!$D$2:$G$99999,4,0)),0) -> 0 | R346: =IFERROR(ABS(VLOOKUP($A346,ZTR2!$D$2:$G$99939,4,0)),0) -> 0 | S346: =SUM(P346:R346)*G346 -> 0 | T346: =N346-S346 -> 212.72924 | U346: =T346*1.18 -> 251.0205 | V346: =U346/G346 -> 251.0205 | W346: =V346*F346 -> 5020.41 | X346: =I346-U346 -> 103.9795 | Y346: =X346*H346 -> 2079.59 | Z346: =J346-V346 -> 103.9795 | AA346: =IFERROR(ABS(VLOOKUP(A346,ZSSD!$D$2:$G$99933,4,0)),AI346) -> 6.5 | AB346: =IFERROR(IF(VLOOKUP(A346,ZSSD!$D:$H,5,0)="L29",AA346*G346,AA346*L346/100),AA346*L346/100) -> 16.316333 | AC346: 2 | AD346: =2*(T346-AB346)/100 -> 3.9282581 | AE346: =+AB346/G346 -> 16.316333 | AF346: =+AD346/G346 -> 3.9282581 | AG346: =VLOOKUP(A346,ZSSD!D:D,1,0) -> #N/A | AH346: =VLOOKUP(B346,[2]GRADE!$A:$P,16,0) -> SILVER | AI346: =IF(AH346="SILVER",6.5,IF(AH346="GOLD",8,IF(AH346="INDUSTRIAL",6,IF(AH346="GREEN",7,IF(AH346="BRONZE",5.5,0))))) -> 6.5
A347: 7553203 | B347: =VALUE(LEFT(A347,4)) -> 7553 | C347: =VALUE(RIGHT(A347,3)) -> 203 | D347: =VLOOKUP(C347,Sheet1!$A$2:$K$369991,11,0) -> CAR | E347: SERVO TILLER SUPER 20W-40-4 X 3 L | F347: =VLOOKUP(C347,'PACK MASTER'!$A$2:$I$512998,9,0)*1000 -> 12 | G347: =VLOOKUP(C347,'PACK MASTER'!$A$2:$G$512998,7,0) -> 3 | H347: =F347/G347 -> 4 | I347: =VLOOKUP($A347,ZMRP!$C$2:$F$99995,4,0) -> 1025 | J347: =I347/G347 -> 341.66667 | K347: =VLOOKUP($A347,ZLAM!$C$2:$F$99999,4,0) -> 72.12 | L347: =I347*K347/100 -> 739.23 | M347: =L347/G347 -> 246.41 | N347: =L347/1.18 -> 626.4661 | O347: =N347/G347 -> 208.82203 | P347: =IFERROR(ABS(VLOOKUP($A347,ZTRV!$D$2:$G$99407,4,0)),0) -> 28 | Q347: =IFERROR(ABS(VLOOKUP($A347,ZTR1!$D$2:$G$99999,4,0)),0) -> 0 | R347: =IFERROR(ABS(VLOOKUP($A347,ZTR2!$D$2:$G$99939,4,0)),0) -> 0 | S347: =SUM(P347:R347)*G347 -> 84 | T347: =N347-S347 -> 542.4661 | U347: =T347*1.18 -> 640.11 | V347: =U347/G347 -> 213.37 | W347: =V347*F347 -> 2560.44 | X347: =I347-U347 -> 384.89 | Y347: =X347*H347 -> 1539.56 | Z347: =J347-V347 -> 128.29667 | AA347: =IFERROR(ABS(VLOOKUP(A347,ZSSD!$D$2:$G$99933,4,0)),AI347) -> 6.5 | AB347: =IFERROR(IF(VLOOKUP(A347,ZSSD!$D:$H,5,0)="L29",AA347*G347,AA347*L347/100),AA347*L347/100) -> 48.04995 | AC347: 2 | AD347: =2*(T347-AB347)/100 -> 9.888323 | AE347: =+AB347/G347 -> 16.01665 | AF347: =+AD347/G347 -> 3.2961077 | AG347: =VLOOKUP(A347,ZSSD!D:D,1,0) -> #N/A | AH347: =VLOOKUP(B347,[2]GRADE!$A:$P,16,0) -> SILVER | AI347: =IF(AH347="SILVER",6.5,IF(AH347="GOLD",8,IF(AH347="INDUSTRIAL",6,IF(AH347="GREEN",7,IF(AH347="BRONZE",5.5,0))))) -> 6.5
... A352: 7554252 | B352: =VALUE(LEFT(A352,4)) -> 7554 | C352: =VALUE(RIGHT(A352,3)) -> 252 | D352: =VLOOKUP(C352,Sheet1!$A$2:$K$369991,11,0) -> BUC | E352: SERVO TRCTR OIL PLS 15W40-8.5 L BUC | F352: =VLOOKUP(C352,'PACK MASTER'!$A$2:$I$512998,9,0)*1000 -> 8.5 | G352: =VLOOKUP(C352,'PACK MASTER'!$A$2:$G$512998,7,0) -> 8.5 | H352: =F352/G352 -> 1 | I352: =VLOOKUP($A352,ZMRP!$C$2:$F$99995,4,0) -> 2800 | J352: =I352/G352 -> 329.41176 | K352: =VLOOKUP($A352,ZLAM!$C$2:$F$99999,4,0) -> 82.27 | L352: =I352*K352/100 -> 2303.56 | M352: =L352/G352 -> 271.00706 | N352: =L352/1.18 -> 1952.1695 | O352: =N352/G352 -> 229.667 | P352: =IFERROR(ABS(VLOOKUP($A352,ZTRV!$D$2:$G$99407,4,0)),0) -> 0 | Q352: =IFERROR(ABS(VLOOKUP($A352,ZTR1!$D$2:$G$99999,4,0)),0) -> 0 | R352: =IFERROR(ABS(VLOOKUP($A352,ZTR2!$D$2:$G$99939,4,0)),0) -> 0 | S352: =SUM(P352:R352)*G352 -> 0 | T352: =N352-S352 -> 1952.1695 | U352: =T352*1.18 -> 2303.56 | V352: =U352/G352 -> 271.00706 | W352: =V352*F352 -> 2303.56 | X352: =I352-U352 -> 496.44 | Y352: =X352*H352 -> 496.44 | Z352: =J352-V352 -> 58.404706 | AA352: =IFERROR(ABS(VLOOKUP(A352,ZSSD!$D$2:$G$99933,4,0)),AI352) -> 6.5 | AB352: =IFERROR(IF(VLOOKUP(A352,ZSSD!$D:$H,5,0)="L29",AA352*G352,AA352*L352/100),AA352*L352/100) -> 149.7314 | AC352: 2 | AD352: =2*(T352-AB352)/100 -> 36.048762 | AE352: =+AB352/G352 -> 17.615459 | AF352: =+AD352/G352 -> 4.2410308 | AG352: =VLOOKUP(A352,ZSSD!D:D,1,0) -> #N/A | AH352: =VLOOKUP(B352,[2]GRADE!$A:$P,16,0) -> SILVER | AI352: =IF(AH352="SILVER",6.5,IF(AH352="GOLD",8,IF(AH352="INDUSTRIAL",6,IF(AH352="GREEN",7,IF(AH352="BRONZE",5.5,0))))) -> 6.5
A353: 7556051 | B353: 7556 | C353: 51 | D353: =VLOOKUP(C353,Sheet1!$A$2:$K$369991,11,0) -> #N/A | E353: SERVO PRIDE TC 15W40-6 L BUC | F353: =VLOOKUP(C353,'PACK MASTER'!$A$2:$I$512998,9,0)*1000 -> 6 | G353: =VLOOKUP(C353,'PACK MASTER'!$A$2:$G$512998,7,0) -> 6 | H353: =F353/G353 -> 1 | I353: =VLOOKUP($A353,ZMRP!$C$2:$F$99995,4,0) -> 2070 | J353: =I353/G353 -> 345 | K353: =VLOOKUP($A353,ZLAM!$C$2:$F$99999,4,0) -> 76.81 | L353: =I353*K353/100 -> 1589.967 | M353: =L353/G353 -> 264.9945 | N353: =L353/1.18 -> 1347.4297 | O353: =N353/G353 -> 224.57161 | P353: =IFERROR(ABS(VLOOKUP($A353,ZTRV!$D$2:$G$99407,4,0)),0) -> 0 | Q353: =IFERROR(ABS(VLOOKUP($A353,ZTR1!$D$2:$G$99999,4,0)),0) -> 0 | R353: =IFERROR(ABS(VLOOKUP($A353,ZTR2!$D$2:$G$99939,4,0)),0) -> 0 | S353: =SUM(P353:R353)*G353 -> 0 | T353: =N353-S353 -> 1347.4297 | U353: =T353*1.18 -> 1589.967 | V353: =U353/G353 -> 264.9945 | W353: =V353*F353 -> 1589.967 | X353: =I353-U353 -> 480.033 | Y353: =X353*H353 -> 480.033 | Z353: =J353-V353 -> 80.0055 | AA353: =IFERROR(ABS(VLOOKUP(A353,ZSSD!$D$2:$G$99933,4,0)),AI353) -> 6.5 | AB353: =IFERROR(IF(VLOOKUP(A353,ZSSD!$D:$H,5,0)="L29",AA353*G353,AA353*L353/100),AA353*L353/100) -> 103.34785 | AC353: 2 | AD353: =2*(T353-AB353)/100 -> 24.881636 | AE353: =+AB353/G353 -> 17.224642 | AF353: =+AD353/G353 -> 4.1469394 | AG353: =VLOOKUP(A353,ZSSD!D:D,1,0) -> #N/A | AH353: =VLOOKUP(B353,[2]GRADE!$A:$P,16,0) -> SILVER | AI353: =IF(AH353="SILVER",6.5,IF(AH353="GOLD",8,IF(AH353="INDUSTRIAL",6,IF(AH353="GREEN",7,IF(AH353="BRONZE",5.5,0))))) -> 6.5
A354: 7556184 | B354: =VALUE(LEFT(A354,4)) -> 7556 | C354: =VALUE(RIGHT(A354,3)) -> 184 | D354: =VLOOKUP(C354,Sheet1!$A$2:$K$369991,11,0) -> CAR | E354: SERVO PRIDE TC 15W40 - 20X1L-HDPE | F354: =VLOOKUP(C354,'PACK MASTER'!$A$2:$I$512998,9,0)*1000 -> 20 | G354: =VLOOKUP(C354,'PACK MASTER'!$A$2:$G$512998,7,0) -> 1 | H354: =F354/G354 -> 20 | I354: =VLOOKUP($A354,ZMRP!$C$2:$F$99995,4,0) -> 355 | J354: =I354/G354 -> 355 | K354: =VLOOKUP($A354,ZLAM!$C$2:$F$99999,4,0) -> 77.74 | L354: =I354*K354/100 -> 275.977 | M354: =L354/G354 -> 275.977 | N354: =L354/1.18 -> 233.87881 | O354: =N354/G354 -> 233.87881 | P354: =IFERROR(ABS(VLOOKUP($A354,ZTRV!$D$2:$G$99407,4,0)),0) -> 13 | Q354: =IFERROR(ABS(VLOOKUP($A354,ZTR1!$D$2:$G$99999,4,0)),0) -> 0 | R354: =IFERROR(ABS(VLOOKUP($A354,ZTR2!$D$2:$G$99939,4,0)),0) -> 0 | S354: =SUM(P354:R354)*G354 -> 13 | T354: =N354-S354 -> 220.87881 | U354: =T354*1.18 -> 260.637 | V354: =U354/G354 -> 260.637 | W354: =V354*F354 -> 5212.74 | X354: =I354-U354 -> 94.363 | Y354: =X354*H354 -> 1887.26 | Z354: =J354-V354 -> 94.363 | AA354: =IFERROR(ABS(VLOOKUP(A354,ZSSD!$D$2:$G$99933,4,0)),AI354) -> 6.5 | AB354: =IFERROR(IF(VLOOKUP(A354,ZSSD!$D:$H,5,0)="L29",AA354*G354,AA354*L354/100),AA354*L354/100) -> 17.938505 | AC354: 2 | AD354: =2*(T354-AB354)/100 -> 4.0588062 | AE354: =+AB354/G354 -> 17.938505 | AF354: =+AD354/G354 -> 4.0588062 | AG354: =VLOOKUP(A354,ZSSD!D:D,1,0) -> #N/A | AH354: =VLOOKUP(B354,[2]GRADE!$A:$P,16,0) -> SILVER | AI354: =IF(AH354="SILVER",6.5,IF(AH354="GOLD",8,IF(AH354="INDUSTRIAL",6,IF(AH354="GREEN",7,IF(AH354="BRONZE",5.5,0))))) -> 6.5
A355: 7556195 | B355: =VALUE(LEFT(A355,4)) -> 7556 | C355: =VALUE(RIGHT(A355,3)) -> 195 | D355: =VLOOKUP(C355,Sheet1!$A$2:$K$369991,11,0) -> CAR | E355: SERVO PRIDE TC 15W-40 - 4 X 2.5 L HDPE | F355: =VLOOKUP(C355,'PACK MASTER'!$A$2:$I$512998,9,0)*1000 -> 10 | G355: =VLOOKUP(C355,'PACK MASTER'!$A$2:$G$512998,7,0) -> 2.5 | H355: =F355/G355 -> 4 | I355: =VLOOKUP($A355,ZMRP!$C$2:$F$99995,4,0) -> 888 | J355: =I355/G355 -> 355.2 | K355: =VLOOKUP($A355,ZLAM!$C$2:$F$99999,4,0) -> 77.74 | L355: =I355*K355/100 -> 690.3312 | M355: =L355/G355 -> 276.13248 | N355: =L355/1.18 -> 585.02644 | O355: =N355/G355 -> 234.01058 | P355: =IFERROR(ABS(VLOOKUP($A355,ZTRV!$D$2:$G$99407,4,0)),0) -> 13 | Q355: =IFERROR(ABS(VLOOKUP($A355,ZTR1!$D$2:$G$99999,4,0)),0) -> 0 | R355: =IFERROR(ABS(VLOOKUP($A355,ZTR2!$D$2:$G$99939,4,0)),0) -> 0 | S355: =SUM(P355:R355)*G355 -> 32.5 | T355: =N355-S355 -> 552.52644 | U355: =T355*1.18 -> 651.9812 | V355: =U355/G355 -> 260.79248 | W355: =V355*F355 -> 2607.9248 | X355: =I355-U355 -> 236.0188 | Y355: =X355*H355 -> 944.0752 | Z355: =J355-V355 -> 94.40752 | AA355: =IFERROR(ABS(VLOOKUP(A355,ZSSD!$D$2:$G$99933,4,0)),AI355) -> 6.5 | AB355: =IFERROR(IF(VLOOKUP(A355,ZSSD!$D:$H,5,0)="L29",AA355*G355,AA355*L355/100),AA355*L355/100) -> 44.871528 | AC355: 2 | AD355: =2*(T355-AB355)/100 -> 10.153098 | AE355: =+AB355/G355 -> 17.948611 | AF355: =+AD355/G355 -> 4.0612393 | AG355: =VLOOKUP(A355,ZSSD!D:D,1,0) -> #N/A | AH355: =VLOOKUP(B355,[2]GRADE!$A:$P,16,0) -> SILVER | AI355: =IF(AH355="SILVER",6.5,IF(AH355="GOLD",8,IF(AH355="INDUSTRIAL",6,IF(AH355="GREEN",7,IF(AH355="BRONZE",5.5,0))))) -> 6.5
A356: 7556203 | B356: =VALUE(LEFT(A356,4)) -> 7556 | C356: =VALUE(RIGHT(A356,3)) -> 203 | D356: =VLOOKUP(C356,Sheet1!$A$2:$K$369991,11,0) -> CAR | E356: SERVO PRIDE TC 15W-40 - 4 X 3 L HDPE | F356: =VLOOKUP(C356,'PACK MASTER'!$A$2:$I$512998,9,0)*1000 -> 12 | G356: =VLOOKUP(C356,'PACK MASTER'!$A$2:$G$512998,7,0) -> 3 | H356: =F356/G356 -> 4 | I356: =VLOOKUP($A356,ZMRP!$C$2:$F$99995,4,0) -> 1045 | J356: =I356/G356 -> 348.33333 | K356: =VLOOKUP($A356,ZLAM!$C$2:$F$99999,4,0) -> 78.27 | L356: =I356*K356/100 -> 817.9215 | M356: =L356/G356 -> 272.6405 | N356: =L356/1.18 -> 693.15381 | O356: =N356/G356 -> 231.05127 | P356: =IFERROR(ABS(VLOOKUP($A356,ZTRV!$D$2:$G$99407,4,0)),0) -> 50 | Q356: =IFERROR(ABS(VLOOKUP($A356,ZTR1!$D$2:$G$99999,4,0)),0) -> 0 | R356: =IFERROR(ABS(VLOOKUP($A356,ZTR2!$D$2:$G$99939,4,0)),0) -> 0 | S356: =SUM(P356:R356)*G356 -> 150 | T356: =N356-S356 -> 543.15381 | U356: =T356*1.18 -> 640.9215 | V356: =U356/G356 -> 213.6405 | W356: =V356*F356 -> 2563.686 | X356: =I356-U356 -> 404.0785 | Y356: =X356*H356 -> 1616.314 | Z356: =J356-V356 -> 134.69283 | AA356: =IFERROR(ABS(VLOOKUP(A356,ZSSD!$D$2:$G$99933,4,0)),AI356) -> 6.5 | AB356: =IFERROR(IF(VLOOKUP(A356,ZSSD!$D:$H,5,0)="L29",AA356*G356,AA356*L356/100),AA356*L356/100) -> 53.164897 | AC356: 2 | AD356: =2*(T356-AB356)/100 -> 9.7997783 | AE356: =+AB356/G356 -> 17.721632 | AF356: =+AD356/G356 -> 3.2665928 | AG356: =VLOOKUP(A356,ZSSD!D:D,1,0) -> #N/A | AH356: =VLOOKUP(B356,[2]GRADE!$A:$P,16,0) -> SILVER | AI356: =IF(AH356="SILVER",6.5,IF(AH356="GOLD",8,IF(AH356="INDUSTRIAL",6,IF(AH356="GREEN",7,IF(AH356="BRONZE",5.5,0))))) -> 6.5
A357: 7556204 | B357: =VALUE(LEFT(A357,4)) -> 7556 | C357: =VALUE(RIGHT(A357,3)) -> 204 | D357: =VLOOKUP(C357,Sheet1!$A$2:$K$369991,11,0) -> CAR | E357: SERVO PRIDE TC 15W40-4X3 L PROMO | F357: =VLOOKUP(C357,'PACK MASTER'!$A$2:$I$512998,9,0)*1000 -> 12 | G357: =VLOOKUP(C357,'PACK MASTER'!$A$2:$G$512998,7,0) -> 3 | H357: =F357/G357 -> 4 | I357: =VLOOKUP($A357,ZMRP!$C$2:$F$99995,4,0) -> 1045 | J357: =I357/G357 -> 348.33333 | K357: =VLOOKUP($A357,ZLAM!$C$2:$F$99999,4,0) -> 78.27 | L357: =I357*K357/100 -> 817.9215 | M357: =L357/G357 -> 272.6405 | N357: =L357/1.18 -> 693.15381 | O357: =N357/G357 -> 231.05127 | P357: =IFERROR(ABS(VLOOKUP($A357,ZTRV!$D$2:$G$99407,4,0)),0) -> 50 | Q357: =IFERROR(ABS(VLOOKUP($A357,ZTR1!$D$2:$G$99999,4,0)),0) -> 0 | R357: =IFERROR(ABS(VLOOKUP($A357,ZTR2!$D$2:$G$99939,4,0)),0) -> 0 | S357: =SUM(P357:R357)*G357 -> 150 | T357: =N357-S357 -> 543.15381 | U357: =T357*1.18 -> 640.9215 | V357: =U357/G357 -> 213.6405 | W357: =V357*F357 -> 2563.686 | X357: =I357-U357 -> 404.0785 | Y357: =X357*H357 -> 1616.314 | Z357: =J357-V357 -> 134.69283 | AA357: =IFERROR(ABS(VLOOKUP(A357,ZSSD!$D$2:$G$99933,4,0)),AI357) -> 6.5 | AB357: =IFERROR(IF(VLOOKUP(A357,ZSSD!$D:$H,5,0)="L29",AA357*G357,AA357*L357/100),AA357*L357/100) -> 53.164897 | AC357: 2 | AD357: =2*(T357-AB357)/100 -> 9.7997783 | AE357: =+AB357/G357 -> 17.721632 | AF357: =+AD357/G357 -> 3.2665928 | AG357: =VLOOKUP(A357,ZSSD!D:D,1,0) -> #N/A | AH357: =VLOOKUP(B357,[2]GRADE!$A:$P,16,0) -> SILVER | AI357: =IF(AH357="SILVER",6.5,IF(AH357="GOLD",8,IF(AH357="INDUSTRIAL",6,IF(AH357="GREEN",7,IF(AH357="BRONZE",5.5,0))))) -> 6.5
A358: 7556234 | B358: =VALUE(LEFT(A358,4)) -> 7556 | C358: =VALUE(RIGHT(A358,3)) -> 234 | D358: =VLOOKUP(C358,Sheet1!$A$2:$K$369991,11,0) -> CAR | E358: SERVO PRIDE TC 15W-40- 4 X 5L | F358: =VLOOKUP(C358,'PACK MASTER'!$A$2:$I$512998,9,0)*1000 -> 20 | G358: =VLOOKUP(C358,'PACK MASTER'!$A$2:$G$512998,7,0) -> 5 | H358: =F358/G358 -> 4 | I358: =VLOOKUP($A358,ZMRP!$C$2:$F$99995,4,0) -> 1725 | J358: =I358/G358 -> 345 | K358: =VLOOKUP($A358,ZLAM!$C$2:$F$99999,4,0) -> 78.4 | L358: =I358*K358/100 -> 1352.4 | M358: =L358/G358 -> 270.48 | N358: =L358/1.18 -> 1146.1017 | O358: =N358/G358 -> 229.22034 | P358: =IFERROR(ABS(VLOOKUP($A358,ZTRV!$D$2:$G$99407,4,0)),0) -> 23 | Q358: =IFERROR(ABS(VLOOKUP($A358,ZTR1!$D$2:$G$99999,4,0)),0) -> 0 | R358: =IFERROR(ABS(VLOOKUP($A358,ZTR2!$D$2:$G$99939,4,0)),0) -> 0 | S358: =SUM(P358:R358)*G358 -> 115 | T358: =N358-S358 -> 1031.1017 | U358: =T358*1.18 -> 1216.7 | V358: =U358/G358 -> 243.34 | W358: =V358*F358 -> 4866.8 | X358: =I358-U358 -> 508.3 | Y358: =X358*H358 -> 2033.2 | Z358: =J358-V358 -> 101.66 | AA358: =IFERROR(ABS(VLOOKUP(A358,ZSSD!$D$2:$G$99933,4,0)),AI358) -> 6.5 | AB358: =IFERROR(IF(VLOOKUP(A358,ZSSD!$D:$H,5,0)="L29",AA358*G358,AA358*L358/100),AA358*L358/100) -> 87.906 | AC358: 2 | AD358: =2*(T358-AB358)/100 -> 18.863914 | AE358: =+AB358/G358 -> 17.5812 | AF358: =+AD358/G358 -> 3.7727828 | AG358: =VLOOKUP(A358,ZSSD!D:D,1,0) -> #N/A | AH358: =VLOOKUP(B358,[2]GRADE!$A:$P,16,0) -> SILVER | AI358: =IF(AH358="SILVER",6.5,IF(AH358="GOLD",8,IF(AH358="INDUSTRIAL",6,IF(AH358="GREEN",7,IF(AH358="BRONZE",5.5,0))))) -> 6.5
A359: 7556241 | B359: =VALUE(LEFT(A359,4)) -> 7556 | C359: =VALUE(RIGHT(A359,3)) -> 241 | D359: =VLOOKUP(C359,Sheet1!$A$2:$K$369991,11,0) -> BUC | E359: SERVO PRIDE TC 15W40-10L PROMO | F359: =VLOOKUP(C359,'PACK MASTER'!$A$2:$I$512998,9,0)*1000 -> 10 | G359: =VLOOKUP(C359,'PACK MASTER'!$A$2:$G$512998,7,0) -> 10 | H359: =F359/G359 -> 1 | I359: =VLOOKUP($A359,ZMRP!$C$2:$F$99995,4,0) -> 3400 | J359: =I359/G359 -> 340 | K359: =VLOOKUP($A359,ZLAM!$C$2:$F$99999,4,0) -> 78.62 | L359: =I359*K359/100 -> 2673.08 | M359: =L359/G359 -> 267.308 | N359: =L359/1.18 -> 2265.322 | O359: =N359/G359 -> 226.5322 | P359: =IFERROR(ABS(VLOOKUP($A359,ZTRV!$D$2:$G$99407,4,0)),0) -> 48 | Q359: =IFERROR(ABS(VLOOKUP($A359,ZTR1!$D$2:$G$99999,4,0)),0) -> 0 | R359: =IFERROR(ABS(VLOOKUP($A359,ZTR2!$D$2:$G$99939,4,0)),0) -> 0 | S359: =SUM(P359:R359)*G359 -> 480 | T359: =N359-S359 -> 1785.322 | U359: =T359*1.18 -> 2106.68 | V359: =U359/G359 -> 210.668 | W359: =V359*F359 -> 2106.68 | X359: =I359-U359 -> 1293.32 | Y359: =X359*H359 -> 1293.32 | Z359: =J359-V359 -> 129.332 | AA359: =IFERROR(ABS(VLOOKUP(A359,ZSSD!$D$2:$G$99933,4,0)),AI359) -> 6.5 | AB359: =IFERROR(IF(VLOOKUP(A359,ZSSD!$D:$H,5,0)="L29",AA359*G359,AA359*L359/100),AA359*L359/100) -> 173.7502 | AC359: 2 | AD359: =2*(T359-AB359)/100 -> 32.231437 | AE359: =+AB359/G359 -> 17.37502 | AF359: =+AD359/G359 -> 3.2231437 | AG359: =VLOOKUP(A359,ZSSD!D:D,1,0) -> #N/A | AH359: =VLOOKUP(B359,[2]GRADE!$A:$P,16,0) -> SILVER | AI359: =IF(AH359="SILVER",6.5,IF(AH359="GOLD",8,IF(AH359="INDUSTRIAL",6,IF(AH359="GREEN",7,IF(AH359="BRONZE",5.5,0))))) -> 6.5
A360: 7556242 | B360: =VALUE(LEFT(A360,4)) -> 7556 | C360: =VALUE(RIGHT(A360,3)) -> 242 | D360: =VLOOKUP(C360,Sheet1!$A$2:$K$369991,11,0) -> BUC | E360: SERVO PRIDE TC 15W-40 - 10 L BUC | F360: =VLOOKUP(C360,'PACK MASTER'!$A$2:$I$512998,9,0)*1000 -> 10 | G360: =VLOOKUP(C360,'PACK MASTER'!$A$2:$G$512998,7,0) -> 10 | H360: =F360/G360 -> 1 | I360: =VLOOKUP($A360,ZMRP!$C$2:$F$99995,4,0) -> 3400 | J360: =I360/G360 -> 340 | K360: =VLOOKUP($A360,ZLAM!$C$2:$F$99999,4,0) -> 78.62 | L360: =I360*K360/100 -> 2673.08 | M360: =L360/G360 -> 267.308 | N360: =L360/1.18 -> 2265.322 | O360: =N360/G360 -> 226.5322 | P360: =IFERROR(ABS(VLOOKUP($A360,ZTRV!$D$2:$G$99407,4,0)),0) -> 48 | Q360: =IFERROR(ABS(VLOOKUP($A360,ZTR1!$D$2:$G$99999,4,0)),0) -> 0 | R360: =IFERROR(ABS(VLOOKUP($A360,ZTR2!$D$2:$G$99939,4,0)),0) -> 0 | S360: =SUM(P360:R360)*G360 -> 480 | T360: =N360-S360 -> 1785.322 | U360: =T360*1.18 -> 2106.68 | V360: =U360/G360 -> 210.668 | W360: =V360*F360 -> 2106.68 | X360: =I360-U360 -> 1293.32 | Y360: =X360*H360 -> 1293.32 | Z360: =J360-V360 -> 129.332 | AA360: =IFERROR(ABS(VLOOKUP(A360,ZSSD!$D$2:$G$99933,4,0)),AI360) -> 6.5 | AB360: =IFERROR(IF(VLOOKUP(A360,ZSSD!$D:$H,5,0)="L29",AA360*G360,AA360*L360/100),AA360*L360/100) -> 173.7502 | AC360: 2 | AD360: =2*(T360-AB360)/100 -> 32.231437 | AE360: =+AB360/G360 -> 17.37502 | AF360: =+AD360/G360 -> 3.2231437 | AG360: =VLOOKUP(A360,ZSSD!D:D,1,0) -> #N/A | AH360: =VLOOKUP(B360,[2]GRADE!$A:$P,16,0) -> SILVER | AI360: =IF(AH360="SILVER",6.5,IF(AH360="GOLD",8,IF(AH360="INDUSTRIAL",6,IF(AH360="GREEN",7,IF(AH360="BRONZE",5.5,0))))) -> 6.5
A361: 7556250 | B361: =VALUE(LEFT(A361,4)) -> 7556 | C361: =VALUE(RIGHT(A361,3)) -> 250 | D361: =VLOOKUP(C361,Sheet1!$A$2:$K$369991,11,0) -> BUC | E361: SERVO PRIDE TC 15W40-7.5L PROMO | F361: =VLOOKUP(C361,'PACK MASTER'!$A$2:$I$512998,9,0)*1000 -> 7.5 | G361: =VLOOKUP(C361,'PACK MASTER'!$A$2:$G$512998,7,0) -> 7.5 | H361: =F361/G361 -> 1 | I361: =VLOOKUP($A361,ZMRP!$C$2:$F$99995,4,0) -> 2563 | J361: =I361/G361 -> 341.73333 | K361: =VLOOKUP($A361,ZLAM!$C$2:$F$99999,4,0) -> 78.72 | L361: =I361*K361/100 -> 2017.5936 | M361: =L361/G361 -> 269.01248 | N361: =L361/1.18 -> 1709.8251 | O361: =N361/G361 -> 227.97668 | P361: =IFERROR(ABS(VLOOKUP($A361,ZTRV!$D$2:$G$99407,4,0)),0) -> 50 | Q361: =IFERROR(ABS(VLOOKUP($A361,ZTR1!$D$2:$G$99999,4,0)),0) -> 0 | R361: =IFERROR(ABS(VLOOKUP($A361,ZTR2!$D$2:$G$99939,4,0)),0) -> 0 | S361: =SUM(P361:R361)*G361 -> 375 | T361: =N361-S361 -> 1334.8251 | U361: =T361*1.18 -> 1575.0936 | V361: =U361/G361 -> 210.01248 | W361: =V361*F361 -> 1575.0936 | X361: =I361-U361 -> 987.9064 | Y361: =X361*H361 -> 987.9064 | Z361: =J361-V361 -> 131.72085 | AA361: =IFERROR(ABS(VLOOKUP(A361,ZSSD!$D$2:$G$99933,4,0)),AI361) -> 6.5 | AB361: =IFERROR(IF(VLOOKUP(A361,ZSSD!$D:$H,5,0)="L29",AA361*G361,AA361*L361/100),AA361*L361/100) -> 131.14358 | AC361: 2 | AD361: =2*(T361-AB361)/100 -> 24.07363 | AE361: =+AB361/G361 -> 17.485811 | AF361: =+AD361/G361 -> 3.2098173 | AG361: =VLOOKUP(A361,ZSSD!D:D,1,0) -> #N/A | AH361: =VLOOKUP(B361,[2]GRADE!$A:$P,16,0) -> SILVER | AI361: =IF(AH361="SILVER",6.5,IF(AH361="GOLD",8,IF(AH361="INDUSTRIAL",6,IF(AH361="GREEN",7,IF(AH361="BRONZE",5.5,0))))) -> 6.5
A362: 7556251 | B362: =VALUE(LEFT(A362,4)) -> 7556 | C362: =VALUE(RIGHT(A362,3)) -> 251 | D362: =VLOOKUP(C362,Sheet1!$A$2:$K$369991,11,0) -> BUC | E362: SERVO PRIDE TC 15W40 - 7.5L BUC | F362: =VLOOKUP(C362,'PACK MASTER'!$A$2:$I$512998,9,0)*1000 -> 7.5 | G362: =VLOOKUP(C362,'PACK MASTER'!$A$2:$G$512998,7,0) -> 7.5 | H362: =F362/G362 -> 1 | I362: =VLOOKUP($A362,ZMRP!$C$2:$F$99995,4,0) -> 2563 | J362: =I362/G362 -> 341.73333 | K362: =VLOOKUP($A362,ZLAM!$C$2:$F$99999,4,0) -> 78.72 | L362: =I362*K362/100 -> 2017.5936 | M362: =L362/G362 -> 269.01248 | N362: =L362/1.18 -> 1709.8251 | O362: =N362/G362 -> 227.97668 | P362: =IFERROR(ABS(VLOOKUP($A362,ZTRV!$D$2:$G$99407,4,0)),0) -> 50 | Q362: =IFERROR(ABS(VLOOKUP($A362,ZTR1!$D$2:$G$99999,4,0)),0) -> 0 | R362: =IFERROR(ABS(VLOOKUP($A362,ZTR2!$D$2:$G$99939,4,0)),0) -> 0 | S362: =SUM(P362:R362)*G362 -> 375 | T362: =N362-S362 -> 1334.8251 | U362: =T362*1.18 -> 1575.0936 | V362: =U362/G362 -> 210.01248 | W362: =V362*F362 -> 1575.0936 | X362: =I362-U362 -> 987.9064 | Y362: =X362*H362 -> 987.9064 | Z362: =J362-V362 -> 131.72085 | AA362: =IFERROR(ABS(VLOOKUP(A362,ZSSD!$D$2:$G$99933,4,0)),AI362) -> 6.5 | AB362: =IFERROR(IF(VLOOKUP(A362,ZSSD!$D:$H,5,0)="L29",AA362*G362,AA362*L362/100),AA362*L362/100) -> 131.14358 | AC362: 2 | AD362: =2*(T362-AB362)/100 -> 24.07363 | AE362: =+AB362/G362 -> 17.485811 | AF362: =+AD362/G362 -> 3.2098173 | AG362: =VLOOKUP(A362,ZSSD!D:D,1,0) -> #N/A | AH362: =VLOOKUP(B362,[2]GRADE!$A:$P,16,0) -> SILVER | AI362: =IF(AH362="SILVER",6.5,IF(AH362="GOLD",8,IF(AH362="INDUSTRIAL",6,IF(AH362="GREEN",7,IF(AH362="BRONZE",5.5,0))))) -> 6.5
A363: 7556253 | B363: =VALUE(LEFT(A363,4)) -> 7556 | C363: =VALUE(RIGHT(A363,3)) -> 253 | D363: =VLOOKUP(C363,Sheet1!$A$2:$K$369991,11,0) -> BUC | E363: SERVO PRIDE TC 15W40-15L PROMO | F363: =VLOOKUP(C363,'PACK MASTER'!$A$2:$I$512998,9,0)*1000 -> 15 | G363: =VLOOKUP(C363,'PACK MASTER'!$A$2:$G$512998,7,0) -> 15 | H363: =F363/G363 -> 1 | I363: =VLOOKUP($A363,ZMRP!$C$2:$F$99995,4,0) -> 5025 | J363: =I363/G363 -> 335 | K363: =VLOOKUP($A363,ZLAM!$C$2:$F$99999,4,0) -> 79.51 | L363: =I363*K363/100 -> 3995.3775 | M363: =L363/G363 -> 266.3585 | N363: =L363/1.18 -> 3385.9131 | O363: =N363/G363 -> 225.72754 | P363: =IFERROR(ABS(VLOOKUP($A363,ZTRV!$D$2:$G$99407,4,0)),0) -> 55 | Q363: =IFERROR(ABS(VLOOKUP($A363,ZTR1!$D$2:$G$99999,4,0)),0) -> 0 | R363: =IFERROR(ABS(VLOOKUP($A363,ZTR2!$D$2:$G$99939,4,0)),0) -> 0 | S363: =SUM(P363:R363)*G363 -> 825 | T363: =N363-S363 -> 2560.9131 | U363: =T363*1.18 -> 3021.8775 | V363: =U363/G363 -> 201.4585 | W363: =V363*F363 -> 3021.8775 | X363: =I363-U363 -> 2003.1225 | Y363: =X363*H363 -> 2003.1225 | Z363: =J363-V363 -> 133.5415 | AA363: =IFERROR(ABS(VLOOKUP(A363,ZSSD!$D$2:$G$99933,4,0)),AI363) -> 6.5 | AB363: =IFERROR(IF(VLOOKUP(A363,ZSSD!$D:$H,5,0)="L29",AA363*G363,AA363*L363/100),AA363*L363/100) -> 259.69954 | AC363: 2 | AD363: =2*(T363-AB363)/100 -> 46.024272 | AE363: =+AB363/G363 -> 17.313303 | AF363: =+AD363/G363 -> 3.0682848 | AG363: =VLOOKUP(A363,ZSSD!D:D,1,0) -> #N/A | AH363: =VLOOKUP(B363,[2]GRADE!$A:$P,16,0) -> SILVER | AI363: =IF(AH363="SILVER",6.5,IF(AH363="GOLD",8,IF(AH363="INDUSTRIAL",6,IF(AH363="GREEN",7,IF(AH363="BRONZE",5.5,0))))) -> 6.5
A364: 7556256 | B364: =VALUE(LEFT(A364,4)) -> 7556 | C364: =VALUE(RIGHT(A364,3)) -> 256 | D364: =VLOOKUP(C364,Sheet1!$A$2:$K$369991,11,0) -> BUC | E364: SERVO PRIDE TC 15W40 - 15 L BUC | F364: =VLOOKUP(C364,'PACK MASTER'!$A$2:$I$512998,9,0)*1000 -> 15 | G364: =VLOOKUP(C364,'PACK MASTER'!$A$2:$G$512998,7,0) -> 15 | H364: =F364/G364 -> 1 | I364: =VLOOKUP($A364,ZMRP!$C$2:$F$99995,4,0) -> 5025 | J364: =I364/G364 -> 335 | K364: =VLOOKUP($A364,ZLAM!$C$2:$F$99999,4,0) -> 79.51 | L364: =I364*K364/100 -> 3995.3775 | M364: =L364/G364 -> 266.3585 | N364: =L364/1.18 -> 3385.9131 | O364: =N364/G364 -> 225.72754 | P364: =IFERROR(ABS(VLOOKUP($A364,ZTRV!$D$2:$G$99407,4,0)),0) -> 55 | Q364: =IFERROR(ABS(VLOOKUP($A364,ZTR1!$D$2:$G$99999,4,0)),0) -> 0 | R364: =IFERROR(ABS(VLOOKUP($A364,ZTR2!$D$2:$G$99939,4,0)),0) -> 0 | S364: =SUM(P364:R364)*G364 -> 825 | T364: =N364-S364 -> 2560.9131 | U364: =T364*1.18 -> 3021.8775 | V364: =U364/G364 -> 201.4585 | W364: =V364*F364 -> 3021.8775 | X364: =I364-U364 -> 2003.1225 | Y364: =X364*H364 -> 2003.1225 | Z364: =J364-V364 -> 133.5415 | AA364: =IFERROR(ABS(VLOOKUP(A364,ZSSD!$D$2:$G$99933,4,0)),AI364) -> 6.5 | AB364: =IFERROR(IF(VLOOKUP(A364,ZSSD!$D:$H,5,0)="L29",AA364*G364,AA364*L364/100),AA364*L364/100) -> 259.69954 | AC364: 2 | AD364: =2*(T364-AB364)/100 -> 46.024272 | AE364: =+AB364/G364 -> 17.313303 | AF364: =+AD364/G364 -> 3.0682848 | AG364: =VLOOKUP(A364,ZSSD!D:D,1,0) -> #N/A | AH364: =VLOOKUP(B364,[2]GRADE!$A:$P,16,0) -> SILVER | AI364: =IF(AH364="SILVER",6.5,IF(AH364="GOLD",8,IF(AH364="INDUSTRIAL",6,IF(AH364="GREEN",7,IF(AH364="BRONZE",5.5,0))))) -> 6.5
A365: 7556265 | B365: =VALUE(LEFT(A365,4)) -> 7556 | C365: =VALUE(RIGHT(A365,3)) -> 265 | D365: =VLOOKUP(C365,Sheet1!$A$2:$K$369991,11,0) -> BUC | E365: SERVO PRIDE TC 15W40 - 20L BUC | F365: =VLOOKUP(C365,'PACK MASTER'!$A$2:$I$512998,9,0)*1000 -> 20 | G365: =VLOOKUP(C365,'PACK MASTER'!$A$2:$G$512998,7,0) -> 20 | H365: =F365/G365 -> 1 | I365: =VLOOKUP($A365,ZMRP!$C$2:$F$99995,4,0) -> 6700 | J365: =I365/G365 -> 335 | K365: =VLOOKUP($A365,ZLAM!$C$2:$F$99999,4,0) -> 79.34 | L365: =I365*K365/100 -> 5315.78 | M365: =L365/G365 -> 265.789 | N365: =L365/1.18 -> 4504.8983 | O365: =N365/G365 -> 225.24492 | P365: =IFERROR(ABS(VLOOKUP($A365,ZTRV!$D$2:$G$99407,4,0)),0) -> 45 | Q365: =IFERROR(ABS(VLOOKUP($A365,ZTR1!$D$2:$G$99999,4,0)),0) -> 0 | R365: =IFERROR(ABS(VLOOKUP($A365,ZTR2!$D$2:$G$99939,4,0)),0) -> 0 | S365: =SUM(P365:R365)*G365 -> 900 | T365: =N365-S365 -> 3604.8983 | U365: =T365*1.18 -> 4253.78 | V365: =U365/G365 -> 212.689 | W365: =V365*F365 -> 4253.78 | X365: =I365-U365 -> 2446.22 | Y365: =X365*H365 -> 2446.22 | Z365: =J365-V365 -> 122.311 | AA365: =IFERROR(ABS(VLOOKUP(A365,ZSSD!$D$2:$G$99933,4,0)),AI365) -> 6.5 | AB365: =IFERROR(IF(VLOOKUP(A365,ZSSD!$D:$H,5,0)="L29",AA365*G365,AA365*L365/100),AA365*L365/100) -> 345.5257 | AC365: 2 | AD365: =2*(T365-AB365)/100 -> 65.187452 | AE365: =+AB365/G365 -> 17.276285 | AF365: =+AD365/G365 -> 3.2593726 | AG365: =VLOOKUP(A365,ZSSD!D:D,1,0) -> #N/A | AH365: =VLOOKUP(B365,[2]GRADE!$A:$P,16,0) -> SILVER | AI365: =IF(AH365="SILVER",6.5,IF(AH365="GOLD",8,IF(AH365="INDUSTRIAL",6,IF(AH365="GREEN",7,IF(AH365="BRONZE",5.5,0))))) -> 6.5
...

Sheet PACK MASTER
A1: PACK CODE | B1: BULK | C1: BULK | D1: BULK | E1: unit | G1: SINGLE ITEM SIZE IN L | H1: BULK | I1: PACK SIZE IN KL
A2: 101 | B2: 20 ML PIL POU | C2: 20 ML | D2: 20 | E2: ML | F2: =VLOOKUP(E2,$P$6:$Q$9,2,0) -> 0.001 | G2: =D2*F2 -> 0.02 | H2: SMALL | I2: 2e-05
A3: 102 | B3: 1000X20ML - POU | C3: 20 ML | D3: 20 | E3: ML | F3: =VLOOKUP(E3,$P$6:$Q$9,2,0) -> 0.001 | G3: =D3*F3 -> 0.02 | H3: SMALL | I3: 0.02
A4: 103 | B4: 600 X 20 ML POU | C4: 20 ML | D4: 20 | E4: ML | F4: =VLOOKUP(E4,$P$6:$Q$9,2,0) -> 0.001 | G4: =D4*F4 -> 0.02 | H4: SMALL | I4: 0.012
A5: 104 | B5: 0.8+0.1L Promo | C5: 0.9 L | D5: 0.9 | E5: L | F5: =VLOOKUP(E5,$P$6:$Q$9,2,0) -> 1 | G5: =D5*F5 -> 0.9 | H5: SMALL | I5: 0.0009
A6: 105 | B6: 20x(0.8+0.1L) Promo | C6: 0.9 L | D6: 0.9 | E6: L | F6: =VLOOKUP(E6,$P$6:$Q$9,2,0) -> 1 | G6: =D6*F6 -> 0.9 | H6: SMALL | I6: 0.018 | P6: ML | Q6: 0.001
A7: 106 | B7: 0.9+0.1L Promo | C7: 1 L | D7: 1 | E7: L | F7: =VLOOKUP(E7,$P$6:$Q$9,2,0) -> 1 | G7: =D7*F7 -> 1 | H7: SMALL | I7: 0.001 | P7: L | Q7: 1
A8: 107 | B8: 20x(0.9+0.1L) Promo | C8: 1 L | D8: 1 | E8: L | F8: =VLOOKUP(E8,$P$6:$Q$9,2,0) -> 1 | G8: =D8*F8 -> 1 | H8: SMALL | I8: 0.02 | P8: GM | Q8: 0.001
A9: 108 | B9: 2.5+0.5L Promo | C9: 3 L | D9: 3 | E9: L | F9: =VLOOKUP(E9,$P$6:$Q$9,2,0) -> 1 | G9: =D9*F9 -> 3 | H9: SMALL | I9: 0.003 | P9: KG | Q9: 1
A10: 109 | B10: 4x(2.5+0.5L) Promo | C10: 3 L | D10: 3 | E10: L | F10: =VLOOKUP(E10,$P$6:$Q$9,2,0) -> 1 | G10: =D10*F10 -> 3 | H10: SMALL | I10: 0.012
A11: 110 | B11: 3.5 L Promo | C11: 3.5 L | D11: 3.5 | E11: L | F11: =VLOOKUP(E11,$P$6:$Q$9,2,0) -> 1 | G11: =D11*F11 -> 3.5 | H11: SMALL | I11: 0.0035
A12: 111 | B12: 4 x 3.5 L Promo | C12: 3.5 L | D12: 3.5 | E12: L | F12: =VLOOKUP(E12,$P$6:$Q$9,2,0) -> 1 | G12: =D12*F12 -> 3.5 | H12: SMALL | I12: 0.014
A13: 112 | B13: 30ML POU | C13: 30 ML | D13: 30 | E13: ML | F13: =VLOOKUP(E13,$P$6:$Q$9,2,0) -> 0.001 | G13: =D13*F13 -> 0.03 | H13: SMALL | I13: 3e-05
A14: 113 | B14: 800X30ML - POU | C14: 30 ML | D14: 30 | E14: ML | F14: =VLOOKUP(E14,$P$6:$Q$9,2,0) -> 0.001 | G14: =D14*F14 -> 0.03 | H14: SMALL | I14: 0.024
A15: 114 | B15: 400X30ML - POU | C15: 30 ML | D15: 30 | E15: ML | F15: =VLOOKUP(E15,$P$6:$Q$9,2,0) -> 0.001 | G15: =D15*F15 -> 0.03 | H15: SMALL | I15: 0.012
A16: 115 | B16: 6+1.5 L Promo | C16: 7.5 L | D16: 7.5 | E16: L | F16: =VLOOKUP(E16,$P$6:$Q$9,2,0) -> 1 | G16: =D16*F16 -> 7.5 | H16: SMALL | I16: 0.0075
A17: 116 | B17: 8+2 L Promo | C17: 10 L | D17: 10 | E17: L | F17: =VLOOKUP(E17,$P$6:$Q$9,2,0) -> 1 | G17: =D17*F17 -> 10 | H17: SMALL | I17: 0.01
A18: 117 | B18: 8.5L Promo | C18: 8.5 L | D18: 8.5 | E18: L | F18: =VLOOKUP(E18,$P$6:$Q$9,2,0) -> 1 | G18: =D18*F18 -> 8.5 | H18: SMALL | I18: 0.0085
A19: 119 | B19: 40 ML HDPE | C19: 40 ML | D19: 40 | E19: ML | F19: =VLOOKUP(E19,$P$6:$Q$9,2,0) -> 0.001 | G19: =D19*F19 -> 0.04 | H19: SMALL | I19: 4e-05
A20: 120 | B20: 40 X 40 ML HDPE | C20: 40 ML | D20: 40 | E20: ML | F20: =VLOOKUP(E20,$P$6:$Q$9,2,0) -> 0.001 | G20: =D20*F20 -> 0.04 | H20: SMALL | I20: 0.0016
A21: 121 | B21: 40 ML PILL POU | C21: 40 ML | E21: ML | F21: =VLOOKUP(E21,$P$6:$Q$9,2,0) -> 0.001 | G21: =D21*F21 -> 0 | H21: SMALL | I21: 4e-05
A22: 122 | B22: 40ML POU | C22: 40 ML | D22: 40 | E22: ML | F22: =VLOOKUP(E22,$P$6:$Q$9,2,0) -> 0.001 | G22: =D22*F22 -> 0.04 | H22: SMALL | I22: 4e-05
A23: 123 | B23: 500X40ML - POU | C23: 40 ML | D23: 40 | E23: ML | F23: =VLOOKUP(E23,$P$6:$Q$9,2,0) -> 0.001 | G23: =D23*F23 -> 0.04 | H23: SMALL
A24: 124 | B24: 600X40ML-POU | C24: 40 ML | D24: 40 | E24: ML | F24: =VLOOKUP(E24,$P$6:$Q$9,2,0) -> 0.001 | G24: =D24*F24 -> 0.04 | H24: SMALL | I24: 0.024
A25: 125 | B25: 300X40ML - POU | C25: 40 ML | D25: 40 | E25: ML | F25: =VLOOKUP(E25,$P$6:$Q$9,2,0) -> 0.001 | G25: =D25*F25 -> 0.04 | H25: SMALL | I25: 0.012
A26: 126 | B26: 120 ML | C26: 120 ML | D26: 120 | E26: ML | F26: =VLOOKUP(E26,$P$6:$Q$9,2,0) -> 0.001 | G26: =D26*F26 -> 0.12 | H26: SMALL | I26: 0.00012
A27: 127 | B27: 20 X 120 ML | C27: 120 ML | D27: 120 | E27: ML | F27: =VLOOKUP(E27,$P$6:$Q$9,2,0) -> 0.001 | G27: =D27*F27 -> 0.12 | H27: SMALL | I27: 0.0024
A28: 128 | B28: (0.8+0.1)L | C28: 0.9 L | D28: 0.9 | E28: L | F28: =VLOOKUP(E28,$P$6:$Q$9,2,0) -> 1 | G28: =D28*F28 -> 0.9 | H28: SMALL | I28: 0.0009
A29: 129 | B29: 10x(0.8+0.1)L | C29: 0.9 L | D29: 0.9 | E29: L | F29: =VLOOKUP(E29,$P$6:$Q$9,2,0) -> 1 | G29: =D29*F29 -> 0.9 | H29: SMALL | I29: 0.009
A30: 130 | B30: 20x(0.8+0.1)L | C30: 0.9 L | D30: 0.9 | E30: L | F30: =VLOOKUP(E30,$P$6:$Q$9,2,0) -> 1 | G30: =D30*F30 -> 0.9 | H30: SMALL | I30: 0.018
A31: 131 | B31: 0.8L Promo | C31: 0.8 L | D31: 0.8 | E31: L | F31: =VLOOKUP(E31,$P$6:$Q$9,2,0) -> 1 | G31: =D31*F31 -> 0.8 | H31: SMALL | I31: 0.0008
A32: 132 | B32: 10 X 0.8 L Promo | C32: 0.8 L | D32: 0.8 | E32: L | F32: =VLOOKUP(E32,$P$6:$Q$9,2,0) -> 1 | G32: =D32*F32 -> 0.8 | H32: SMALL | I32: 0.008
A33: 133 | B33: 20 X 0.8 L Promo | C33: 0.8 L | D33: 0.8 | E33: L | F33: =VLOOKUP(E33,$P$6:$Q$9,2,0) -> 1 | G33: =D33*F33 -> 0.8 | H33: SMALL | I33: 0.016
A34: 134 | B34: 4.1L | C34: 4.1 L | D34: 4.1 | E34: L | F34: =VLOOKUP(E34,$P$6:$Q$9,2,0) -> 1 | G34: =D34*F34 -> 4.1 | H34: SMALL | I34: 0.0041
A35: 135 | B35: 4X4.1L | C35: 4.1 L | D35: 4.1 | E35: L | F35: =VLOOKUP(E35,$P$6:$Q$9,2,0) -> 1 | G35: =D35*F35 -> 4.1 | H35: SMALL | I35: 0.0164
... A439: 774 | B439: old-(12+3)L | C439: 15 L | D439: 15 | E439: L | F439: =VLOOKUP(E439,$P$6:$Q$9,2,0) -> 1 | G439: =D439*F439 -> 15 | H439: SMALL | I439: 0.015
A440: 775 | B440: old-9L | C440: 9L | D440: 9L | F440: =VLOOKUP(E440,$P$6:$Q$9,2,0) -> #N/A | G440: =D440*F440 -> #VALUE! | H440: SMALL | I440: 0.009
A441: 776 | B441: old-(7.5+1)L | C441: 8.5 L | D441: 8.5 | E441: L | F441: =VLOOKUP(E441,$P$6:$Q$9,2,0) -> 1 | G441: =D441*F441 -> 8.5 | H441: SMALL | I441: 0.0085
A442: 777 | B442: old-2 X 7.5 L | C442: 7.5 L | D442: 7.5 | E442: L | F442: =VLOOKUP(E442,$P$6:$Q$9,2,0) -> 1 | G442: =D442*F442 -> 7.5 | H442: SMALL | I442: 0.0075
A443: 778 | B443: old-2 X 8.5 L | C443: 8.5 L | D443: 8.5 | E443: L | F443: =VLOOKUP(E443,$P$6:$Q$9,2,0) -> 1 | G443: =D443*F443 -> 8.5 | H443: SMALL | I443: 0.0085
A444: 779 | B444: old-7.5+1 L Promo | C444: 8.5 L | D444: 8.5 | E444: L | F444: =VLOOKUP(E444,$P$6:$Q$9,2,0) -> 1 | G444: =D444*F444 -> 8.5 | H444: SMALL | I444: 0.0085
A445: 780 | B445: old-28 L- HDPE | C445: 28 L | D445: 28 | E445: L | F445: =VLOOKUP(E445,$P$6:$Q$9,2,0) -> 1 | G445: =D445*F445 -> 28 | H445: SMALL | I445: 0.028
A446: 781 | B446: old-30L DRUM | C446: 30 L | D446: 30 | E446: L | F446: =VLOOKUP(E446,$P$6:$Q$9,2,0) -> 1 | G446: =D446*F446 -> 30 | H446: SMALL | I446: 0.03
A447: 782 | B447: old-11 L | C447: 11 L | D447: 11 | E447: L | F447: =VLOOKUP(E447,$P$6:$Q$9,2,0) -> 1 | G447: =D447*F447 -> 11 | H447: SMALL | I447: 0.011
A448: 783 | B448: old-16 L | C448: 16 L | D448: 16 | E448: L | F448: =VLOOKUP(E448,$P$6:$Q$9,2,0) -> 1 | G448: =D448*F448 -> 16 | H448: SMALL | I448: 0.016
A449: 784 | B449: old-(42+8)L | C449: 50 L | D449: 50 | E449: L | F449: =VLOOKUP(E449,$P$6:$Q$9,2,0) -> 1 | G449: =D449*F449 -> 50 | H449: SMALL | I449: 0.05
A450: 785 | B450: old-100 L HDPE | C450: 100 L | D450: 100 | E450: L | F450: =VLOOKUP(E450,$P$6:$Q$9,2,0) -> 1 | G450: =D450*F450 -> 100 | H450: SMALL | I450: 0.1
A451: 786 | B451: old-18+2 L Promo | C451: 20 L | D451: 20 | E451: L | F451: =VLOOKUP(E451,$P$6:$Q$9,2,0) -> 1 | G451: =D451*F451 -> 20 | H451: SMALL | I451: 0.02
A452: 787 | B452: old-12+3 L Promo | C452: 15 L | D452: 15 | E452: L | F452: =VLOOKUP(E452,$P$6:$Q$9,2,0) -> 1 | G452: =D452*F452 -> 15 | H452: SMALL | I452: 0.015
... A507: 89 | B507: 12 X 1.8L | C507: 1.8 L | D507: 1.8 | E507: L | F507: =VLOOKUP(E507,$P$6:$Q$9,2,0) -> 1 | G507: =D507*F507 -> 1.8 | H507: SMALL | I507: 0.0216
A508: 97 | B508: 12 X 2L | C508: 2 L | D508: 2 | E508: L | F508: =VLOOKUP(E508,$P$6:$Q$9,2,0) -> 1 | G508: =D508*F508 -> 2 | H508: SMALL | I508: =0.024 -> 0.024
A509: 48 | B509: 310 ml | C509: 310 ML | D509: 310 | E509: ML | F509: =VLOOKUP(E509,$P$6:$Q$9,2,0) -> 0.001 | G509: =D509*F509 -> 0.31 | H509: SMALL | I509: 0.00031
A510: 49 | B510: 12 X 310 ML | C510: 310 ML | D510: 310 | E510: ML | F510: =VLOOKUP(E510,$P$6:$Q$9,2,0) -> 0.001 | G510: =D510*F510 -> 0.31 | H510: SMALL | I510: 0.00372
A511: 24 | B511: 10X1.2L | C511: 1.2 L | D511: 1.2 | E511: L | F511: =VLOOKUP(E511,$P$6:$Q$9,2,0) -> 1 | G511: =D511*F511 -> 1.2 | H511: SMALL | I511: 0.012
A512: 91 | B512: 10X1.35 L | C512: 1.35 L | D512: 1.35 | E512: L | F512: =VLOOKUP(E512,$P$6:$Q$9,2,0) -> 1 | G512: =D512*F512 -> 1.35 | H512: SMALL | I512: 0.0135
A513: 22 | B513: 10X1.2L | C513: 1.2 L | D513: 1.2 | E513: L | F513: =VLOOKUP(E513,$P$6:$Q$9,2,0) -> 1 | G513: =D513*F513 -> 1.2 | H513: SMALL | I513: 0.012
A514: 30 | B514: 4 X 2.8 L | C514: 2.8 L | D514: 2.8 | E514: L | F514: 1 | G514: 2.8 | H514: SMALL | I514: 0.0112
A515: 52 | B515: 12 L HDPE | C515: 12 L | D515: 12 | E515: L | F515: 1 | G515: 12 | H515: SMALL | I515: 0.012
A516: 51 | B516: 6 L HDPE | C516: 6 L | D516: 6 | E516: L | F516: 1 | G516: 6 | H516: SMALL | I516: 0.006
A517: 36 | B517: 20 X 0.6 L Promo | C517: 0.6 L | D517: 0.6 | E517: L | F517: 1 | G517: 0.6 | H517: SMALL | I517: 0.012

Sheet BARREL
A1: Material | C1: Material Description | D1: Item Size in L | E1: MRP | F1: DLP conv | G1: DLP | H1: RSP/L | I1: HO DISC/L | J1: MSS1/L | K1: MSS/L | L1: TOTAL DISCOUNT/L | M1: DISCOUNTED RSP/L | N1: EDLP/L | O1: EDLP/BRL or BUC | P1: Stockist Discount % | Q1: Stockist Discount/ITEM | R1: Cash Discount | S1: Cash Discount/ITEM | T1: PRODU | U1: Stockist Discount/L | V1: Cash Discount/L
A2: 1301288 | B2: 288 | C2: SERVO ULTRA 10W-26 L | D2: =VLOOKUP($B2,'PACK MASTER'!$A$2:$G$512,7,0) -> 26 | H2: =VLOOKUP($A2,ZAVL!$C$2:$F$1048576,4,0) -> 195 | I2: =IFERROR(ABS(VLOOKUP($A2,ZTRV!$D$2:$G$1048576,4,0)),0) -> 8 | J2: =IFERROR(ABS(VLOOKUP(A2,ZTR1!$D$2:$G$829999,4,0)),0) -> 0 | K2: =IFERROR(ABS(VLOOKUP(A2,ZTR2!$D$2:$G$59939,4,0)),0) -> 0 | L2: =SUM(I2:K2) -> 8 | M2: =H2-L2 -> 187 | N2: =M2*1.18 -> 220.66 | O2: =N2*D2 -> 5737.16 | P2: =IF(A2=3040288,0,IFERROR(ABS(VLOOKUP(A2,ZCON!$D$2:$G$128870,4,0)),5.5)) -> 5.5 | Q2: =P2*H2*D2/100 -> 278.85 | R2: 0.02 | S2: =1.5%*(H2*D2-Q2) -> 71.86725 | T2: =VALUE(LEFT(A2,4)) -> 1301 | U2: =+Q2/D2 -> 10.725 | V2: =+S2/D2 -> 2.764125
A3: 1301401 | B3: 401 | C3: SERVO ULTRA 10W - 210L BRL | D3: =VLOOKUP($B3,'PACK MASTER'!$A$2:$G$512,7,0) -> 210 | H3: =VLOOKUP($A3,ZAVL!$C$2:$F$1048576,4,0) -> 191 | I3: =IFERROR(ABS(VLOOKUP($A3,ZTRV!$D$2:$G$1048576,4,0)),0) -> 8 | J3: =IFERROR(ABS(VLOOKUP(A3,ZTR1!$D$2:$G$829999,4,0)),0) -> 0 | K3: =IFERROR(ABS(VLOOKUP(A3,ZTR2!$D$2:$G$59939,4,0)),0) -> 0 | L3: =SUM(I3:K3) -> 8 | M3: =H3-L3 -> 183 | N3: =M3*1.18 -> 215.94 | O3: =N3*D3 -> 45347.4 | P3: =IF(A3=3040288,0,IFERROR(ABS(VLOOKUP(A3,ZCON!$D$2:$G$128870,4,0)),5.5)) -> 5.5 | Q3: =P3*H3*D3/100 -> 2206.05 | R3: 0.02 | S3: =1.5%*(H3*D3-Q3) -> 568.55925 | T3: =VALUE(LEFT(A3,4)) -> 1301 | U3: =+Q3/D3 -> 10.505 | V3: =+S3/D3 -> 2.707425
A4: 1303401 | B4: 401 | C4: SERVO ULTRA 30 - 210L BRL | D4: =VLOOKUP($B4,'PACK MASTER'!$A$2:$G$512,7,0) -> 210 | H4: =VLOOKUP($A4,ZAVL!$C$2:$F$1048576,4,0) -> 202 | I4: =IFERROR(ABS(VLOOKUP($A4,ZTRV!$D$2:$G$1048576,4,0)),0) -> 8 | J4: =IFERROR(ABS(VLOOKUP(A4,ZTR1!$D$2:$G$829999,4,0)),0) -> 0 | K4: =IFERROR(ABS(VLOOKUP(A4,ZTR2!$D$2:$G$59939,4,0)),0) -> 0 | L4: =SUM(I4:K4) -> 8 | M4: =H4-L4 -> 194 | N4: =M4*1.18 -> 228.92 | O4: =N4*D4 -> 48073.2 | P4: =IF(A4=3040288,0,IFERROR(ABS(VLOOKUP(A4,ZCON!$D$2:$G$128870,4,0)),5.5)) -> 5.5 | Q4: =P4*H4*D4/100 -> 2333.1 | R4: 0.02 | S4: =1.5%*(H4*D4-Q4) -> 601.3035 | T4: =VALUE(LEFT(A4,4)) -> 1303 | U4: =+Q4/D4 -> 11.11 | V4: =+S4/D4 -> 2.86335
A5: 1304401 | B5: 401 | C5: SERVO ULTRA 40 - 210L BRL | D5: =VLOOKUP($B5,'PACK MASTER'!$A$2:$G$512,7,0) -> 210 | H5: =VLOOKUP($A5,ZAVL!$C$2:$F$1048576,4,0) -> 208 | I5: =IFERROR(ABS(VLOOKUP($A5,ZTRV!$D$2:$G$1048576,4,0)),0) -> 8 | J5: =IFERROR(ABS(VLOOKUP(A5,ZTR1!$D$2:$G$829999,4,0)),0) -> 0 | K5: =IFERROR(ABS(VLOOKUP(A5,ZTR2!$D$2:$G$59939,4,0)),0) -> 0 | L5: =SUM(I5:K5) -> 8 | M5: =H5-L5 -> 200 | N5: =M5*1.18 -> 236 | O5: =N5*D5 -> 49560 | P5: =IF(A5=3040288,0,IFERROR(ABS(VLOOKUP(A5,ZCON!$D$2:$G$128870,4,0)),5.5)) -> 5.5 | Q5: =P5*H5*D5/100 -> 2402.4 | R5: 0.02 | S5: =1.5%*(H5*D5-Q5) -> 619.164 | T5: =VALUE(LEFT(A5,4)) -> 1304 | U5: =+Q5/D5 -> 11.44 | V5: =+S5/D5 -> 2.9484
A6: 1403401 | B6: 401 | C6: SERVO PRIDE 30 - 210L BRL | D6: =VLOOKUP($B6,'PACK MASTER'!$A$2:$G$512,7,0) -> 210 | H6: =VLOOKUP($A6,ZAVL!$C$2:$F$1048576,4,0) -> 223 | I6: =IFERROR(ABS(VLOOKUP($A6,ZTRV!$D$2:$G$1048576,4,0)),0) -> 8 | J6: =IFERROR(ABS(VLOOKUP(A6,ZTR1!$D$2:$G$829999,4,0)),0) -> 0 | K6: =IFERROR(ABS(VLOOKUP(A6,ZTR2!$D$2:$G$59939,4,0)),0) -> 0 | L6: =SUM(I6:K6) -> 8 | M6: =H6-L6 -> 215 | N6: =M6*1.18 -> 253.7 | O6: =N6*D6 -> 53277 | P6: =IF(A6=3040288,0,IFERROR(ABS(VLOOKUP(A6,ZCON!$D$2:$G$128870,4,0)),5.5)) -> 5.5 | Q6: =P6*H6*D6/100 -> 2575.65 | R6: 0.02 | S6: =1.5%*(H6*D6-Q6) -> 663.81525 | T6: =VALUE(LEFT(A6,4)) -> 1403 | U6: =+Q6/D6 -> 12.265 | V6: =+S6/D6 -> 3.161025
A7: 1404271 | B7: 271 | C7: SERVO PRIDE 40 - 50L HDPE DRUM | D7: =VLOOKUP($B7,'PACK MASTER'!$A$2:$G$512,7,0) -> 50 | H7: =VLOOKUP($A7,ZAVL!$C$2:$F$1048576,4,0) -> 231 | I7: =IFERROR(ABS(VLOOKUP($A7,ZTRV!$D$2:$G$1048576,4,0)),0) -> 8 | J7: =IFERROR(ABS(VLOOKUP(A7,ZTR1!$D$2:$G$829999,4,0)),0) -> 0 | K7: =IFERROR(ABS(VLOOKUP(A7,ZTR2!$D$2:$G$59939,4,0)),0) -> 0 | L7: =SUM(I7:K7) -> 8 | M7: =H7-L7 -> 223 | N7: =M7*1.18 -> 263.14 | O7: =N7*D7 -> 13157 | P7: =IF(A7=3040288,0,IFERROR(ABS(VLOOKUP(A7,ZCON!$D$2:$G$128870,4,0)),5.5)) -> 5.5 | Q7: =P7*H7*D7/100 -> 635.25 | R7: 0.02 | S7: =1.5%*(H7*D7-Q7) -> 163.72125 | T7: =VALUE(LEFT(A7,4)) -> 1404 | U7: =+Q7/D7 -> 12.705 | V7: =+S7/D7 -> 3.274425
